Workbook
Name Céglista: Cégek[[#All],[Vevő név]]
Name Termekek: Terméklista!$A:$P
Name Vevő_név: Céglista!$A$2:$A$13

Sheet Új feladat
A1: Új | B1: Rendelés
A3: Customer | B3: Termék neve | C3: Megnevezése | D3: Megjegyzés | E3: Saját rendelési szám | F3: Anyag | G3: Rendelési szám | H3: Amount/pc | I3: Order date (y/m/) | J3: Required delivery date (y/m/d)
F4: =IFERROR(IF(_xlfn.XLOOKUP(B4,Terméklista!$B$2:$B$103,Terméklista!$G$2:$G$103)="","",_xlfn.XLOOKUP(B4,Terméklista!$B$2:$B$103,Terméklista!$G$2:$G$103)),"")
F5: =IFERROR(IF(_xlfn.XLOOKUP(B5,Terméklista!$B$2:$B$103,Terméklista!$G$2:$G$103)="","",_xlfn.XLOOKUP(B5,Terméklista!$B$2:$B$103,Terméklista!$G$2:$G$103)),"")
F6: =IFERROR(IF(_xlfn.XLOOKUP(B6,Terméklista!$B$2:$B$103,Terméklista!$G$2:$G$103)="","",_xlfn.XLOOKUP(B6,Terméklista!$B$2:$B$103,Terméklista!$G$2:$G$103)),"")
F7: =IFERROR(IF(_xlfn.XLOOKUP(B7,Terméklista!$B$2:$B$103,Terméklista!$G$2:$G$103)="","",_xlfn.XLOOKUP(B7,Terméklista!$B$2:$B$103,Terméklista!$G$2:$G$103)),"")
F8: =IFERROR(IF(_xlfn.XLOOKUP(B8,Terméklista!$B$2:$B$103,Terméklista!$G$2:$G$103)="","",_xlfn.XLOOKUP(B8,Terméklista!$B$2:$B$103,Terméklista!$G$2:$G$103)),"")
F9: =IFERROR(IF(_xlfn.XLOOKUP(B9,Terméklista!$B$2:$B$103,Terméklista!$G$2:$G$103)="","",_xlfn.XLOOKUP(B9,Terméklista!$B$2:$B$103,Terméklista!$G$2:$G$103)),"")
F10: =IFERROR(IF(_xlfn.XLOOKUP(B10,Terméklista!$B$2:$B$103,Terméklista!$G$2:$G$103)="","",_xlfn.XLOOKUP(B10,Terméklista!$B$2:$B$103,Terméklista!$G$2:$G$103)),"")
F11: =IFERROR(IF(_xlfn.XLOOKUP(B11,Terméklista!$B$2:$B$103,Terméklista!$G$2:$G$103)="","",_xlfn.XLOOKUP(B11,Terméklista!$B$2:$B$103,Terméklista!$G$2:$G$103)),"")
A13: Meglévő | B13: Rendelés
A15: Customer | B15: Termék neve | C15: Megnevezése | D15: Megjegyzés | E15: Saját rendelési szám | F15: Anyag | G15: Rendelési szám | H15: Amount/pc | I15: Order date (y/m/) | J15: Required delivery date (y/m/d)
A21: Új | B21: Termék
A22: Ügyfél | B22: Termék megnevezés | C22: Termék rajzszáma | D22: Megjegyzés | E22: Fészekszáma | F22: Súly/db g | G22: Anyag | H22: Felületkezelés | I22: Ciklus idő | J22: Utómunka idő | K22: Utómunkák | L22: Doboz méret | M22: Doboz/db | N22: Doboz/Raklap | O22: Arktikál nr. | P22: Raktár | Q22: Engusz súly
A27: Új | B27: Cég
A29: Vevő név | B29: Szállító Nyelve | C29: Város | D29: Irányítószám | E29: Utca, házszám | F29: Ország | G29: Cím | H29: Adószám | I29: Vevő név
G30: =CONCATENATE(D30," ",C30,", ",E30) -> ,

Sheet Rendelés
A1: Megrendelési információ | R1: =SUM(Rendelés[Szükséges anyagmennyiség]) -> #N/A
A2: Customer | B2: Termék neve | C2: Megnevezése | D2: Megjegyzés | E2: Saját rendelési szám | F2: Anyag | G2: Rendelési szám | H2: Amount/pc | I2: Order date (year/month/day) | J2: Required delivery date (year/month/day) | K2: Actual pickup date (year/month/day) | L2: Számlázva (x) | M2: Szállításra kész | N2: Felületkezelés | O2: Dobozok száma | P2: Össz raklapok száma | Q2: Össz bruttó súly | R2: Szükséges anyagmennyiség | S2: Tervezett gyártási idő | T2: Szállítólevél | U2: Státusz
A3: Systec Pos-Technology Gmbh | B3: Smartstop-2 Rasthebel-2 | C3: =IFERROR(_xlfn.XLOOKUP(B3,Terméklista!$B$2:$B$103,Terméklista!$C$2:$C$103,)," ") | E3: M251001 | F3: =_xlfn.XLOOKUP(B3,Terméklista!$B$2:$B$103,Terméklista!$G$2:$G$103," ") | G3: 26287 | H3: 10000 | I3: 2024-11-18 | J3: 2025-01-28 | K3: 2025-01-21 | L3: x | N3: =IFERROR(_xlfn.XLOOKUP(B3,Terméklista!B2:B103,Terméklista!H2:H103)," ") | O3: =IFERROR(ROUNDUP(Rendelés[[#This Row],[Amount/pc]]/_xlfn.XLOOKUP(B3,Terméklista!$B$2:$B$103,Terméklista!$M$2:$M$103,),0)," ") | P3: =IFERROR(ROUNDUP(Rendelés[[#This Row],[Dobozok száma]]/_xlfn.XLOOKUP(B3,Terméklista!$B$2:$B$103,Terméklista!$N$2:$N$103,),0)," ") | Q3: =IFERROR(Rendelés[[#This Row],[Szükséges anyagmennyiség]]+(Rendelés[[#This Row],[Össz raklapok száma]]*25),"") | R3: {=(H3*_xlfn.XLOOKUP(B3,Terméklista!$B$2:$B$103,Terméklista!F$2:$F$103,))/1000} -> #N/A | S3: =IFERROR(((H3/_xlfn.XLOOKUP(B3,Terméklista!$B$2:$B$103,Terméklista!$E$2:$E$103)*_xlfn.XLOOKUP(B3,Terméklista!$B$2:$B$103,Terméklista!$I$2:$I$103)))/3600," ")
A4: Seidel Gmbh&co Kg | B4: MA41 | C4: =IFERROR(_xlfn.XLOOKUP(B4,Terméklista!$B$2:$B$103,Terméklista!$C$2:$C$103,)," ") -> Zamak Gewicht | E4: M251017 | F4: =_xlfn.XLOOKUP(B4,Terméklista!$B$2:$B$103,Terméklista!$G$2:$G$103," ") -> Z410 | G4: 4500099245 | H4: 75000 | I4: 2024-11-25 | J4: 2025-02-03 | K4: 2025-02-18 | L4: x | N4: =IFERROR(_xlfn.XLOOKUP(B4,Terméklista!B18:B119,Terméklista!H18:H119)," ") -> 0 | O4: =IFERROR(ROUNDUP(Rendelés[[#This Row],[Amount/pc]]/_xlfn.XLOOKUP(B4,Terméklista!$B$2:$B$103,Terméklista!$M$2:$M$103,),0)," ") -> 215 | P4: =IFERROR(ROUNDUP(Rendelés[[#This Row],[Dobozok száma]]/_xlfn.XLOOKUP(B4,Terméklista!$B$2:$B$103,Terméklista!$N$2:$N$103,),0)," ") -> 3 | Q4: =IFERROR(Rendelés[[#This Row],[Szükséges anyagmennyiség]]+(Rendelés[[#This Row],[Össz raklapok száma]]*25),"") -> 1350 | R4: {=(H4*_xlfn.XLOOKUP(B4,Terméklista!$B$2:$B$103,Terméklista!F$2:$F$103,))/1000} -> 1275 | S4: =IFERROR(((H4/_xlfn.XLOOKUP(B4,Terméklista!$B$2:$B$103,Terméklista!$E$2:$E$103)*_xlfn.XLOOKUP(B4,Terméklista!$B$2:$B$103,Terméklista!$I$2:$I$103)))/3600," ") -> 52.083333
A5: Seidel Gmbh&co Kg | B5: MA66 | C5: =IFERROR(_xlfn.XLOOKUP(B5,Terméklista!$B$2:$B$103,Terméklista!$C$2:$C$103,)," ") -> Zamak Gewicht | E5: M251002 | F5: =_xlfn.XLOOKUP(B5,Terméklista!$B$2:$B$103,Terméklista!$G$2:$G$103," ") -> Z410 | G5: 4500099503 | H5: 100000 | I5: 2024-12-12 | J5: 2025-02-13 | K5: 2025-03-06 | L5: x | N5: =IFERROR(_xlfn.XLOOKUP(B5,Terméklista!B3:B104,Terméklista!H3:H104)," ") -> 0 | O5: =IFERROR(ROUNDUP(Rendelés[[#This Row],[Amount/pc]]/_xlfn.XLOOKUP(B5,Terméklista!$B$2:$B$103,Terméklista!$M$2:$M$103,),0)," ") -> 200 | P5: =IFERROR(ROUNDUP(Rendelés[[#This Row],[Dobozok száma]]/_xlfn.XLOOKUP(B5,Terméklista!$B$2:$B$103,Terméklista!$N$2:$N$103,),0)," ") -> 3 | Q5: =IFERROR(Rendelés[[#This Row],[Szükséges anyagmennyiség]]+(Rendelés[[#This Row],[Össz raklapok száma]]*25),"") -> 1125 | R5: {=(H5*_xlfn.XLOOKUP(B5,Terméklista!$B$2:$B$103,Terméklista!F$2:$F$103,))/1000} -> 1050 | S5: =IFERROR(((H5/_xlfn.XLOOKUP(B5,Terméklista!$B$2:$B$103,Terméklista!$E$2:$E$103)*_xlfn.XLOOKUP(B5,Terméklista!$B$2:$B$103,Terméklista!$I$2:$I$103)))/3600," ") -> 69.444444
A6: Seidel Gmbh&co Kg | B6: MA41 | C6: =IFERROR(_xlfn.XLOOKUP(B6,Terméklista!$B$2:$B$103,Terméklista!$C$2:$C$103,)," ") -> Zamak Gewicht | E6: M251003 | F6: =_xlfn.XLOOKUP(B6,Terméklista!$B$2:$B$103,Terméklista!$G$2:$G$103," ") -> Z410 | G6: 4500099546 | H6: 50000 | I6: 2024-12-16 | J6: 2025-03-31 | L6: x | N6: =IFERROR(_xlfn.XLOOKUP(B6,Terméklista!B4:B105,Terméklista!H4:H105)," ") -> 0 | O6: =IFERROR(ROUNDUP(Rendelés[[#This Row],[Amount/pc]]/_xlfn.XLOOKUP(B6,Terméklista!$B$2:$B$103,Terméklista!$M$2:$M$103,),0)," ") -> 143 | P6: =IFERROR(ROUNDUP(Rendelés[[#This Row],[Dobozok száma]]/_xlfn.XLOOKUP(B6,Terméklista!$B$2:$B$103,Terméklista!$N$2:$N$103,),0)," ") -> 2 | Q6: =IFERROR(Rendelés[[#This Row],[Szükséges anyagmennyiség]]+(Rendelés[[#This Row],[Össz raklapok száma]]*25),"") -> 900 | R6: {=(H6*_xlfn.XLOOKUP(B6,Terméklista!$B$2:$B$103,Terméklista!F$2:$F$103,))/1000} -> 850 | S6: =IFERROR(((H6/_xlfn.XLOOKUP(B6,Terméklista!$B$2:$B$103,Terméklista!$E$2:$E$103)*_xlfn.XLOOKUP(B6,Terméklista!$B$2:$B$103,Terméklista!$I$2:$I$103)))/3600," ") -> 34.722222 | T6: 2025/23
A7: Ela Solutions Kft. | B7: 90ZA-ZK011-06 | C7: =IFERROR(_xlfn.XLOOKUP(B7,Terméklista!$B$2:$B$103,Terméklista!$C$2:$C$103,)," ") -> nagykulcs - 3mm | E7: M251004 | F7: =_xlfn.XLOOKUP(B7,Terméklista!$B$2:$B$103,Terméklista!$G$2:$G$103," ") -> Z410 | G7: 5491 | H7: 1000 | I7: 2025-01-06 | J7: 2025-01-08 | K7: 2025-01-09 | L7: x | N7: =IFERROR(_xlfn.XLOOKUP(B7,Terméklista!B5:B106,Terméklista!H5:H106)," ") -> 0 | O7: =IFERROR(ROUNDUP(Rendelés[[#This Row],[Amount/pc]]/_xlfn.XLOOKUP(B7,Terméklista!$B$2:$B$103,Terméklista!$M$2:$M$103,),0)," ") | P7: =IFERROR(ROUNDUP(Rendelés[[#This Row],[Dobozok száma]]/_xlfn.XLOOKUP(B7,Terméklista!$B$2:$B$103,Terméklista!$N$2:$N$103,),0)," ") | Q7: =IFERROR(Rendelés[[#This Row],[Szükséges anyagmennyiség]]+(Rendelés[[#This Row],[Össz raklapok száma]]*25),"") | R7: {=(H7*_xlfn.XLOOKUP(B7,Terméklista!$B$2:$B$103,Terméklista!F$2:$F$103,))/1000} -> 47.55 | S7: =IFERROR(((H7/_xlfn.XLOOKUP(B7,Terméklista!$B$2:$B$103,Terméklista!$E$2:$E$103)*_xlfn.XLOOKUP(B7,Terméklista!$B$2:$B$103,Terméklista!$I$2:$I$103)))/3600," ") -> 2.0833333
A8: Ela Solutions Kft. | B8: 90ZA-ZK011-06 | C8: =IFERROR(_xlfn.XLOOKUP(B8,Terméklista!$B$2:$B$103,Terméklista!$C$2:$C$103,)," ") -> nagykulcs - 3mm | E8: M251005 | F8: =_xlfn.XLOOKUP(B8,Terméklista!$B$2:$B$103,Terméklista!$G$2:$G$103," ") -> Z410 | G8: 5505 | H8: 1500 | I8: 2025-01-13 | J8: 2025-02-03 | K8: 2025-02-03 | L8: x | N8: =IFERROR(_xlfn.XLOOKUP(B8,Terméklista!B6:B107,Terméklista!H6:H107)," ") -> 0 | O8: =IFERROR(ROUNDUP(Rendelés[[#This Row],[Amount/pc]]/_xlfn.XLOOKUP(B8,Terméklista!$B$2:$B$103,Terméklista!$M$2:$M$103,),0)," ") | P8: =IFERROR(ROUNDUP(Rendelés[[#This Row],[Dobozok száma]]/_xlfn.XLOOKUP(B8,Terméklista!$B$2:$B$103,Terméklista!$N$2:$N$103,),0)," ") | Q8: =IFERROR(Rendelés[[#This Row],[Szükséges anyagmennyiség]]+(Rendelés[[#This Row],[Össz raklapok száma]]*30),"") | R8: {=(H8*_xlfn.XLOOKUP(B8,Terméklista!$B$2:$B$103,Terméklista!F$2:$F$103,))/1000} -> 71.325 | S8: =IFERROR(((H8/_xlfn.XLOOKUP(B8,Terméklista!$B$2:$B$103,Terméklista!$E$2:$E$103)*_xlfn.XLOOKUP(B8,Terméklista!$B$2:$B$103,Terméklista!$I$2:$I$103)))/3600," ") -> 3.125
A9: Seidel Gmbh&co Kg | B9: M83 | C9: =IFERROR(_xlfn.XLOOKUP(B9,Terméklista!$B$2:$B$103,Terméklista!$C$2:$C$103,)," ") -> Zamak Gewicht | E9: M251006 | F9: =_xlfn.XLOOKUP(B9,Terméklista!$B$2:$B$103,Terméklista!$G$2:$G$103," ") -> Z410 | G9: 4500099767 | H9: 70000 | I9: 2025-01-14 | J9: 2025-04-02 | K9: 2025-04-03 | L9: x | N9: =IFERROR(_xlfn.XLOOKUP(B9,Terméklista!B7:B108,Terméklista!H7:H108)," ") -> 0 | O9: =IFERROR(ROUNDUP(Rendelés[[#This Row],[Amount/pc]]/_xlfn.XLOOKUP(B9,Terméklista!$B$2:$B$103,Terméklista!$M$2:$M$103,),0)," ") -> 467 | P9: =IFERROR(ROUNDUP(Rendelés[[#This Row],[Dobozok száma]]/_xlfn.XLOOKUP(B9,Terméklista!$B$2:$B$103,Terméklista!$N$2:$N$103,),0)," ") -> 16 | Q9: =IFERROR(Rendelés[[#This Row],[Szükséges anyagmennyiség]]+(Rendelés[[#This Row],[Össz raklapok száma]]*30),"") -> 5051 | R9: {=(H9*_xlfn.XLOOKUP(B9,Terméklista!$B$2:$B$103,Terméklista!F$2:$F$103,))/1000} -> 4571 | S9: =IFERROR(((H9/_xlfn.XLOOKUP(B9,Terméklista!$B$2:$B$103,Terméklista!$E$2:$E$103)*_xlfn.XLOOKUP(B9,Terméklista!$B$2:$B$103,Terméklista!$I$2:$I$103)))/3600," ") -> 97.222222 | T9: 2025/27
A10: Arsisco AMO Pack LLC | B10: Fehér hüvely | C10: =IFERROR(_xlfn.XLOOKUP(B10,Terméklista!$B$2:$B$103,Terméklista!$C$2:$C$103,)," ") -> 0 | E10: M251007 | F10: =_xlfn.XLOOKUP(B10,Terméklista!$B$2:$B$103,Terméklista!$G$2:$G$103," ") -> Műanyag | G10: email: 21.01.2025 | H10: 360000 | I10: 2025-01-21 | J10: 2025-02-28 | K10: 2025-06-10 | L10: x | N10: =_xlfn.XLOOKUP(J10,Terméklista!$B$2:$B$103,Terméklista!$H$2:$H$103," ") | O10: =IFERROR(ROUNDUP(Rendelés[[#This Row],[Amount/pc]]/_xlfn.XLOOKUP(B10,Terméklista!$B$2:$B$103,Terméklista!$M$2:$M$103,),0)," ") | P10: =IFERROR(ROUNDUP(Rendelés[[#This Row],[Dobozok száma]]/_xlfn.XLOOKUP(B10,Terméklista!$B$2:$B$103,Terméklista!$N$2:$N$103,),0)," ") | Q10: =IFERROR(Rendelés[[#This Row],[Szükséges anyagmennyiség]]+(Rendelés[[#This Row],[Össz raklapok száma]]*25),"") | R10: {=(H10*_xlfn.XLOOKUP(B10,Terméklista!$B$2:$B$203,Terméklista!F$2:$F$203,))/1000} -> 81 | S10: =IFERROR(((H10/_xlfn.XLOOKUP(B10,Terméklista!$B$2:$B$103,Terméklista!$E$2:$E$103)*_xlfn.XLOOKUP(B10,Terméklista!$B$2:$B$103,Terméklista!$I$2:$I$103)))/3600," ") -> 325
A11: Ela Solutions Kft. | B11: 90ZA-B0011-06 | C11: =IFERROR(_xlfn.XLOOKUP(B11,Terméklista!$B$2:$B$103,Terméklista!$C$2:$C$103,)," ") -> 0 | E11: M251008 | F11: =_xlfn.XLOOKUP(B11,Terméklista!$B$2:$B$103,Terméklista!$G$2:$G$103," ") -> Z410 | G11: 5526 | H11: 150 | I11: 2025-01-21 | J11: 2025-01-22 | K11: 2025-01-22 | L11: x | N11: =IFERROR(_xlfn.XLOOKUP(B11,Terméklista!B9:B110,Terméklista!H9:H110)," ") -> 0 | O11: =IFERROR(ROUNDUP(Rendelés[[#This Row],[Amount/pc]]/_xlfn.XLOOKUP(B11,Terméklista!$B$2:$B$103,Terméklista!$M$2:$M$103,),0)," ") | P11: =IFERROR(ROUNDUP(Rendelés[[#This Row],[Dobozok száma]]/_xlfn.XLOOKUP(B11,Terméklista!$B$2:$B$103,Terméklista!$N$2:$N$103,),0)," ") | Q11: =IFERROR(Rendelés[[#This Row],[Szükséges anyagmennyiség]]+(Rendelés[[#This Row],[Össz raklapok száma]]*25),"") | R11: {=(H11*_xlfn.XLOOKUP(B11,Terméklista!$B$2:$B$103,Terméklista!F$2:$F$103,))/1000} -> 0.4335 | S11: =IFERROR(((H11/_xlfn.XLOOKUP(B11,Terméklista!$B$2:$B$103,Terméklista!$E$2:$E$103)*_xlfn.XLOOKUP(B11,Terméklista!$B$2:$B$103,Terméklista!$I$2:$I$103)))/3600," ") | T11: 2025/24
A12: Ela Solutions Kft. | B12: 90ZA-ZK001-06 | C12: =IFERROR(_xlfn.XLOOKUP(B12,Terméklista!$B$2:$B$103,Terméklista!$C$2:$C$103,)," ") -> 0 | E12: M251009 | F12: =_xlfn.XLOOKUP(B12,Terméklista!$B$2:$B$103,Terméklista!$G$2:$G$103," ") -> Z410 | G12: 5526 | H12: 500 | I12: 2025-01-21 | J12: 2025-01-22 | K12: 2025-01-22 | L12: x | N12: =IFERROR(_xlfn.XLOOKUP(B12,Terméklista!B10:B111,Terméklista!H10:H111)," ") -> 0 | O12: =IFERROR(ROUNDUP(Rendelés[[#This Row],[Amount/pc]]/_xlfn.XLOOKUP(B12,Terméklista!$B$2:$B$103,Terméklista!$M$2:$M$103,),0)," ") | P12: =IFERROR(ROUNDUP(Rendelés[[#This Row],[Dobozok száma]]/_xlfn.XLOOKUP(B12,Terméklista!$B$2:$B$103,Terméklista!$N$2:$N$103,),0)," ") | Q12: =IFERROR(Rendelés[[#This Row],[Szükséges anyagmennyiség]]+(Rendelés[[#This Row],[Össz raklapok száma]]*25),"") | R12: {=(H12*_xlfn.XLOOKUP(B12,Terméklista!$B$2:$B$103,Terméklista!F$2:$F$103,))/1000} -> 11.17 | S12: =IFERROR(((H12/_xlfn.XLOOKUP(B12,Terméklista!$B$2:$B$103,Terméklista!$E$2:$E$103)*_xlfn.XLOOKUP(B12,Terméklista!$B$2:$B$103,Terméklista!$I$2:$I$103)))/3600," ") -> 1.0416667
A13: Ela Solutions Kft. | B13: 90ZA-ZS001-06 | C13: =IFERROR(_xlfn.XLOOKUP(B13,Terméklista!$B$2:$B$103,Terméklista!$C$2:$C$103,)," ") -> Zsanérbelső | E13: M251010 | F13: =_xlfn.XLOOKUP(B13,Terméklista!$B$2:$B$103,Terméklista!$G$2:$G$103," ") -> Z410 | G13: 5526 | H13: 1000 | I13: 2025-01-21 | J13: 2025-01-22 | K13: 2025-01-22 | L13: x | N13: =IFERROR(_xlfn.XLOOKUP(B13,Terméklista!B11:B112,Terméklista!H11:H112)," ") -> 0 | O13: =IFERROR(ROUNDUP(Rendelés[[#This Row],[Amount/pc]]/_xlfn.XLOOKUP(B13,Terméklista!$B$2:$B$103,Terméklista!$M$2:$M$103,),0)," ") | P13: =IFERROR(ROUNDUP(Rendelés[[#This Row],[Dobozok száma]]/_xlfn.XLOOKUP(B13,Terméklista!$B$2:$B$103,Terméklista!$N$2:$N$103,),0)," ") | Q13: =IFERROR(Rendelés[[#This Row],[Szükséges anyagmennyiség]]+(Rendelés[[#This Row],[Össz raklapok száma]]*25),"") | R13: {=(H13*_xlfn.XLOOKUP(B13,Terméklista!$B$2:$B$103,Terméklista!F$2:$F$103,))/1000} -> 15 | S13: =IFERROR(((H13/_xlfn.XLOOKUP(B13,Terméklista!$B$2:$B$103,Terméklista!$E$2:$E$103)*_xlfn.XLOOKUP(B13,Terméklista!$B$2:$B$103,Terméklista!$I$2:$I$103)))/3600," ") -> 2.0833333
A14: Ela Solutions Kft. | B14: 90ZA-ZS002-06 | C14: =IFERROR(_xlfn.XLOOKUP(B14,Terméklista!$B$2:$B$103,Terméklista!$C$2:$C$103,)," ") -> Zsanérkülső | E14: M251011 | F14: =_xlfn.XLOOKUP(B14,Terméklista!$B$2:$B$103,Terméklista!$G$2:$G$103," ") -> Z410 | G14: 5526 | H14: 1000 | I14: 2025-01-21 | J14: 2025-01-22 | K14: 2025-01-22 | L14: x | N14: =IFERROR(_xlfn.XLOOKUP(B14,Terméklista!B12:B113,Terméklista!H12:H113)," ") -> 0 | O14: =IFERROR(ROUNDUP(Rendelés[[#This Row],[Amount/pc]]/_xlfn.XLOOKUP(B14,Terméklista!$B$2:$B$103,Terméklista!$M$2:$M$103,),0)," ") | P14: =IFERROR(ROUNDUP(Rendelés[[#This Row],[Dobozok száma]]/_xlfn.XLOOKUP(B14,Terméklista!$B$2:$B$103,Terméklista!$N$2:$N$103,),0)," ") | Q14: =IFERROR(Rendelés[[#This Row],[Szükséges anyagmennyiség]]+(Rendelés[[#This Row],[Össz raklapok száma]]*25),"") | R14: {=(H14*_xlfn.XLOOKUP(B14,Terméklista!$B$2:$B$103,Terméklista!F$2:$F$103,))/1000} -> 20.8 | S14: =IFERROR(((H14/_xlfn.XLOOKUP(B14,Terméklista!$B$2:$B$103,Terméklista!$E$2:$E$103)*_xlfn.XLOOKUP(B14,Terméklista!$B$2:$B$103,Terméklista!$I$2:$I$103)))/3600," ") -> 2.0833333 | T14: 2025/22
A15: Arsisco AMO Pack LLC | B15: Fehér hüvely | C15: =IFERROR(_xlfn.XLOOKUP(B15,Terméklista!$B$2:$B$103,Terméklista!$C$2:$C$103,)," ") -> 0 | E15: M251031 | F15: =_xlfn.XLOOKUP(B15,Terméklista!$B$2:$B$103,Terméklista!$G$2:$G$103," ") -> Műanyag | G15: email: 21.01.2025 | H15: 140000 | I15: 2025-01-21 | K15: 2025-03-19 | L15: x | N15: =IFERROR(_xlfn.XLOOKUP(B15,Terméklista!B32:B133,Terméklista!H32:H133)," ") | O15: =IFERROR(ROUNDUP(Rendelés[[#This Row],[Amount/pc]]/_xlfn.XLOOKUP(B15,Terméklista!$B$2:$B$103,Terméklista!$M$2:$M$103,),0)," ") | P15: =IFERROR(ROUNDUP(Rendelés[[#This Row],[Dobozok száma]]/_xlfn.XLOOKUP(B15,Terméklista!$B$2:$B$103,Terméklista!$N$2:$N$103,),0)," ") | Q15: =IFERROR(Rendelés[[#This Row],[Szükséges anyagmennyiség]]+(Rendelés[[#This Row],[Össz raklapok száma]]*25),"") | R15: {=(H15*_xlfn.XLOOKUP(B15,Terméklista!$B$2:$B$103,Terméklista!F$2:$F$103,))/1000} -> 31.5 | S15: =IFERROR(((H15/_xlfn.XLOOKUP(B15,Terméklista!$B$2:$B$103,Terméklista!$E$2:$E$103)*_xlfn.XLOOKUP(B15,Terméklista!$B$2:$B$103,Terméklista!$I$2:$I$103)))/3600," ") -> 126.38889
A16: Seidel Gmbh&co Kg | B16: MA51 | C16: =IFERROR(_xlfn.XLOOKUP(B16,Terméklista!$B$2:$B$103,Terméklista!$C$2:$C$103,)," ") -> Zamak Gewicht | E16: M251012 | F16: =_xlfn.XLOOKUP(B16,Terméklista!$B$2:$B$103,Terméklista!$G$2:$G$103," ") -> Z410 | G16: 4500099914 | H16: 150000 | I16: 2025-01-22 | J16: 2025-03-24 | L16: x | N16: =IFERROR(_xlfn.XLOOKUP(B16,Terméklista!B13:B114,Terméklista!H13:H114)," ") -> 0 | O16: =IFERROR(ROUNDUP(Rendelés[[#This Row],[Amount/pc]]/_xlfn.XLOOKUP(B16,Terméklista!$B$2:$B$103,Terméklista!$M$2:$M$103,),0)," ") -> 429 | P16: =IFERROR(ROUNDUP(Rendelés[[#This Row],[Dobozok száma]]/_xlfn.XLOOKUP(B16,Terméklista!$B$2:$B$103,Terméklista!$N$2:$N$103,),0)," ") -> 15 | Q16: =IFERROR(Rendelés[[#This Row],[Szükséges anyagmennyiség]]+(Rendelés[[#This Row],[Össz raklapok száma]]*25),"") -> 4653 | R16: {=(H16*_xlfn.XLOOKUP(B16,Terméklista!$B$2:$B$103,Terméklista!F$2:$F$103,))/1000} -> 4278 | S16: =IFERROR(((H16/_xlfn.XLOOKUP(B16,Terméklista!$B$2:$B$103,Terméklista!$E$2:$E$103)*_xlfn.XLOOKUP(B16,Terméklista!$B$2:$B$103,Terméklista!$I$2:$I$103)))/3600," ") -> 208.33333 | T16: 2025/23
A17: Ela Solutions Kft. | B17: 90ZA-H001-06 | C17: =IFERROR(_xlfn.XLOOKUP(B17,Terméklista!$B$2:$B$103,Terméklista!$C$2:$C$103,)," ") -> zárház | E17: M251013 | F17: =_xlfn.XLOOKUP(B17,Terméklista!$B$2:$B$103,Terméklista!$G$2:$G$103," ") -> Z410 | G17: 5535 | H17: 1000 | I17: 2025-01-23 | J17: 2025-01-29 | K17: 2025-02-03 | L17: x | N17: =IFERROR(_xlfn.XLOOKUP(B17,Terméklista!B14:B115,Terméklista!H14:H115)," ") -> 0 | O17: =IFERROR(ROUNDUP(Rendelés[[#This Row],[Amount/pc]]/_xlfn.XLOOKUP(B17,Terméklista!$B$2:$B$103,Terméklista!$M$2:$M$103,),0)," ") | P17: =IFERROR(ROUNDUP(Rendelés[[#This Row],[Dobozok száma]]/_xlfn.XLOOKUP(B17,Terméklista!$B$2:$B$103,Terméklista!$N$2:$N$103,),0)," ") | Q17: =IFERROR(Rendelés[[#This Row],[Szükséges anyagmennyiség]]+(Rendelés[[#This Row],[Össz raklapok száma]]*25),"") | R17: {=(H17*_xlfn.XLOOKUP(B17,Terméklista!$B$2:$B$103,Terméklista!F$2:$F$103,))/1000} -> 24.5 | S17: =IFERROR(((H17/_xlfn.XLOOKUP(B17,Terméklista!$B$2:$B$103,Terméklista!$E$2:$E$103)*_xlfn.XLOOKUP(B17,Terméklista!$B$2:$B$103,Terméklista!$I$2:$I$103)))/3600," ") -> 2.0833333
A18: Systec Pos-Technology Gmbh | B18: Verdrehsicherung C3R Flanch | C18: =IFERROR(_xlfn.XLOOKUP(B18,Terméklista!$B$2:$B$103,Terméklista!$C$2:$C$103,)," ") | E18: M251014 | F18: =_xlfn.XLOOKUP(B18,Terméklista!$B$2:$B$103,Terméklista!$G$2:$G$103," ") | G18: 26449 | H18: 5000 | I18: 2025-01-27 | J18: 2025-02-19 | K18: 2025-02-21 | L18: x | N18: =IFERROR(_xlfn.XLOOKUP(B18,Terméklista!B15:B116,Terméklista!H15:H116)," ") | O18: =IFERROR(ROUNDUP(Rendelés[[#This Row],[Amount/pc]]/_xlfn.XLOOKUP(B18,Terméklista!$B$2:$B$103,Terméklista!$M$2:$M$103,),0)," ") | P18: =IFERROR(ROUNDUP(Rendelés[[#This Row],[Dobozok száma]]/_xlfn.XLOOKUP(B18,Terméklista!$B$2:$B$103,Terméklista!$N$2:$N$103,),0)," ") | Q18: =IFERROR(Rendelés[[#This Row],[Szükséges anyagmennyiség]]+(Rendelés[[#This Row],[Össz raklapok száma]]*25),"") | R18: {=(H18*_xlfn.XLOOKUP(B18,Terméklista!$B$2:$B$103,Terméklista!F$2:$F$103,))/1000} -> #N/A | S18: =IFERROR(((H18/_xlfn.XLOOKUP(B18,Terméklista!$B$2:$B$103,Terméklista!$E$2:$E$103)*_xlfn.XLOOKUP(B18,Terméklista!$B$2:$B$103,Terméklista!$I$2:$I$103)))/3600," ")
A19: Systec Pos-Technology Gmbh | B19: Euroloc 2 sperrhacken Zn S | C19: =IFERROR(_xlfn.XLOOKUP(B19,Terméklista!$B$2:$B$103,Terméklista!$C$2:$C$103,)," ") | E19: M251015 | F19: =_xlfn.XLOOKUP(B19,Terméklista!$B$2:$B$103,Terméklista!$G$2:$G$103," ") | G19: 26452 | H19: 20000 | I19: 2025-01-27 | J19: 2025-03-05 | K19: 2025-02-21 | L19: x | N19: =IFERROR(_xlfn.XLOOKUP(B19,Terméklista!B16:B117,Terméklista!H16:H117)," ") | O19: =IFERROR(ROUNDUP(Rendelés[[#This Row],[Amount/pc]]/_xlfn.XLOOKUP(B19,Terméklista!$B$2:$B$103,Terméklista!$M$2:$M$103,),0)," ") | P19: =IFERROR(ROUNDUP(Rendelés[[#This Row],[Dobozok száma]]/_xlfn.XLOOKUP(B19,Terméklista!$B$2:$B$103,Terméklista!$N$2:$N$103,),0)," ") | Q19: =IFERROR(Rendelés[[#This Row],[Szükséges anyagmennyiség]]+(Rendelés[[#This Row],[Össz raklapok száma]]*25),"") | R19: {=(H19*_xlfn.XLOOKUP(B19,Terméklista!$B$2:$B$103,Terméklista!F$2:$F$103,))/1000} -> #N/A | S19: =IFERROR(((H19/_xlfn.XLOOKUP(B19,Terméklista!$B$2:$B$103,Terméklista!$E$2:$E$103)*_xlfn.XLOOKUP(B19,Terméklista!$B$2:$B$103,Terméklista!$I$2:$I$103)))/3600," ") | T19: 2025/22
A20: Seidel Gmbh&co Kg | B20: MB22 | C20: =IFERROR(_xlfn.XLOOKUP(B20,Terméklista!$B$2:$B$103,Terméklista!$C$2:$C$103,)," ") -> Zamak Gewicht | E20: M251016 | F20: =_xlfn.XLOOKUP(B20,Terméklista!$B$2:$B$103,Terméklista!$G$2:$G$103," ") -> Z410 | G20: 4500100205 | H20: 24000 | I20: 2025-02-11 | J20: 2025-03-26 | L20: x | N20: =IFERROR(_xlfn.XLOOKUP(B20,Terméklista!B17:B118,Terméklista!H17:H118)," ") -> 0 | O20: =IFERROR(ROUNDUP(Rendelés[[#This Row],[Amount/pc]]/_xlfn.XLOOKUP(B20,Terméklista!$B$2:$B$103,Terméklista!$M$2:$M$103,),0)," ") -> 24 | P20: =IFERROR(ROUNDUP(Rendelés[[#This Row],[Dobozok száma]]/_xlfn.XLOOKUP(B20,Terméklista!$B$2:$B$103,Terméklista!$N$2:$N$103,),0)," ") -> 1 | Q20: =IFERROR(Rendelés[[#This Row],[Szükséges anyagmennyiség]]+(Rendelés[[#This Row],[Össz raklapok száma]]*25),"") -> 217 | R20: {=(H20*_xlfn.XLOOKUP(B20,Terméklista!$B$2:$B$103,Terméklista!F$2:$F$103,))/1000} -> 192 | S20: =IFERROR(((H20/_xlfn.XLOOKUP(B20,Terméklista!$B$2:$B$103,Terméklista!$E$2:$E$103)*_xlfn.XLOOKUP(B20,Terméklista!$B$2:$B$103,Terméklista!$I$2:$I$103)))/3600," ") -> 8.3333333 | T20: 2025/23
A21: Systec Pos-Technology Gmbh | B21: Smartstop-2 Sperritzteil-2 | C21: =IFERROR(_xlfn.XLOOKUP(B21,Terméklista!$B$2:$B$103,Terméklista!$C$2:$C$103,)," ") | E21: M251019 | F21: =_xlfn.XLOOKUP(B21,Terméklista!$B$2:$B$103,Terméklista!$G$2:$G$103," ") | G21: 26514 | H21: 10000 | I21: 2025-02-12 | J21: 2025-03-27 | L21: x | N21: =IFERROR(_xlfn.XLOOKUP(B21,Terméklista!B20:B121,Terméklista!H20:H121)," ") | O21: =IFERROR(ROUNDUP(Rendelés[[#This Row],[Amount/pc]]/_xlfn.XLOOKUP(B21,Terméklista!$B$2:$B$103,Terméklista!$M$2:$M$103,),0)," ") | P21: =IFERROR(ROUNDUP(Rendelés[[#This Row],[Dobozok száma]]/_xlfn.XLOOKUP(B21,Terméklista!$B$2:$B$103,Terméklista!$N$2:$N$103,),0)," ") | Q21: =IFERROR(Rendelés[[#This Row],[Szükséges anyagmennyiség]]+(Rendelés[[#This Row],[Össz raklapok száma]]*25),"") | R21: {=(H21*_xlfn.XLOOKUP(B21,Terméklista!$B$2:$B$103,Terméklista!F$2:$F$103,))/1000} -> #N/A | S21: =IFERROR(((H21/_xlfn.XLOOKUP(B21,Terméklista!$B$2:$B$103,Terméklista!$E$2:$E$103)*_xlfn.XLOOKUP(B21,Terméklista!$B$2:$B$103,Terméklista!$I$2:$I$103)))/3600," ") | T21: 2025/22
A22: Ela Solutions Kft. | B22: 90ZA-ZS004-00 | C22: =IFERROR(_xlfn.XLOOKUP(B22,Terméklista!$B$2:$B$103,Terméklista!$C$2:$C$103,)," ") -> zsanértest | E22: M251018 | F22: =_xlfn.XLOOKUP(B22,Terméklista!$B$2:$B$103,Terméklista!$G$2:$G$103," ") -> Z410 | G22: 5577 | H22: 200 | I22: 2025-02-13 | J22: 2025-02-20 | K22: 2025-02-21 | L22: x | N22: =IFERROR(_xlfn.XLOOKUP(B22,Terméklista!B19:B120,Terméklista!H19:H120)," ") -> 0 | O22: =IFERROR(ROUNDUP(Rendelés[[#This Row],[Amount/pc]]/_xlfn.XLOOKUP(B22,Terméklista!$B$2:$B$103,Terméklista!$M$2:$M$103,),0)," ") | P22: =IFERROR(ROUNDUP(Rendelés[[#This Row],[Dobozok száma]]/_xlfn.XLOOKUP(B22,Terméklista!$B$2:$B$103,Terméklista!$N$2:$N$103,),0)," ") | Q22: =IFERROR(Rendelés[[#This Row],[Szükséges anyagmennyiség]]+(Rendelés[[#This Row],[Össz raklapok száma]]*25),"") | R22: {=(H22*_xlfn.XLOOKUP(B22,Terméklista!$B$2:$B$103,Terméklista!F$2:$F$103,))/1000} -> 14 | S22: =IFERROR(((H22/_xlfn.XLOOKUP(B22,Terméklista!$B$2:$B$103,Terméklista!$E$2:$E$103)*_xlfn.XLOOKUP(B22,Terméklista!$B$2:$B$103,Terméklista!$I$2:$I$103)))/3600," ") -> 0.41666667
A23: Seidel Gmbh&co Kg | B23: MA41 | C23: =IFERROR(_xlfn.XLOOKUP(B23,Terméklista!$B$2:$B$103,Terméklista!$C$2:$C$103,)," ") -> Zamak Gewicht | E23: M251020 | F23: =_xlfn.XLOOKUP(B23,Terméklista!$B$2:$B$103,Terméklista!$G$2:$G$103," ") -> Z410 | G23: 4500100294 | H23: 50000 | I23: 2025-02-17 | J23: 2025-05-26 | K23: 2025-05-14 | L23: x | N23: =IFERROR(_xlfn.XLOOKUP(B23,Terméklista!B21:B122,Terméklista!H21:H122)," ") -> 0 | O23: =IFERROR(ROUNDUP(Rendelés[[#This Row],[Amount/pc]]/_xlfn.XLOOKUP(B23,Terméklista!$B$2:$B$103,Terméklista!$M$2:$M$103,),0)," ") -> 143 | P23: =IFERROR(ROUNDUP(Rendelés[[#This Row],[Dobozok száma]]/_xlfn.XLOOKUP(B23,Terméklista!$B$2:$B$103,Terméklista!$N$2:$N$103,),0)," ") -> 2 | Q23: =IFERROR(Rendelés[[#This Row],[Szükséges anyagmennyiség]]+(Rendelés[[#This Row],[Össz raklapok száma]]*25),"") -> 900 | R23: {=(H23*_xlfn.XLOOKUP(B23,Terméklista!$B$2:$B$103,Terméklista!F$2:$F$103,))/1000} -> 850 | S23: =IFERROR(((H23/_xlfn.XLOOKUP(B23,Terméklista!$B$2:$B$103,Terméklista!$E$2:$E$103)*_xlfn.XLOOKUP(B23,Terméklista!$B$2:$B$103,Terméklista!$I$2:$I$103)))/3600," ") -> 34.722222 | T23: 2025/27
A24: Fasten Italia S.R.L | B24: P6 body | C24: =IFERROR(_xlfn.XLOOKUP(B24,Terméklista!$B$2:$B$103,Terméklista!$C$2:$C$103,)," ") -> 0 | E24: M251021 | F24: =_xlfn.XLOOKUP(B24,Terméklista!$B$2:$B$103,Terméklista!$G$2:$G$103," ") -> Z410 | G24: 25/00113 | H24: 30000 | I24: 2025-02-17 | J24: 2025-04-16 | L24: x | M24: CMR | N24: =IFERROR(_xlfn.XLOOKUP(B24,Terméklista!B22:B123,Terméklista!H22:H123)," ") -> 0 | O24: =IFERROR(ROUNDUP(Rendelés[[#This Row],[Amount/pc]]/_xlfn.XLOOKUP(B24,Terméklista!$B$2:$B$103,Terméklista!$M$2:$M$103,),0)," ") | P24: =IFERROR(ROUNDUP(Rendelés[[#This Row],[Dobozok száma]]/_xlfn.XLOOKUP(B24,Terméklista!$B$2:$B$103,Terméklista!$N$2:$N$103,),0)," ") | Q24: =IFERROR(Rendelés[[#This Row],[Szükséges anyagmennyiség]]+(Rendelés[[#This Row],[Össz raklapok száma]]*25),"") | R24: {=(H24*_xlfn.XLOOKUP(B24,Terméklista!$B$2:$B$103,Terméklista!F$2:$F$103,))/1000} -> 0 | S24: =IFERROR(((H24/_xlfn.XLOOKUP(B24,Terméklista!$B$2:$B$103,Terméklista!$E$2:$E$103)*_xlfn.XLOOKUP(B24,Terméklista!$B$2:$B$103,Terméklista!$I$2:$I$103)))/3600," ") | T24: 2025/34
A25: Fasten Italia S.R.L | B25: YKK fogó | C25: =IFERROR(_xlfn.XLOOKUP(B25,Terméklista!$B$2:$B$103,Terméklista!$C$2:$C$103,)," ") -> 0 | E25: M251022 | F25: =_xlfn.XLOOKUP(B25,Terméklista!$B$2:$B$103,Terméklista!$G$2:$G$103," ") -> Z410 | G25: 25/00113 | H25: 30000 | I25: 2025-02-17 | J25: 2025-04-16 | L25: x | M25: CMR | N25: =IFERROR(_xlfn.XLOOKUP(B25,Terméklista!B23:B124,Terméklista!H23:H124)," ") -> 0 | O25: =IFERROR(ROUNDUP(Rendelés[[#This Row],[Amount/pc]]/_xlfn.XLOOKUP(B25,Terméklista!$B$2:$B$103,Terméklista!$M$2:$M$103,),0)," ") | P25: =IFERROR(ROUNDUP(Rendelés[[#This Row],[Dobozok száma]]/_xlfn.XLOOKUP(B25,Terméklista!$B$2:$B$103,Terméklista!$N$2:$N$103,),0)," ") | Q25: =IFERROR(Rendelés[[#This Row],[Szükséges anyagmennyiség]]+(Rendelés[[#This Row],[Össz raklapok száma]]*25),"") | R25: {=(H25*_xlfn.XLOOKUP(B25,Terméklista!$B$2:$B$103,Terméklista!F$2:$F$103,))/1000} -> 0 | S25: =IFERROR(((H25/_xlfn.XLOOKUP(B25,Terméklista!$B$2:$B$103,Terméklista!$E$2:$E$103)*_xlfn.XLOOKUP(B25,Terméklista!$B$2:$B$103,Terméklista!$I$2:$I$103)))/3600," ") | T25: 2025/34
A26: Ela Solutions Kft. | B26: 90ZA-B0011-06 | C26: =IFERROR(_xlfn.XLOOKUP(B26,Terméklista!$B$2:$B$103,Terméklista!$C$2:$C$103,)," ") -> 0 | E26: M251023 | F26: =_xlfn.XLOOKUP(B26,Terméklista!$B$2:$B$103,Terméklista!$G$2:$G$103," ") -> Z410 | G26: 5585 | H26: 992 | I26: 2025-02-21 | J26: 2025-02-26 | K26: 2025-02-26 | L26: x | N26: =IFERROR(_xlfn.XLOOKUP(B26,Terméklista!B24:B125,Terméklista!H24:H125)," ") -> 0 | O26: =IFERROR(ROUNDUP(Rendelés[[#This Row],[Amount/pc]]/_xlfn.XLOOKUP(B26,Terméklista!$B$2:$B$103,Terméklista!$M$2:$M$103,),0)," ") | P26: =IFERROR(ROUNDUP(Rendelés[[#This Row],[Dobozok száma]]/_xlfn.XLOOKUP(B26,Terméklista!$B$2:$B$103,Terméklista!$N$2:$N$103,),0)," ") | Q26: =IFERROR(Rendelés[[#This Row],[Szükséges anyagmennyiség]]+(Rendelés[[#This Row],[Össz raklapok száma]]*25),"") | R26: {=(H26*_xlfn.XLOOKUP(B26,Terméklista!$B$2:$B$103,Terméklista!F$2:$F$103,))/1000} -> 2.86688 | S26: =IFERROR(((H26/_xlfn.XLOOKUP(B26,Terméklista!$B$2:$B$103,Terméklista!$E$2:$E$103)*_xlfn.XLOOKUP(B26,Terméklista!$B$2:$B$103,Terméklista!$I$2:$I$103)))/3600," ")
A27: Seidel Gmbh&co Kg | B27: MA51 | C27: =IFERROR(_xlfn.XLOOKUP(B27,Terméklista!$B$2:$B$103,Terméklista!$C$2:$C$103,)," ") -> Zamak Gewicht | E27: M251024 | F27: =_xlfn.XLOOKUP(B27,Terméklista!$B$2:$B$103,Terméklista!$G$2:$G$103," ") -> Z410 | G27: 4500100427 | H27: 50000 | I27: 2025-02-25 | J27: 2025-04-17 | K27: 2025-04-10 | L27: x | N27: =IFERROR(_xlfn.XLOOKUP(B27,Terméklista!B25:B126,Terméklista!H25:H126)," ") -> 0 | O27: =IFERROR(ROUNDUP(Rendelés[[#This Row],[Amount/pc]]/_xlfn.XLOOKUP(B27,Terméklista!$B$2:$B$103,Terméklista!$M$2:$M$103,),0)," ") -> 143 | P27: =IFERROR(ROUNDUP(Rendelés[[#This Row],[Dobozok száma]]/_xlfn.XLOOKUP(B27,Terméklista!$B$2:$B$103,Terméklista!$N$2:$N$103,),0)," ") -> 5 | Q27: =IFERROR(Rendelés[[#This Row],[Szükséges anyagmennyiség]]+(Rendelés[[#This Row],[Össz raklapok száma]]*25),"") -> 1551 | R27: {=(H27*_xlfn.XLOOKUP(B27,Terméklista!$B$2:$B$103,Terméklista!F$2:$F$103,))/1000} -> 1426 | S27: =IFERROR(((H27/_xlfn.XLOOKUP(B27,Terméklista!$B$2:$B$103,Terméklista!$E$2:$E$103)*_xlfn.XLOOKUP(B27,Terméklista!$B$2:$B$103,Terméklista!$I$2:$I$103)))/3600," ") -> 69.444444 | T27: 2025/30
A28: Systec Pos-Technology Gmbh | B28: Rasthebel-2 | C28: =IFERROR(_xlfn.XLOOKUP(B28,Terméklista!$B$2:$B$103,Terméklista!$C$2:$C$103,)," ") -> Smartstop-2 | E28: M251026 | F28: =_xlfn.XLOOKUP(B28,Terméklista!$B$2:$B$103,Terméklista!$G$2:$G$103," ") -> Z410 | G28: 26594 | H28: 10000 | I28: 2025-03-03 | J28: 2025-04-02 | K28: 2025-04-15 | L28: x | M28: CMR | N28: =IFERROR(_xlfn.XLOOKUP(B28,Terméklista!B27:B128,Terméklista!H27:H128)," ") -> 0 | O28: =IFERROR(ROUNDUP(Rendelés[[#This Row],[Amount/pc]]/_xlfn.XLOOKUP(B28,Terméklista!$B$2:$B$103,Terméklista!$M$2:$M$103,),0)," ") -> 16 | P28: =IFERROR(ROUNDUP(Rendelés[[#This Row],[Dobozok száma]]/_xlfn.XLOOKUP(B28,Terméklista!$B$2:$B$103,Terméklista!$N$2:$N$103,),0)," ") -> 1 | Q28: =IFERROR(Rendelés[[#This Row],[Szükséges anyagmennyiség]]+(Rendelés[[#This Row],[Össz raklapok száma]]*25),"") -> 175.3 | R28: {=(H28*_xlfn.XLOOKUP(B28,Terméklista!$B$2:$B$103,Terméklista!F$2:$F$103,))/1000} -> 150.3 | S28: =IFERROR(((H28/_xlfn.XLOOKUP(B28,Terméklista!$B$2:$B$103,Terméklista!$E$2:$E$103)*_xlfn.XLOOKUP(B28,Terméklista!$B$2:$B$103,Terméklista!$I$2:$I$103)))/3600," ") -> 6.9444444 | T28: 2025/34
A29: Seidel Gmbh&co Kg | B29: MA41 | C29: =IFERROR(_xlfn.XLOOKUP(B29,Terméklista!$B$2:$B$103,Terméklista!$C$2:$C$103,)," ") -> Zamak Gewicht | E29: M251025 | F29: =_xlfn.XLOOKUP(B29,Terméklista!$B$2:$B$103,Terméklista!$G$2:$G$103," ") -> Z410 | G29: 4500100560 | H29: 50000 | I29: 2025-03-04 | J29: 2025-06-02 | K29: 2025-06-05 | L29: x | N29: =_xlfn.XLOOKUP(J29,Terméklista!$B$2:$B$103,Terméklista!$H$2:$H$103," ") | O29: =IFERROR(ROUNDUP(Rendelés[[#This Row],[Amount/pc]]/_xlfn.XLOOKUP(B29,Terméklista!$B$2:$B$103,Terméklista!$M$2:$M$103,),0)," ") -> 143 | P29: =IFERROR(ROUNDUP(Rendelés[[#This Row],[Dobozok száma]]/_xlfn.XLOOKUP(B29,Terméklista!$B$2:$B$103,Terméklista!$N$2:$N$103,),0)," ") -> 2 | Q29: =IFERROR(Rendelés[[#This Row],[Szükséges anyagmennyiség]]+(Rendelés[[#This Row],[Össz raklapok száma]]*25),"") -> 900 | R29: {=(H29*_xlfn.XLOOKUP(B29,Terméklista!$B$2:$B$103,Terméklista!F$2:$F$103,))/1000} -> 850 | S29: =IFERROR(((H29/_xlfn.XLOOKUP(B29,Terméklista!$B$2:$B$103,Terméklista!$E$2:$E$103)*_xlfn.XLOOKUP(B29,Terméklista!$B$2:$B$103,Terméklista!$I$2:$I$103)))/3600," ") -> 34.722222
A30: Systec Pos-Technology Gmbh | B30: CVLROH | C30: =IFERROR(_xlfn.XLOOKUP(B30,Terméklista!$B$2:$B$103,Terméklista!$C$2:$C$103,)," ") -> Verdrehsicherung | E30: M251028 | F30: =_xlfn.XLOOKUP(B30,Terméklista!$B$2:$B$103,Terméklista!$G$2:$G$103," ") -> Z410 | G30: 26607 | H30: 5000 | I30: 2025-03-06 | J30: 2025-04-18 | K30: 2025-04-08 | L30: x | M30: CMR | N30: =IFERROR(_xlfn.XLOOKUP(B30,Terméklista!B29:B130,Terméklista!H29:H130)," ") -> 0 | O30: =IFERROR(ROUNDUP(Rendelés[[#This Row],[Amount/pc]]/_xlfn.XLOOKUP(B30,Terméklista!$B$2:$B$103,Terméklista!$M$2:$M$103,),0)," ") -> 25 | P30: =IFERROR(ROUNDUP(Rendelés[[#This Row],[Dobozok száma]]/_xlfn.XLOOKUP(B30,Terméklista!$B$2:$B$103,Terméklista!$N$2:$N$103,),0)," ") -> 1 | Q30: =IFERROR(Rendelés[[#This Row],[Szükséges anyagmennyiség]]+(Rendelés[[#This Row],[Össz raklapok száma]]*25),"") -> 298.5 | R30: {=(H30*_xlfn.XLOOKUP(B30,Terméklista!$B$2:$B$103,Terméklista!F$2:$F$103,))/1000} -> 273.5 | S30: =IFERROR(((H30/_xlfn.XLOOKUP(B30,Terméklista!$B$2:$B$103,Terméklista!$E$2:$E$103)*_xlfn.XLOOKUP(B30,Terméklista!$B$2:$B$103,Terméklista!$I$2:$I$103)))/3600," ") -> 10.416667 | T30: 2025/34
A31: Ela Solutions Kft. | B31: 90ZA-ZK001-06 | C31: =IFERROR(_xlfn.XLOOKUP(B31,Terméklista!$B$2:$B$103,Terméklista!$C$2:$C$103,)," ") -> 0 | E31: M251027 | F31: =_xlfn.XLOOKUP(B31,Terméklista!$B$2:$B$103,Terméklista!$G$2:$G$103," ") -> Z410 | G31: 5611 | H31: 2000 | I31: 2025-03-06 | J31: 2025-03-10 | K31: 2025-03-10 | L31: x | N31: =IFERROR(_xlfn.XLOOKUP(B31,Terméklista!B28:B129,Terméklista!H28:H129)," ") | O31: =IFERROR(ROUNDUP(Rendelés[[#This Row],[Amount/pc]]/_xlfn.XLOOKUP(B31,Terméklista!$B$2:$B$103,Terméklista!$M$2:$M$103,),0)," ") | P31: =IFERROR(ROUNDUP(Rendelés[[#This Row],[Dobozok száma]]/_xlfn.XLOOKUP(B31,Terméklista!$B$2:$B$103,Terméklista!$N$2:$N$103,),0)," ") | Q31: =IFERROR(Rendelés[[#This Row],[Szükséges anyagmennyiség]]+(Rendelés[[#This Row],[Össz raklapok száma]]*25),"") | R31: {=(H31*_xlfn.XLOOKUP(B31,Terméklista!$B$2:$B$103,Terméklista!F$2:$F$103,))/1000} -> 44.68 | S31: =IFERROR(((H31/_xlfn.XLOOKUP(B31,Terméklista!$B$2:$B$103,Terméklista!$E$2:$E$103)*_xlfn.XLOOKUP(B31,Terméklista!$B$2:$B$103,Terméklista!$I$2:$I$103)))/3600," ") -> 4.1666667
A32: Seidel Gmbh&co Kg | B32: MA66 | C32: =IFERROR(_xlfn.XLOOKUP(B32,Terméklista!$B$2:$B$103,Terméklista!$C$2:$C$103,)," ") -> Zamak Gewicht | E32: M251029 | F32: =_xlfn.XLOOKUP(B32,Terméklista!$B$2:$B$103,Terméklista!$G$2:$G$103," ") -> Z410 | G32: 4500100603 | H32: 300000 | I32: 2025-03-06 | J32: 2025-05-15 | K32: 2025-05-14 | L32: x | N32: =IFERROR(_xlfn.XLOOKUP(B32,Terméklista!B30:B131,Terméklista!H30:H131)," ") -> 0 | O32: =IFERROR(ROUNDUP(Rendelés[[#This Row],[Amount/pc]]/_xlfn.XLOOKUP(B32,Terméklista!$B$2:$B$103,Terméklista!$M$2:$M$103,),0)," ") -> 600 | P32: =IFERROR(ROUNDUP(Rendelés[[#This Row],[Dobozok száma]]/_xlfn.XLOOKUP(B32,Terméklista!$B$2:$B$103,Terméklista!$N$2:$N$103,),0)," ") -> 7 | Q32: =IFERROR(Rendelés[[#This Row],[Szükséges anyagmennyiség]]+(Rendelés[[#This Row],[Össz raklapok száma]]*25),"") -> 3325 | R32: {=(H32*_xlfn.XLOOKUP(B32,Terméklista!$B$2:$B$103,Terméklista!F$2:$F$103,))/1000} -> 3150 | S32: =IFERROR(((H32/_xlfn.XLOOKUP(B32,Terméklista!$B$2:$B$103,Terméklista!$E$2:$E$103)*_xlfn.XLOOKUP(B32,Terméklista!$B$2:$B$103,Terméklista!$I$2:$I$103)))/3600," ") -> 208.33333 | T32: 2025/27
A33: Seidel Gmbh&co Kg | B33: MA66 | C33: =IFERROR(_xlfn.XLOOKUP(B33,Terméklista!$B$2:$B$103,Terméklista!$C$2:$C$103,)," ") -> Zamak Gewicht | E33: M251030 | F33: =_xlfn.XLOOKUP(B33,Terméklista!$B$2:$B$103,Terméklista!$G$2:$G$103," ") -> Z410 | G33: 4500100603 | H33: 200000 | I33: 2025-03-06 | J33: 2025-06-25 | K33: 2025-06-19 | L33: x | N33: =_xlfn.XLOOKUP(J33,Terméklista!$B$2:$B$103,Terméklista!$H$2:$H$103," ") | O33: =IFERROR(ROUNDUP(Rendelés[[#This Row],[Amount/pc]]/_xlfn.XLOOKUP(B33,Terméklista!$B$2:$B$103,Terméklista!$M$2:$M$103,),0)," ") -> 400 | P33: =IFERROR(ROUNDUP(Rendelés[[#This Row],[Dobozok száma]]/_xlfn.XLOOKUP(B33,Terméklista!$B$2:$B$103,Terméklista!$N$2:$N$103,),0)," ") -> 5 | Q33: =IFERROR(Rendelés[[#This Row],[Szükséges anyagmennyiség]]+(Rendelés[[#This Row],[Össz raklapok száma]]*25),"") -> 2225 | R33: {=(H33*_xlfn.XLOOKUP(B33,Terméklista!$B$2:$B$103,Terméklista!F$2:$F$103,))/1000} -> 2100 | S33: =IFERROR(((H33/_xlfn.XLOOKUP(B33,Terméklista!$B$2:$B$103,Terméklista!$E$2:$E$103)*_xlfn.XLOOKUP(B33,Terméklista!$B$2:$B$103,Terméklista!$I$2:$I$103)))/3600," ") -> 138.88889
A34: Seidel Gmbh&co Kg | B34: MB22 | E34: M251048 | F34: =_xlfn.XLOOKUP(B34,Terméklista!$B$2:$B$103,Terméklista!$G$2:$G$103," ") -> Z410 | G34: 4500100868 | H34: 92000 | I34: 2025-03-06 | J34: 2025-06-18 | K34: 2025-06-13 | L34: x | M34: CMR | N34: =_xlfn.XLOOKUP(J34,Terméklista!$B$2:$B$103,Terméklista!$H$2:$H$103," ") | O34: =IFERROR(ROUNDUP(Rendelés[[#This Row],[Amount/pc]]/_xlfn.XLOOKUP(B34,Terméklista!$B$2:$B$103,Terméklista!$M$2:$M$103,),0)," ") -> 92 | P34: =IFERROR(ROUNDUP(Rendelés[[#This Row],[Dobozok száma]]/_xlfn.XLOOKUP(B34,Terméklista!$B$2:$B$103,Terméklista!$N$2:$N$103,),0)," ") -> 1 | Q34: =IFERROR(Rendelés[[#This Row],[Szükséges anyagmennyiség]]+(Rendelés[[#This Row],[Össz raklapok száma]]*25),"") -> 761 | R34: {=(H34*_xlfn.XLOOKUP(B34,Terméklista!$B$2:$B$103,Terméklista!F$2:$F$103,))/1000} -> 736 | S34: =IFERROR(((H34/_xlfn.XLOOKUP(B34,Terméklista!$B$2:$B$103,Terméklista!$E$2:$E$103)*_xlfn.XLOOKUP(B34,Terméklista!$B$2:$B$103,Terméklista!$I$2:$I$103)))/3600," ") -> 31.944444 | T34: 2025/44
A35: Arsisco AMO Pack LLC | B35: Töltő sin | C35: 0 | E35: M251032 | F35: =_xlfn.XLOOKUP(B35,Terméklista!$B$2:$B$103,Terméklista!$G$2:$G$103," ") -> Z414 | H35: 1000 | I35: 2025-03-14 | J35: 2025-03-31 | K35: 2025-04-03 | L35: x | N35: =IFERROR(_xlfn.XLOOKUP(B35,Terméklista!B33:B134,Terméklista!H33:H134)," ") | O35: =IFERROR(ROUNDUP(Rendelés[[#This Row],[Amount/pc]]/_xlfn.XLOOKUP(B35,Terméklista!$B$2:$B$103,Terméklista!$M$2:$M$103,),0)," ") | P35: =IFERROR(ROUNDUP(Rendelés[[#This Row],[Dobozok száma]]/_xlfn.XLOOKUP(B35,Terméklista!$B$2:$B$103,Terméklista!$N$2:$N$103,),0)," ") | Q35: =IFERROR(Rendelés[[#This Row],[Szükséges anyagmennyiség]]+(Rendelés[[#This Row],[Össz raklapok száma]]*25),"") | R35: {=(H35*_xlfn.XLOOKUP(B35,Terméklista!$B$2:$B$103,Terméklista!F$2:$F$103,))/1000} -> 0 | S35: =IFERROR(((H35/_xlfn.XLOOKUP(B35,Terméklista!$B$2:$B$103,Terméklista!$E$2:$E$103)*_xlfn.XLOOKUP(B35,Terméklista!$B$2:$B$103,Terméklista!$I$2:$I$103)))/3600," ")
A36: Seidel Gmbh&co Kg | B36: M83 | C36: =IFERROR(_xlfn.XLOOKUP(B36,Terméklista!$B$2:$B$103,Terméklista!$C$2:$C$103,)," ") -> Zamak Gewicht | E36: M251038 | F36: =_xlfn.XLOOKUP(B36,Terméklista!$B$2:$B$103,Terméklista!$G$2:$G$103," ") -> Z410 | G36: 4500100908 | H36: 90000 | I36: 2025-03-25 | J36: 2025-06-02 | K36: 2025-06-05 | L36: x | N36: =_xlfn.XLOOKUP(J36,Terméklista!$B$2:$B$103,Terméklista!$H$2:$H$103," ") | O36: =IFERROR(ROUNDUP(Rendelés[[#This Row],[Amount/pc]]/_xlfn.XLOOKUP(B36,Terméklista!$B$2:$B$103,Terméklista!$M$2:$M$103,),0)," ") -> 600 | P36: =IFERROR(ROUNDUP(Rendelés[[#This Row],[Dobozok száma]]/_xlfn.XLOOKUP(B36,Terméklista!$B$2:$B$103,Terméklista!$N$2:$N$103,),0)," ") -> 20 | Q36: =IFERROR(Rendelés[[#This Row],[Szükséges anyagmennyiség]]+(Rendelés[[#This Row],[Össz raklapok száma]]*25),"") -> 6377 | R36: {=(H36*_xlfn.XLOOKUP(B36,Terméklista!$B$2:$B$103,Terméklista!F$2:$F$103,))/1000} -> 5877 | S36: =IFERROR(((H36/_xlfn.XLOOKUP(B36,Terméklista!$B$2:$B$103,Terméklista!$E$2:$E$103)*_xlfn.XLOOKUP(B36,Terméklista!$B$2:$B$103,Terméklista!$I$2:$I$103)))/3600," ") -> 125
A37: Ela Solutions Kft. | B37: 90ZA-ZS004-00 | C37: =IFERROR(_xlfn.XLOOKUP(B37,Terméklista!$B$2:$B$103,Terméklista!$C$2:$C$103,)," ") -> zsanértest | E37: M251033 | F37: =_xlfn.XLOOKUP(B37,Terméklista!$B$2:$B$103,Terméklista!$G$2:$G$103," ") -> Z410 | G37: 5664 | H37: 550 | I37: 2025-04-02 | J37: 2025-04-04 | K37: 2025-04-07 | L37: x | N37: =IFERROR(_xlfn.XLOOKUP(B37,Terméklista!B34:B135,Terméklista!H34:H135)," ") -> 0 | O37: =IFERROR(ROUNDUP(Rendelés[[#This Row],[Amount/pc]]/_xlfn.XLOOKUP(B37,Terméklista!$B$2:$B$103,Terméklista!$M$2:$M$103,),0)," ") | P37: =IFERROR(ROUNDUP(Rendelés[[#This Row],[Dobozok száma]]/_xlfn.XLOOKUP(B37,Terméklista!$B$2:$B$103,Terméklista!$N$2:$N$103,),0)," ") | Q37: =IFERROR(Rendelés[[#This Row],[Szükséges anyagmennyiség]]+(Rendelés[[#This Row],[Össz raklapok száma]]*25),"") | R37: {=(H37*_xlfn.XLOOKUP(B37,Terméklista!$B$2:$B$103,Terméklista!F$2:$F$103,))/1000} -> 38.5 | S37: =IFERROR(((H37/_xlfn.XLOOKUP(B37,Terméklista!$B$2:$B$103,Terméklista!$E$2:$E$103)*_xlfn.XLOOKUP(B37,Terméklista!$B$2:$B$103,Terméklista!$I$2:$I$103)))/3600," ") -> 1.1458333
A38: Ela Solutions Kft. | B38: 90ZA-ZK011-06 | C38: =IFERROR(_xlfn.XLOOKUP(B38,Terméklista!$B$2:$B$103,Terméklista!$C$2:$C$103,)," ") -> nagykulcs - 3mm | E38: M251035 | F38: =_xlfn.XLOOKUP(B38,Terméklista!$B$2:$B$103,Terméklista!$G$2:$G$103," ") -> Z410 | G38: 5681 | H38: 1000 | I38: 2025-04-14 | J38: 2025-05-05 | L38: x | N38: =IFERROR(_xlfn.XLOOKUP(B38,Terméklista!B36:B137,Terméklista!H36:H137)," ") | O38: =IFERROR(ROUNDUP(Rendelés[[#This Row],[Amount/pc]]/_xlfn.XLOOKUP(B38,Terméklista!$B$2:$B$103,Terméklista!$M$2:$M$103,),0)," ") | P38: =IFERROR(ROUNDUP(Rendelés[[#This Row],[Dobozok száma]]/_xlfn.XLOOKUP(B38,Terméklista!$B$2:$B$103,Terméklista!$N$2:$N$103,),0)," ") | Q38: =IFERROR(Rendelés[[#This Row],[Szükséges anyagmennyiség]]+(Rendelés[[#This Row],[Össz raklapok száma]]*25),"") | R38: {=(H38*_xlfn.XLOOKUP(B38,Terméklista!$B$2:$B$103,Terméklista!F$2:$F$103,))/1000} -> 47.55 | S38: =IFERROR(((H38/_xlfn.XLOOKUP(B38,Terméklista!$B$2:$B$103,Terméklista!$E$2:$E$103)*_xlfn.XLOOKUP(B38,Terméklista!$B$2:$B$103,Terméklista!$I$2:$I$103)))/3600," ") -> 2.0833333 | T38: 2025/39
A39: Seidel Gmbh&co Kg | B39: MA41 | C39: =IFERROR(_xlfn.XLOOKUP(B39,Terméklista!$B$2:$B$103,Terméklista!$C$2:$C$103,)," ") -> Zamak Gewicht | E39: M251039 | F39: =_xlfn.XLOOKUP(B39,Terméklista!$B$2:$B$103,Terméklista!$G$2:$G$103," ") -> Z410 | G39: 4500101272 | H39: 50000 | I39: 2025-04-23 | J39: 2025-08-04 | K39: 2025-08-05 | L39: x | M39: CMR | N39: =_xlfn.XLOOKUP(J39,Terméklista!$B$2:$B$103,Terméklista!$H$2:$H$103," ") | O39: =IFERROR(ROUNDUP(Rendelés[[#This Row],[Amount/pc]]/_xlfn.XLOOKUP(B39,Terméklista!$B$2:$B$103,Terméklista!$M$2:$M$103,),0)," ") -> 143 | P39: =IFERROR(ROUNDUP(Rendelés[[#This Row],[Dobozok száma]]/_xlfn.XLOOKUP(B39,Terméklista!$B$2:$B$103,Terméklista!$N$2:$N$103,),0)," ") -> 2 | Q39: =IFERROR(Rendelés[[#This Row],[Szükséges anyagmennyiség]]+(Rendelés[[#This Row],[Össz raklapok száma]]*25),"") -> 900 | R39: {=(H39*_xlfn.XLOOKUP(B39,Terméklista!$B$2:$B$103,Terméklista!F$2:$F$103,))/1000} -> 850 | S39: =IFERROR(((H39/_xlfn.XLOOKUP(B39,Terméklista!$B$2:$B$103,Terméklista!$E$2:$E$103)*_xlfn.XLOOKUP(B39,Terméklista!$B$2:$B$103,Terméklista!$I$2:$I$103)))/3600," ") -> 34.722222 | T39: 2025/56
A40: Ela Solutions Kft. | B40: 90ZA-H021-06 | C40: =IFERROR(_xlfn.XLOOKUP(B40,Terméklista!$B$2:$B$103,Terméklista!$C$2:$C$103,)," ") -> lakattal zárható zárház | E40: M251040 | F40: =_xlfn.XLOOKUP(B40,Terméklista!$B$2:$B$103,Terméklista!$G$2:$G$103," ") -> Z410 | G40: 5696 | H40: 200 | I40: 2025-04-25 | J40: 2025-04-28 | L40: x | N40: =IFERROR(_xlfn.XLOOKUP(B40,Terméklista!B41:B142,Terméklista!H41:H142)," ") | O40: =IFERROR(ROUNDUP(Rendelés[[#This Row],[Amount/pc]]/_xlfn.XLOOKUP(B40,Terméklista!$B$2:$B$103,Terméklista!$M$2:$M$103,),0)," ") | P40: =IFERROR(ROUNDUP(Rendelés[[#This Row],[Dobozok száma]]/_xlfn.XLOOKUP(B40,Terméklista!$B$2:$B$103,Terméklista!$N$2:$N$103,),0)," ") | Q40: =IFERROR(Rendelés[[#This Row],[Szükséges anyagmennyiség]]+(Rendelés[[#This Row],[Össz raklapok száma]]*25),"") | R40: {=(H40*_xlfn.XLOOKUP(B40,Terméklista!$B$2:$B$103,Terméklista!F$2:$F$103,))/1000} -> 18.512 | S40: =IFERROR(((H40/_xlfn.XLOOKUP(B40,Terméklista!$B$2:$B$103,Terméklista!$E$2:$E$103)*_xlfn.XLOOKUP(B40,Terméklista!$B$2:$B$103,Terméklista!$I$2:$I$103)))/3600," ") -> 0.41666667 | T40: 2025/39
A41: Ela Solutions Kft. | B41: 90ZA-ZK007-06 | C41: =IFERROR(_xlfn.XLOOKUP(B41,Terméklista!$B$2:$B$103,Terméklista!$C$2:$C$103,)," ") -> kulcs 10mm 3szög | E41: M251040 | F41: =_xlfn.XLOOKUP(B41,Terméklista!B42:B143,Terméklista!G42:G143," ") | G41: 5696 | H41: 300 | I41: 2025-04-25 | J41: 2025-04-28 | L41: x | M41: CMR | N41: =IFERROR(_xlfn.XLOOKUP(B41,Terméklista!B42:B143,Terméklista!H42:H143)," ") | O41: =IFERROR(ROUNDUP(Rendelés[[#This Row],[Amount/pc]]/_xlfn.XLOOKUP(B41,Terméklista!$B$2:$B$103,Terméklista!$M$2:$M$103,),0)," ") | P41: =IFERROR(ROUNDUP(Rendelés[[#This Row],[Dobozok száma]]/_xlfn.XLOOKUP(B41,Terméklista!$B$2:$B$103,Terméklista!$N$2:$N$103,),0)," ") | Q41: =IFERROR(Rendelés[[#This Row],[Szükséges anyagmennyiség]]+(Rendelés[[#This Row],[Össz raklapok száma]]*25),"") | R41: {=(H41*_xlfn.XLOOKUP(B41,Terméklista!$B$2:$B$103,Terméklista!F$2:$F$103,))/1000} -> 7.59 | S41: =IFERROR(((H41/_xlfn.XLOOKUP(B41,Terméklista!$B$2:$B$103,Terméklista!$E$2:$E$103)*_xlfn.XLOOKUP(B41,Terméklista!$B$2:$B$103,Terméklista!$I$2:$I$103)))/3600," ") -> 0.625 | T41: 2025/37
A42: Systec Pos-Technology Gmbh | B42: Sperrhacken Zn S | C42: =IFERROR(_xlfn.XLOOKUP(B42,Terméklista!$B$2:$B$103,Terméklista!$C$2:$C$103,)," ") -> Euroloc 1 | E42: M251041 | F42: =_xlfn.XLOOKUP(B42,Terméklista!$B$2:$B$103,Terméklista!$G$2:$G$103," ") -> Z410 | G42: 26764 | H42: 10000 | I42: 2025-04-30 | J42: 2025-06-04 | K42: 2025-06-04 | L42: x | N42: =_xlfn.XLOOKUP(J42,Terméklista!$B$2:$B$103,Terméklista!$H$2:$H$103," ") | O42: =IFERROR(ROUNDUP(Rendelés[[#This Row],[Amount/pc]]/_xlfn.XLOOKUP(B42,Terméklista!$B$2:$B$103,Terméklista!$M$2:$M$103,),0)," ") -> 20 | P42: =IFERROR(ROUNDUP(Rendelés[[#This Row],[Dobozok száma]]/_xlfn.XLOOKUP(B42,Terméklista!$B$2:$B$103,Terméklista!$N$2:$N$103,),0)," ") -> 1 | Q42: =IFERROR(Rendelés[[#This Row],[Szükséges anyagmennyiség]]+(Rendelés[[#This Row],[Össz raklapok száma]]*25),"") -> 212 | R42: {=(H42*_xlfn.XLOOKUP(B42,Terméklista!$B$2:$B$103,Terméklista!F$2:$F$103,))/1000} -> 187 | S42: =IFERROR(((H42/_xlfn.XLOOKUP(B42,Terméklista!$B$2:$B$103,Terméklista!$E$2:$E$103)*_xlfn.XLOOKUP(B42,Terméklista!$B$2:$B$103,Terméklista!$I$2:$I$103)))/3600," ") -> 20.833333
A43: Arsisco AMO Pack LLC | C43: =IFERROR(_xlfn.XLOOKUP(B43,Terméklista!$B$2:$B$103,Terméklista!$C$2:$C$103,)," ") -> 0 | D43: szerszám - sin5 | E43: M251044 | F43: =_xlfn.XLOOKUP(B43,Terméklista!$B$2:$B$103,Terméklista!$G$2:$G$103," ") -> 0 | I43: 2025-05-07 | J43: 2025-07-16 | N43: =_xlfn.XLOOKUP(J43,Terméklista!$B$2:$B$103,Terméklista!$H$2:$H$103," ") | O43: =IFERROR(ROUNDUP(Rendelés[[#This Row],[Amount/pc]]/_xlfn.XLOOKUP(B43,Terméklista!$B$2:$B$103,Terméklista!$M$2:$M$103,),0)," ") | P43: =IFERROR(ROUNDUP(Rendelés[[#This Row],[Dobozok száma]]/_xlfn.XLOOKUP(B43,Terméklista!$B$2:$B$103,Terméklista!$N$2:$N$103,),0)," ") | Q43: =IFERROR(Rendelés[[#This Row],[Szükséges anyagmennyiség]]+(Rendelés[[#This Row],[Össz raklapok száma]]*25),"") | R43: {=(H43*_xlfn.XLOOKUP(B43,Terméklista!$B$2:$B$103,Terméklista!F$2:$F$103,))/1000} -> 0 | S43: =IFERROR(((H43/_xlfn.XLOOKUP(B43,Terméklista!$B$2:$B$103,Terméklista!$E$2:$E$103)*_xlfn.XLOOKUP(B43,Terméklista!$B$2:$B$103,Terméklista!$I$2:$I$103)))/3600," ") | U43: szünetel
A44: Ela Solutions Kft. | B44: 91ZA-F002-06 | C44: =IFERROR(_xlfn.XLOOKUP(B44,Terméklista!$B$2:$B$103,Terméklista!$C$2:$C$103,)," ") -> vésznyitó | E44: M251042 | F44: =_xlfn.XLOOKUP(B44,Terméklista!$B$2:$B$103,Terméklista!$G$2:$G$103," ") -> Z410 | G44: 5719 | H44: 200 | I44: 2025-05-14 | J44: 2025-06-02 | K44: 2025-06-16 | L44: x | N44: =_xlfn.XLOOKUP(J44,Terméklista!$B$2:$B$103,Terméklista!$H$2:$H$103," ") | O44: =IFERROR(ROUNDUP(Rendelés[[#This Row],[Amount/pc]]/_xlfn.XLOOKUP(B44,Terméklista!$B$2:$B$103,Terméklista!$M$2:$M$103,),0)," ") | P44: =IFERROR(ROUNDUP(Rendelés[[#This Row],[Dobozok száma]]/_xlfn.XLOOKUP(B44,Terméklista!$B$2:$B$103,Terméklista!$N$2:$N$103,),0)," ") | Q44: =IFERROR(Rendelés[[#This Row],[Szükséges anyagmennyiség]]+(Rendelés[[#This Row],[Össz raklapok száma]]*25),"") | R44: {=(H44*_xlfn.XLOOKUP(B44,Terméklista!$B$2:$B$103,Terméklista!F$2:$F$103,))/1000} -> 11.22 | S44: =IFERROR(((H44/_xlfn.XLOOKUP(B44,Terméklista!$B$2:$B$103,Terméklista!$E$2:$E$103)*_xlfn.XLOOKUP(B44,Terméklista!$B$2:$B$103,Terméklista!$I$2:$I$103)))/3600," ") -> 0.83333333 | T44: 2025/47
A45: Ela Solutions Kft. | B45: 91ZA-H0006-06 | C45: =IFERROR(_xlfn.XLOOKUP(B45,Terméklista!$B$2:$B$103,Terméklista!$C$2:$C$103,)," ") -> zártest | E45: M251042 | F45: =_xlfn.XLOOKUP(B45,Terméklista!$B$2:$B$103,Terméklista!$G$2:$G$103," ") -> Z410 | G45: 5719 | H45: 200 | I45: 2025-05-14 | J45: 2025-06-02 | K45: 2025-06-16 | L45: x | N45: =_xlfn.XLOOKUP(J45,Terméklista!$B$2:$B$103,Terméklista!$H$2:$H$103," ") | O45: =IFERROR(ROUNDUP(Rendelés[[#This Row],[Amount/pc]]/_xlfn.XLOOKUP(B45,Terméklista!$B$2:$B$103,Terméklista!$M$2:$M$103,),0)," ") | P45: =IFERROR(ROUNDUP(Rendelés[[#This Row],[Dobozok száma]]/_xlfn.XLOOKUP(B45,Terméklista!$B$2:$B$103,Terméklista!$N$2:$N$103,),0)," ") | Q45: =IFERROR(Rendelés[[#This Row],[Szükséges anyagmennyiség]]+(Rendelés[[#This Row],[Össz raklapok száma]]*25),"") | R45: {=(H45*_xlfn.XLOOKUP(B45,Terméklista!$B$2:$B$103,Terméklista!F$2:$F$103,))/1000} -> 60 | S45: =IFERROR(((H45/_xlfn.XLOOKUP(B45,Terméklista!$B$2:$B$103,Terméklista!$E$2:$E$103)*_xlfn.XLOOKUP(B45,Terméklista!$B$2:$B$103,Terméklista!$I$2:$I$103)))/3600," ") -> 0.83333333 | T45: 2025/47
A46: Ela Solutions Kft. | B46: 91ZA-NY003-00 | C46: =IFERROR(_xlfn.XLOOKUP(B46,Terméklista!$B$2:$B$103,Terméklista!$C$2:$C$103,)," ") -> zárnyelv | E46: M251042 | F46: =_xlfn.XLOOKUP(B46,Terméklista!$B$2:$B$103,Terméklista!$G$2:$G$103," ") -> Z410 | G46: 5719 | H46: 200 | I46: 2025-05-14 | J46: 2025-06-02 | K46: 2025-06-16 | L46: x | N46: =_xlfn.XLOOKUP(J46,Terméklista!$B$2:$B$103,Terméklista!$H$2:$H$103," ") | O46: =IFERROR(ROUNDUP(Rendelés[[#This Row],[Amount/pc]]/_xlfn.XLOOKUP(B46,Terméklista!$B$2:$B$103,Terméklista!$M$2:$M$103,),0)," ") | P46: =IFERROR(ROUNDUP(Rendelés[[#This Row],[Dobozok száma]]/_xlfn.XLOOKUP(B46,Terméklista!$B$2:$B$103,Terméklista!$N$2:$N$103,),0)," ") | Q46: =IFERROR(Rendelés[[#This Row],[Szükséges anyagmennyiség]]+(Rendelés[[#This Row],[Össz raklapok száma]]*25),"") | R46: {=(H46*_xlfn.XLOOKUP(B46,Terméklista!$B$2:$B$103,Terméklista!F$2:$F$103,))/1000} -> 5.02 | S46: =IFERROR(((H46/_xlfn.XLOOKUP(B46,Terméklista!$B$2:$B$103,Terméklista!$E$2:$E$103)*_xlfn.XLOOKUP(B46,Terméklista!$B$2:$B$103,Terméklista!$I$2:$I$103)))/3600," ") -> 0.83333333 | T46: 2025/47
A47: Seidel Gmbh&co Kg | B47: MA41 | C47: =IFERROR(_xlfn.XLOOKUP(B47,Terméklista!$B$2:$B$103,Terméklista!$C$2:$C$103,)," ") -> Zamak Gewicht | D47: POS010 | E47: M251043 | F47: =_xlfn.XLOOKUP(B47,Terméklista!$B$2:$B$103,Terméklista!$G$2:$G$103," ") -> Z410 | G47: 4500101596 | H47: 50000 | I47: 2025-05-19 | J47: 2025-09-08 | K47: 2025-09-05 | L47: x | M47: CMR | N47: =_xlfn.XLOOKUP(J47,Terméklista!$B$2:$B$103,Terméklista!$H$2:$H$103," ") | O47: =IFERROR(ROUNDUP(Rendelés[[#This Row],[Amount/pc]]/_xlfn.XLOOKUP(B47,Terméklista!$B$2:$B$103,Terméklista!$M$2:$M$103,),0)," ") -> 143 | P47: =IFERROR(ROUNDUP(Rendelés[[#This Row],[Dobozok száma]]/_xlfn.XLOOKUP(B47,Terméklista!$B$2:$B$103,Terméklista!$N$2:$N$103,),0)," ") -> 2 | Q47: =IFERROR(Rendelés[[#This Row],[Szükséges anyagmennyiség]]+(Rendelés[[#This Row],[Össz raklapok száma]]*25),"") -> 900 | R47: {=(H47*_xlfn.XLOOKUP(B47,Terméklista!$B$2:$B$103,Terméklista!F$2:$F$103,))/1000} -> 850 | S47: =IFERROR(((H47/_xlfn.XLOOKUP(B47,Terméklista!$B$2:$B$103,Terméklista!$E$2:$E$103)*_xlfn.XLOOKUP(B47,Terméklista!$B$2:$B$103,Terméklista!$I$2:$I$103)))/3600," ") -> 34.722222 | T47: 2025/61
A48: Ela Solutions Kft. | B48: 90ZA-ZK011-06 | C48: =IFERROR(_xlfn.XLOOKUP(B48,Terméklista!$B$2:$B$103,Terméklista!$C$2:$C$103,)," ") -> nagykulcs - 3mm | E48: M251049 | F48: =_xlfn.XLOOKUP(B48,Terméklista!$B$2:$B$103,Terméklista!$G$2:$G$103," ") -> Z410 | G48: 5743 | H48: 1000 | I48: 2025-05-26 | J48: 2025-06-17 | K48: 2025-06-16 | L48: x | N48: =IFERROR(_xlfn.XLOOKUP(B48,Terméklista!B52:B153,Terméklista!H52:H153)," ") | O48: =IFERROR(ROUNDUP(Rendelés[[#This Row],[Amount/pc]]/_xlfn.XLOOKUP(B48,Terméklista!$B$2:$B$103,Terméklista!$M$2:$M$103,),0)," ") | P48: =IFERROR(ROUNDUP(Rendelés[[#This Row],[Dobozok száma]]/_xlfn.XLOOKUP(B48,Terméklista!$B$2:$B$103,Terméklista!$N$2:$N$103,),0)," ") | Q48: =IFERROR(Rendelés[[#This Row],[Szükséges anyagmennyiség]]+(Rendelés[[#This Row],[Össz raklapok száma]]*25),"") | R48: {=(H48*_xlfn.XLOOKUP(B48,Terméklista!$B$2:$B$103,Terméklista!F$2:$F$103,))/1000} -> 47.55 | S48: =IFERROR(((H48/_xlfn.XLOOKUP(B48,Terméklista!$B$2:$B$103,Terméklista!$E$2:$E$103)*_xlfn.XLOOKUP(B48,Terméklista!$B$2:$B$103,Terméklista!$I$2:$I$103)))/3600," ") -> 2.0833333 | T48: 2025/47
A49: Ela Solutions Kft. | B49: 90ZA-ZK008-06 | C49: =IFERROR(_xlfn.XLOOKUP(B49,Terméklista!$B$2:$B$103,Terméklista!$C$2:$C$103,)," ") -> kiskulcs - 3mm | D49: COALSA logo | E49: M251050 | F49: =_xlfn.XLOOKUP(B49,Terméklista!$B$2:$B$103,Terméklista!$G$2:$G$103," ") -> Z410 | G49: 5745 | H49: 2000 | I49: 2025-05-27 | J49: 2025-05-28 | K49: 2025-05-29 | L49: x | M49: CMR | N49: =IFERROR(_xlfn.XLOOKUP(B49,Terméklista!B53:B154,Terméklista!H53:H154)," ") | O49: =IFERROR(ROUNDUP(Rendelés[[#This Row],[Amount/pc]]/_xlfn.XLOOKUP(B49,Terméklista!$B$2:$B$103,Terméklista!$M$2:$M$103,),0)," ") | P49: =IFERROR(ROUNDUP(Rendelés[[#This Row],[Dobozok száma]]/_xlfn.XLOOKUP(B49,Terméklista!$B$2:$B$103,Terméklista!$N$2:$N$103,),0)," ") | Q49: =IFERROR(Rendelés[[#This Row],[Szükséges anyagmennyiség]]+(Rendelés[[#This Row],[Össz raklapok száma]]*25),"") | R49: {=(H49*_xlfn.XLOOKUP(B49,Terméklista!$B$2:$B$103,Terméklista!F$2:$F$103,))/1000} -> 45.6 | S49: =IFERROR(((H49/_xlfn.XLOOKUP(B49,Terméklista!$B$2:$B$103,Terméklista!$E$2:$E$103)*_xlfn.XLOOKUP(B49,Terméklista!$B$2:$B$103,Terméklista!$I$2:$I$103)))/3600," ") -> 4.1666667 | T49: 2025/41
A50: Seidel Gmbh&co Kg | B50: MB01 | C50: =IFERROR(_xlfn.XLOOKUP(B50,Terméklista!$B$2:$B$103,Terméklista!$C$2:$C$103,)," ") -> Zamak Gewicht | E50: M251059 Pos-10 | F50: Z410 | G50: 4500101783 | H50: 25000 | I50: 2025-06-03 | J50: 2025-09-08 | K50: 2025-09-05 | L50: x | M50: CMR | N50: =IFERROR(_xlfn.XLOOKUP(B50,Terméklista!B55:B156,Terméklista!H55:H156)," ") -> 0 | O50: =IFERROR(ROUNDUP(Rendelés[[#This Row],[Amount/pc]]/_xlfn.XLOOKUP(B50,Terméklista!$B$2:$B$103,Terméklista!$M$2:$M$103,),0)," ") -> 50 | P50: =IFERROR(ROUNDUP(Rendelés[[#This Row],[Dobozok száma]]/_xlfn.XLOOKUP(B50,Terméklista!$B$2:$B$103,Terméklista!$N$2:$N$103,),0)," ") -> 1 | Q50: =IFERROR(Rendelés[[#This Row],[Szükséges anyagmennyiség]]+(Rendelés[[#This Row],[Össz raklapok száma]]*25),"") -> 560.75 | R50: {=(H50*_xlfn.XLOOKUP(B50,Terméklista!$B$2:$B$103,Terméklista!F$2:$F$103,))/1000} -> 535.75 | S50: =IFERROR(((H50/_xlfn.XLOOKUP(B50,Terméklista!$B$2:$B$103,Terméklista!$E$2:$E$103)*_xlfn.XLOOKUP(B50,Terméklista!$B$2:$B$103,Terméklista!$I$2:$I$103)))/3600," ") -> 34.722222 | T50: 2025/61
A51: Seidel Gmbh&co Kg | B51: MA66 | C51: =IFERROR(_xlfn.XLOOKUP(B51,Terméklista!$B$2:$B$103,Terméklista!$C$2:$C$103,)," ") -> Zamak Gewicht | D51: POSS010 | F51: =_xlfn.XLOOKUP(B51,Terméklista!B61:B162,Terméklista!G61:G162," ") -> Z410 | G51: 4500102067 | H51: 350000 | I51: 2025-06-23 | J51: 2025-08-11 | K51: 2025-08-12 | L51: x | M51: CMR | N51: =IFERROR(_xlfn.XLOOKUP(B51,Terméklista!B61:B162,Terméklista!H61:H162)," ") -> 0 | O51: =IFERROR(ROUNDUP(Rendelés[[#This Row],[Amount/pc]]/_xlfn.XLOOKUP(B51,Terméklista!$B$2:$B$103,Terméklista!$M$2:$M$103,),0)," ") -> 700 | P51: =IFERROR(ROUNDUP(Rendelés[[#This Row],[Dobozok száma]]/_xlfn.XLOOKUP(B51,Terméklista!$B$2:$B$103,Terméklista!$N$2:$N$103,),0)," ") -> 8 | Q51: =IFERROR(Rendelés[[#This Row],[Szükséges anyagmennyiség]]+(Rendelés[[#This Row],[Össz raklapok száma]]*25),"") -> 3875 | R51: {=(H51*_xlfn.XLOOKUP(B51,Terméklista!$B$2:$B$103,Terméklista!F$2:$F$103,))/1000} -> 3675 | S51: =IFERROR(((H51/_xlfn.XLOOKUP(B51,Terméklista!$B$2:$B$103,Terméklista!$E$2:$E$103)*_xlfn.XLOOKUP(B51,Terméklista!$B$2:$B$103,Terméklista!$I$2:$I$103)))/3600," ") -> 243.05556 | T51: 2025/73
A52: Ela Solutions Kft. | B52: 90ZA-ZK001-06 | C52: =IFERROR(_xlfn.XLOOKUP(B52,Terméklista!$B$2:$B$103,Terméklista!$C$2:$C$103,)," ") -> 0 | F52: =_xlfn.XLOOKUP(B52,Terméklista!B62:B163,Terméklista!G62:G163," ") | G52: 5783 | H52: 2000 | I52: 2025-06-24 | J52: 2025-06-25 | L52: x | N52: =IFERROR(_xlfn.XLOOKUP(B52,Terméklista!B62:B163,Terméklista!H62:H163)," ") | O52: =IFERROR(ROUNDUP(Rendelés[[#This Row],[Amount/pc]]/_xlfn.XLOOKUP(B52,Terméklista!$B$2:$B$103,Terméklista!$M$2:$M$103,),0)," ") | P52: =IFERROR(ROUNDUP(Rendelés[[#This Row],[Dobozok száma]]/_xlfn.XLOOKUP(B52,Terméklista!$B$2:$B$103,Terméklista!$N$2:$N$103,),0)," ") | Q52: =IFERROR(Rendelés[[#This Row],[Szükséges anyagmennyiség]]+(Rendelés[[#This Row],[Össz raklapok száma]]*25),"") | R52: {=(H52*_xlfn.XLOOKUP(B52,Terméklista!$B$2:$B$103,Terméklista!F$2:$F$103,))/1000} -> 44.68 | S52: =IFERROR(((H52/_xlfn.XLOOKUP(B52,Terméklista!$B$2:$B$103,Terméklista!$E$2:$E$103)*_xlfn.XLOOKUP(B52,Terméklista!$B$2:$B$103,Terméklista!$I$2:$I$103)))/3600," ") -> 4.1666667 | T52: 2025/51
A53: Ela Solutions Kft. | B53: 90ZA-ZK011-06 | C53: =IFERROR(_xlfn.XLOOKUP(B53,Terméklista!$B$2:$B$103,Terméklista!$C$2:$C$103,)," ") -> nagykulcs - 3mm | F53: =_xlfn.XLOOKUP(B53,Terméklista!B64:B165,Terméklista!G64:G165," ") | G53: 5813 | H53: 1000 | I53: 2025-07-10 | J53: 2025-07-17 | K53: 2025-07-15 | L53: x | N53: =IFERROR(_xlfn.XLOOKUP(B53,Terméklista!B64:B165,Terméklista!H64:H165)," ") | O53: =IFERROR(ROUNDUP(Rendelés[[#This Row],[Amount/pc]]/_xlfn.XLOOKUP(B53,Terméklista!$B$2:$B$103,Terméklista!$M$2:$M$103,),0)," ") | P53: =IFERROR(ROUNDUP(Rendelés[[#This Row],[Dobozok száma]]/_xlfn.XLOOKUP(B53,Terméklista!$B$2:$B$103,Terméklista!$N$2:$N$103,),0)," ") | Q53: =IFERROR(Rendelés[[#This Row],[Szükséges anyagmennyiség]]+(Rendelés[[#This Row],[Össz raklapok száma]]*25),"") | R53: {=(H53*_xlfn.XLOOKUP(B53,Terméklista!$B$2:$B$103,Terméklista!F$2:$F$103,))/1000} -> 47.55 | S53: =IFERROR(((H53/_xlfn.XLOOKUP(B53,Terméklista!$B$2:$B$103,Terméklista!$E$2:$E$103)*_xlfn.XLOOKUP(B53,Terméklista!$B$2:$B$103,Terméklista!$I$2:$I$103)))/3600," ") -> 2.0833333 | T53: 2025/54
A54: Systec Pos-Technology Gmbh | B54: Sperritzteil-2 | C54: =IFERROR(_xlfn.XLOOKUP(B54,Terméklista!$B$2:$B$103,Terméklista!$C$2:$C$103,)," ") -> Smartstop-2 | F54: =_xlfn.XLOOKUP(B54,Terméklista!B65:B166,Terméklista!G65:G166," ") -> Z410 | G54: 26935 | H54: 10000 | I54: 2025-07-17 | J54: 2025-08-19 | K54: 2025-08-13 | L54: x | M54: CMR | N54: =IFERROR(_xlfn.XLOOKUP(B54,Terméklista!B65:B166,Terméklista!H65:H166)," ") -> 0 | O54: =IFERROR(ROUNDUP(Rendelés[[#This Row],[Amount/pc]]/_xlfn.XLOOKUP(B54,Terméklista!$B$2:$B$103,Terméklista!$M$2:$M$103,),0)," ") -> 67 | P54: =IFERROR(ROUNDUP(Rendelés[[#This Row],[Dobozok száma]]/_xlfn.XLOOKUP(B54,Terméklista!$B$2:$B$103,Terméklista!$N$2:$N$103,),0)," ") -> 1 | Q54: =IFERROR(Rendelés[[#This Row],[Szükséges anyagmennyiség]]+(Rendelés[[#This Row],[Össz raklapok száma]]*25),"") -> 695 | R54: {=(H54*_xlfn.XLOOKUP(B54,Terméklista!$B$2:$B$103,Terméklista!F$2:$F$103,))/1000} -> 670 | S54: =IFERROR(((H54/_xlfn.XLOOKUP(B54,Terméklista!$B$2:$B$103,Terméklista!$E$2:$E$103)*_xlfn.XLOOKUP(B54,Terméklista!$B$2:$B$103,Terméklista!$I$2:$I$103)))/3600," ") -> 6.9444444 | T54: 2025/59
A55: Systec Pos-Technology Gmbh | B55: W1L-S6 | C55: =IFERROR(_xlfn.XLOOKUP(B55,Terméklista!$B$2:$B$103,Terméklista!$C$2:$C$103,)," ") -> Verdrehsicherung | D55: felületkezelés kell | F55: =_xlfn.XLOOKUP(B55,Terméklista!B66:B167,Terméklista!G66:G167," ") -> Z410 | G55: 26978 | H55: 5000 | I55: 2025-07-28 | J55: 2025-08-20 | K55: 2025-08-26 | L55: x | M55: CMR | N55: =IFERROR(_xlfn.XLOOKUP(B55,Terméklista!B66:B167,Terméklista!H66:H167)," ") -> Galvanizálás | O55: =IFERROR(ROUNDUP(Rendelés[[#This Row],[Amount/pc]]/_xlfn.XLOOKUP(B55,Terméklista!$B$2:$B$103,Terméklista!$M$2:$M$103,),0)," ") -> 25 | P55: =IFERROR(ROUNDUP(Rendelés[[#This Row],[Dobozok száma]]/_xlfn.XLOOKUP(B55,Terméklista!$B$2:$B$103,Terméklista!$N$2:$N$103,),0)," ") -> 1 | Q55: =IFERROR(Rendelés[[#This Row],[Szükséges anyagmennyiség]]+(Rendelés[[#This Row],[Össz raklapok száma]]*25),"") -> 355 | R55: {=(H55*_xlfn.XLOOKUP(B55,Terméklista!$B$2:$B$103,Terméklista!F$2:$F$103,))/1000} -> 330 | S55: =IFERROR(((H55/_xlfn.XLOOKUP(B55,Terméklista!$B$2:$B$103,Terméklista!$E$2:$E$103)*_xlfn.XLOOKUP(B55,Terméklista!$B$2:$B$103,Terméklista!$I$2:$I$103)))/3600," ") -> 10.416667 | T55: 2025/60
A56: Systec Pos-Technology Gmbh | B56: W1R-S6 | C56: =IFERROR(_xlfn.XLOOKUP(B56,Terméklista!$B$2:$B$103,Terméklista!$C$2:$C$103,)," ") -> Verdrehsicherung | D56: felületkezelés kell | F56: =_xlfn.XLOOKUP(B56,Terméklista!B67:B168,Terméklista!G67:G168," ") -> Z410 | G56: 26978 | H56: 5000 | I56: 2025-07-28 | J56: 2025-08-20 | K56: 2025-08-26 | L56: x | M56: CMR | N56: =IFERROR(_xlfn.XLOOKUP(B56,Terméklista!B67:B168,Terméklista!H67:H168)," ") -> Galvanizálás | O56: =IFERROR(ROUNDUP(Rendelés[[#This Row],[Amount/pc]]/_xlfn.XLOOKUP(B56,Terméklista!$B$2:$B$103,Terméklista!$M$2:$M$103,),0)," ") -> 25 | P56: =IFERROR(ROUNDUP(Rendelés[[#This Row],[Dobozok száma]]/_xlfn.XLOOKUP(B56,Terméklista!$B$2:$B$103,Terméklista!$N$2:$N$103,),0)," ") -> 1 | Q56: =IFERROR(Rendelés[[#This Row],[Szükséges anyagmennyiség]]+(Rendelés[[#This Row],[Össz raklapok száma]]*25),"") -> 295.5 | R56: {=(H56*_xlfn.XLOOKUP(B56,Terméklista!$B$2:$B$103,Terméklista!F$2:$F$103,))/1000} -> 270.5 | S56: =IFERROR(((H56/_xlfn.XLOOKUP(B56,Terméklista!$B$2:$B$103,Terméklista!$E$2:$E$103)*_xlfn.XLOOKUP(B56,Terméklista!$B$2:$B$103,Terméklista!$I$2:$I$103)))/3600," ") -> 10.416667 | T56: 2025/60
A57: Ela Solutions Kft. | B57: 90ZA-ZK001-06 | C57: =IFERROR(_xlfn.XLOOKUP(B57,Terméklista!$B$2:$B$103,Terméklista!$C$2:$C$103,)," ") -> 0 | F57: =_xlfn.XLOOKUP(B57,Terméklista!B68:B169,Terméklista!G68:G169," ") | G57: 5847 | H57: 1300 | I57: 2025-08-13 | J57: 2025-08-18 | K57: 2025-08-18 | L57: x | M57: CMR | N57: =IFERROR(_xlfn.XLOOKUP(B57,Terméklista!B68:B169,Terméklista!H68:H169)," ") | O57: =IFERROR(ROUNDUP(Rendelés[[#This Row],[Amount/pc]]/_xlfn.XLOOKUP(B57,Terméklista!$B$2:$B$103,Terméklista!$M$2:$M$103,),0)," ") | P57: =IFERROR(ROUNDUP(Rendelés[[#This Row],[Dobozok száma]]/_xlfn.XLOOKUP(B57,Terméklista!$B$2:$B$103,Terméklista!$N$2:$N$103,),0)," ") | Q57: =IFERROR(Rendelés[[#This Row],[Szükséges anyagmennyiség]]+(Rendelés[[#This Row],[Össz raklapok száma]]*25),"") | R57: {=(H57*_xlfn.XLOOKUP(B57,Terméklista!$B$2:$B$103,Terméklista!F$2:$F$103,))/1000} -> 29.042 | S57: =IFERROR(((H57/_xlfn.XLOOKUP(B57,Terméklista!$B$2:$B$103,Terméklista!$E$2:$E$103)*_xlfn.XLOOKUP(B57,Terméklista!$B$2:$B$103,Terméklista!$I$2:$I$103)))/3600," ") -> 2.7083333
A58: Ela Solutions Kft. | B58: 90ZA-ZK011-06 | C58: =IFERROR(_xlfn.XLOOKUP(B58,Terméklista!$B$2:$B$103,Terméklista!$C$2:$C$103,)," ") -> nagykulcs - 3mm | F58: =_xlfn.XLOOKUP(B58,Terméklista!B69:B170,Terméklista!G69:G170," ") | G58: 5854 | H58: 1000 | I58: 2025-08-15 | J58: 2025-09-15 | L58: x | M58: CMR | N58: =IFERROR(_xlfn.XLOOKUP(B58,Terméklista!B69:B170,Terméklista!H69:H170)," ") | O58: =IFERROR(ROUNDUP(Rendelés[[#This Row],[Amount/pc]]/_xlfn.XLOOKUP(B58,Terméklista!$B$2:$B$103,Terméklista!$M$2:$M$103,),0)," ") | P58: =IFERROR(ROUNDUP(Rendelés[[#This Row],[Dobozok száma]]/_xlfn.XLOOKUP(B58,Terméklista!$B$2:$B$103,Terméklista!$N$2:$N$103,),0)," ") | Q58: =IFERROR(Rendelés[[#This Row],[Szükséges anyagmennyiség]]+(Rendelés[[#This Row],[Össz raklapok száma]]*25),"") | R58: {=(H58*_xlfn.XLOOKUP(B58,Terméklista!$B$2:$B$103,Terméklista!F$2:$F$103,))/1000} -> 47.55 | S58: =IFERROR(((H58/_xlfn.XLOOKUP(B58,Terméklista!$B$2:$B$103,Terméklista!$E$2:$E$103)*_xlfn.XLOOKUP(B58,Terméklista!$B$2:$B$103,Terméklista!$I$2:$I$103)))/3600," ") -> 2.0833333 | T58: 2025/63
A59: Systec Pos-Technology Gmbh | B59: Rasthebel-2 | C59: =IFERROR(_xlfn.XLOOKUP(B59,Terméklista!$B$2:$B$103,Terméklista!$C$2:$C$103,)," ") -> Smartstop-2 | F59: =_xlfn.XLOOKUP(B59,Terméklista!B72:B173,Terméklista!G72:G173," ") -> Z410 | G59: 27048 | H59: 10000 | I59: 2025-08-25 | J59: 2025-09-24 | K59: 2025-09-18 | L59: x | M59: CMR | N59: =IFERROR(_xlfn.XLOOKUP(B59,Terméklista!B72:B173,Terméklista!H72:H173)," ") -> 0 | O59: =IFERROR(ROUNDUP(Rendelés[[#This Row],[Amount/pc]]/_xlfn.XLOOKUP(B59,Terméklista!$B$2:$B$103,Terméklista!$M$2:$M$103,),0)," ") -> 16 | P59: =IFERROR(ROUNDUP(Rendelés[[#This Row],[Dobozok száma]]/_xlfn.XLOOKUP(B59,Terméklista!$B$2:$B$103,Terméklista!$N$2:$N$103,),0)," ") -> 1 | Q59: =IFERROR(Rendelés[[#This Row],[Szükséges anyagmennyiség]]+(Rendelés[[#This Row],[Össz raklapok száma]]*25),"") -> 175.3 | R59: {=(H59*_xlfn.XLOOKUP(B59,Terméklista!$B$2:$B$103,Terméklista!F$2:$F$103,))/1000} -> 150.3 | S59: =IFERROR(((H59/_xlfn.XLOOKUP(B59,Terméklista!$B$2:$B$103,Terméklista!$E$2:$E$103)*_xlfn.XLOOKUP(B59,Terméklista!$B$2:$B$103,Terméklista!$I$2:$I$103)))/3600," ") -> 6.9444444 | T59: 2025/64
A60: Seidel Gmbh&co Kg | B60: MA41 | C60: =IFERROR(_xlfn.XLOOKUP(B60,Terméklista!$B$2:$B$103,Terméklista!$C$2:$C$103,)," ") -> Zamak Gewicht | D60: POS010 | F60: =_xlfn.XLOOKUP(B60,Terméklista!B70:B171,Terméklista!G70:G171," ") -> Z410 | G60: 4500102857 | H60: 50000 | I60: 2025-08-26 | J60: 2026-01-05 | L60: x | M60: CMR | N60: =IFERROR(_xlfn.XLOOKUP(B60,Terméklista!B70:B171,Terméklista!H70:H171)," ") -> 0 | O60: =IFERROR(ROUNDUP(Rendelés[[#This Row],[Amount/pc]]/_xlfn.XLOOKUP(B60,Terméklista!$B$2:$B$103,Terméklista!$M$2:$M$103,),0)," ") -> 143 | P60: =IFERROR(ROUNDUP(Rendelés[[#This Row],[Dobozok száma]]/_xlfn.XLOOKUP(B60,Terméklista!$B$2:$B$103,Terméklista!$N$2:$N$103,),0)," ") -> 2 | Q60: =IFERROR(Rendelés[[#This Row],[Szükséges anyagmennyiség]]+(Rendelés[[#This Row],[Össz raklapok száma]]*25),"") -> 900 | R60: {=(H60*_xlfn.XLOOKUP(B60,Terméklista!$B$2:$B$103,Terméklista!F$2:$F$103,))/1000} -> 850 | S60: =IFERROR(((H60/_xlfn.XLOOKUP(B60,Terméklista!$B$2:$B$103,Terméklista!$E$2:$E$103)*_xlfn.XLOOKUP(B60,Terméklista!$B$2:$B$103,Terméklista!$I$2:$I$103)))/3600," ") -> 34.722222 | T60: 2026/81
A61: Seidel Gmbh&co Kg | B61: MA41 | C61: =IFERROR(_xlfn.XLOOKUP(B61,Terméklista!$B$2:$B$103,Terméklista!$C$2:$C$103,)," ") -> Zamak Gewicht | F61: =_xlfn.XLOOKUP(B61,Terméklista!B71:B172,Terméklista!G71:G172," ") -> Z410 | G61: 4500102961 | H61: 50000 | I61: 2025-09-01 | J61: 2025-11-10 | L61: x | M61: CMR | N61: =IFERROR(_xlfn.XLOOKUP(B61,Terméklista!B71:B172,Terméklista!H71:H172)," ") -> 0 | O61: =IFERROR(ROUNDUP(Rendelés[[#This Row],[Amount/pc]]/_xlfn.XLOOKUP(B61,Terméklista!$B$2:$B$103,Terméklista!$M$2:$M$103,),0)," ") -> 143 | P61: =IFERROR(ROUNDUP(Rendelés[[#This Row],[Dobozok száma]]/_xlfn.XLOOKUP(B61,Terméklista!$B$2:$B$103,Terméklista!$N$2:$N$103,),0)," ") -> 2 | Q61: =IFERROR(Rendelés[[#This Row],[Szükséges anyagmennyiség]]+(Rendelés[[#This Row],[Össz raklapok száma]]*25),"") -> 900 | R61: {=(H61*_xlfn.XLOOKUP(B61,Terméklista!$B$2:$B$103,Terméklista!F$2:$F$103,))/1000} -> 850 | S61: =IFERROR(((H61/_xlfn.XLOOKUP(B61,Terméklista!$B$2:$B$103,Terméklista!$E$2:$E$103)*_xlfn.XLOOKUP(B61,Terméklista!$B$2:$B$103,Terméklista!$I$2:$I$103)))/3600," ") -> 34.722222 | T61: 2025/74
A62: Ela Solutions Kft. | B62: 90ZA-H021-06 | C62: =IFERROR(_xlfn.XLOOKUP(B62,Terméklista!$B$2:$B$103,Terméklista!$C$2:$C$103,)," ") -> lakattal zárható zárház | F62: =_xlfn.XLOOKUP(B62,Terméklista!B73:B174,Terméklista!G73:G174," ") | G62: 5877 | H62: 250 | I62: 2025-09-03 | J62: 2025-09-15 | L62: x | M62: CMR | N62: =IFERROR(_xlfn.XLOOKUP(B62,Terméklista!B73:B174,Terméklista!H73:H174)," ") | O62: =IFERROR(ROUNDUP(Rendelés[[#This Row],[Amount/pc]]/_xlfn.XLOOKUP(B62,Terméklista!$B$2:$B$103,Terméklista!$M$2:$M$103,),0)," ") | P62: =IFERROR(ROUNDUP(Rendelés[[#This Row],[Dobozok száma]]/_xlfn.XLOOKUP(B62,Terméklista!$B$2:$B$103,Terméklista!$N$2:$N$103,),0)," ") | Q62: =IFERROR(Rendelés[[#This Row],[Szükséges anyagmennyiség]]+(Rendelés[[#This Row],[Össz raklapok száma]]*25),"") | R62: {=(H62*_xlfn.XLOOKUP(B62,Terméklista!$B$2:$B$103,Terméklista!F$2:$F$103,))/1000} -> 23.14 | S62: =IFERROR(((H62/_xlfn.XLOOKUP(B62,Terméklista!$B$2:$B$103,Terméklista!$E$2:$E$103)*_xlfn.XLOOKUP(B62,Terméklista!$B$2:$B$103,Terméklista!$I$2:$I$103)))/3600," ") -> 0.52083333 | T62: 2025/63
A63: Seidel Gmbh&co Kg | B63: MB22 | C63: =IFERROR(_xlfn.XLOOKUP(B63,Terméklista!$B$2:$B$103,Terméklista!$C$2:$C$103,)," ") -> Zamak Gewicht | D63: POS010 | F63: =_xlfn.XLOOKUP(B63,Terméklista!B74:B175,Terméklista!G74:G175," ") -> Z410 | G63: 4500103024 | H63: 25000 | I63: 2025-09-05 | J63: 2025-10-09 | K63: 2025-10-02 | L63: x | M63: CMR | N63: =IFERROR(_xlfn.XLOOKUP(B63,Terméklista!B74:B175,Terméklista!H74:H175)," ") -> 0 | O63: =IFERROR(ROUNDUP(Rendelés[[#This Row],[Amount/pc]]/_xlfn.XLOOKUP(B63,Terméklista!$B$2:$B$103,Terméklista!$M$2:$M$103,),0)," ") -> 25 | P63: =IFERROR(ROUNDUP(Rendelés[[#This Row],[Dobozok száma]]/_xlfn.XLOOKUP(B63,Terméklista!$B$2:$B$103,Terméklista!$N$2:$N$103,),0)," ") -> 1 | Q63: =IFERROR(Rendelés[[#This Row],[Szükséges anyagmennyiség]]+(Rendelés[[#This Row],[Össz raklapok száma]]*25),"") -> 225 | R63: {=(H63*_xlfn.XLOOKUP(B63,Terméklista!$B$2:$B$103,Terméklista!F$2:$F$103,))/1000} -> 200 | S63: =IFERROR(((H63/_xlfn.XLOOKUP(B63,Terméklista!$B$2:$B$103,Terméklista!$E$2:$E$103)*_xlfn.XLOOKUP(B63,Terméklista!$B$2:$B$103,Terméklista!$I$2:$I$103)))/3600," ") -> 8.6805556 | T63: 2025/68
A64: Inter-Metal Recycling Kft. | B64: Forgács Vas | E64: M251064 Pos-10 | F64: Forgács | H64: 4 | I64: 2025-09-08 | J64: 2025-09-08 | K64: 2025-09-08 | L64: x | N64: =IFERROR(_xlfn.XLOOKUP(B64,Terméklista!B75:B176,Terméklista!H75:H176)," ") | O64: =IFERROR(ROUNDUP(Rendelés[[#This Row],[Amount/pc]]/_xlfn.XLOOKUP(B64,Terméklista!$B$2:$B$103,Terméklista!$M$2:$M$103,),0)," ") | P64: =IFERROR(ROUNDUP(Rendelés[[#This Row],[Dobozok száma]]/_xlfn.XLOOKUP(B64,Terméklista!$B$2:$B$103,Terméklista!$N$2:$N$103,),0)," ") | Q64: =IFERROR(Rendelés[[#This Row],[Szükséges anyagmennyiség]]+(Rendelés[[#This Row],[Össz raklapok száma]]*25),"") | R64: {=(H64*_xlfn.XLOOKUP(B64,Terméklista!$B$2:$B$103,Terméklista!F$2:$F$103,))/1000} -> 0 | S64: =IFERROR(((H64/_xlfn.XLOOKUP(B64,Terméklista!$B$2:$B$103,Terméklista!$E$2:$E$103)*_xlfn.XLOOKUP(B64,Terméklista!$B$2:$B$103,Terméklista!$I$2:$I$103)))/3600," ") | T64: 2025/62
A65: Inter-Metal Recycling Kft. | B65: Forgács Aluminium | E65: M251064 Pos-20 | F65: Forgács | H65: 1 | I65: 2025-09-08 | J65: 2025-09-08 | K65: 2025-09-08 | L65: x | N65: =IFERROR(_xlfn.XLOOKUP(B65,Terméklista!B76:B177,Terméklista!H76:H177)," ") | O65: =IFERROR(ROUNDUP(Rendelés[[#This Row],[Amount/pc]]/_xlfn.XLOOKUP(B65,Terméklista!$B$2:$B$103,Terméklista!$M$2:$M$103,),0)," ") | P65: =IFERROR(ROUNDUP(Rendelés[[#This Row],[Dobozok száma]]/_xlfn.XLOOKUP(B65,Terméklista!$B$2:$B$103,Terméklista!$N$2:$N$103,),0)," ") | Q65: =IFERROR(Rendelés[[#This Row],[Szükséges anyagmennyiség]]+(Rendelés[[#This Row],[Össz raklapok száma]]*25),"") | R65: {=(H65*_xlfn.XLOOKUP(B65,Terméklista!$B$2:$B$103,Terméklista!F$2:$F$103,))/1000} -> 0 | S65: =IFERROR(((H65/_xlfn.XLOOKUP(B65,Terméklista!$B$2:$B$103,Terméklista!$E$2:$E$103)*_xlfn.XLOOKUP(B65,Terméklista!$B$2:$B$103,Terméklista!$I$2:$I$103)))/3600," ") | T65: 2025/62
A66: Inter-Metal Recycling Kft. | B66: Forgács Rozsdamentés | E66: M251064 Pos-30 | F66: Forgács | H66: 1 | I66: 2025-09-08 | J66: 2025-09-08 | K66: 2025-09-08 | L66: x | N66: =IFERROR(_xlfn.XLOOKUP(B66,Terméklista!B77:B178,Terméklista!H77:H178)," ") | O66: =IFERROR(ROUNDUP(Rendelés[[#This Row],[Amount/pc]]/_xlfn.XLOOKUP(B66,Terméklista!$B$2:$B$103,Terméklista!$M$2:$M$103,),0)," ") | P66: =IFERROR(ROUNDUP(Rendelés[[#This Row],[Dobozok száma]]/_xlfn.XLOOKUP(B66,Terméklista!$B$2:$B$103,Terméklista!$N$2:$N$103,),0)," ") | Q66: =IFERROR(Rendelés[[#This Row],[Szükséges anyagmennyiség]]+(Rendelés[[#This Row],[Össz raklapok száma]]*25),"") | R66: {=(H66*_xlfn.XLOOKUP(B66,Terméklista!$B$2:$B$103,Terméklista!F$2:$F$103,))/1000} -> 0 | S66: =IFERROR(((H66/_xlfn.XLOOKUP(B66,Terméklista!$B$2:$B$103,Terméklista!$E$2:$E$103)*_xlfn.XLOOKUP(B66,Terméklista!$B$2:$B$103,Terméklista!$I$2:$I$103)))/3600," ") | T66: 2025/62
A67: Inter-Metal Recycling Kft. | B67: Forgács Vegyes | E67: M251064 Pos-40 | F67: Forgács | H67: 1 | I67: 2025-09-08 | J67: 2025-09-08 | K67: 2025-09-08 | L67: x | N67: =IFERROR(_xlfn.XLOOKUP(B67,Terméklista!B78:B179,Terméklista!H78:H179)," ") | O67: =IFERROR(ROUNDUP(Rendelés[[#This Row],[Amount/pc]]/_xlfn.XLOOKUP(B67,Terméklista!$B$2:$B$103,Terméklista!$M$2:$M$103,),0)," ") | P67: =IFERROR(ROUNDUP(Rendelés[[#This Row],[Dobozok száma]]/_xlfn.XLOOKUP(B67,Terméklista!$B$2:$B$103,Terméklista!$N$2:$N$103,),0)," ") | Q67: =IFERROR(Rendelés[[#This Row],[Szükséges anyagmennyiség]]+(Rendelés[[#This Row],[Össz raklapok száma]]*25),"") | R67: {=(H67*_xlfn.XLOOKUP(B67,Terméklista!$B$2:$B$103,Terméklista!F$2:$F$103,))/1000} -> 0 | S67: =IFERROR(((H67/_xlfn.XLOOKUP(B67,Terméklista!$B$2:$B$103,Terméklista!$E$2:$E$103)*_xlfn.XLOOKUP(B67,Terméklista!$B$2:$B$103,Terméklista!$I$2:$I$103)))/3600," ") | T67: 2025/62
A68: Ela Solutions Kft. | B68: 90ZA-B001-06 | E68: M251065 Pos-10 | F68: Z410 | H68: 1000 | I68: 2025-09-11 | J68: 2025-09-15 | L68: x | M68: CMR | N68: =IFERROR(_xlfn.XLOOKUP(B68,Terméklista!B79:B180,Terméklista!H79:H180)," ") | O68: =IFERROR(ROUNDUP(Rendelés[[#This Row],[Amount/pc]]/_xlfn.XLOOKUP(B68,Terméklista!$B$2:$B$103,Terméklista!$M$2:$M$103,),0)," ") | P68: =IFERROR(ROUNDUP(Rendelés[[#This Row],[Dobozok száma]]/_xlfn.XLOOKUP(B68,Terméklista!$B$2:$B$103,Terméklista!$N$2:$N$103,),0)," ") | Q68: =IFERROR(Rendelés[[#This Row],[Szükséges anyagmennyiség]]+(Rendelés[[#This Row],[Össz raklapok száma]]*25),"") | R68: {=(H68*_xlfn.XLOOKUP(B68,Terméklista!$B$2:$B$103,Terméklista!F$2:$F$103,))/1000} -> 14.85 | S68: =IFERROR(((H68/_xlfn.XLOOKUP(B68,Terméklista!$B$2:$B$103,Terméklista!$E$2:$E$103)*_xlfn.XLOOKUP(B68,Terméklista!$B$2:$B$103,Terméklista!$I$2:$I$103)))/3600," ") -> 2.0833333 | T68: 2025/63
A69: Ela Solutions Kft. | B69: 90ZA-ZK011-06 | C69: =IFERROR(_xlfn.XLOOKUP(B69,Terméklista!$B$2:$B$103,Terméklista!$C$2:$C$103,)," ") -> nagykulcs - 3mm | F69: =_xlfn.XLOOKUP(B69,Terméklista!B82:B183,Terméklista!G82:G183," ") | G69: 5906 | H69: 1000 | I69: 2025-09-25 | J69: 2025-10-20 | L69: x | N69: =IFERROR(_xlfn.XLOOKUP(B69,Terméklista!B82:B183,Terméklista!H82:H183)," ") | O69: =IFERROR(ROUNDUP(Rendelés[[#This Row],[Amount/pc]]/_xlfn.XLOOKUP(B69,Terméklista!$B$2:$B$103,Terméklista!$M$2:$M$103,),0)," ") | P69: =IFERROR(ROUNDUP(Rendelés[[#This Row],[Dobozok száma]]/_xlfn.XLOOKUP(B69,Terméklista!$B$2:$B$103,Terméklista!$N$2:$N$103,),0)," ") | Q69: =IFERROR(Rendelés[[#This Row],[Szükséges anyagmennyiség]]+(Rendelés[[#This Row],[Össz raklapok száma]]*25),"") | R69: {=(H69*_xlfn.XLOOKUP(B69,Terméklista!$B$2:$B$103,Terméklista!F$2:$F$103,))/1000} -> 47.55 | S69: =IFERROR(((H69/_xlfn.XLOOKUP(B69,Terméklista!$B$2:$B$103,Terméklista!$E$2:$E$103)*_xlfn.XLOOKUP(B69,Terméklista!$B$2:$B$103,Terméklista!$I$2:$I$103)))/3600," ") -> 2.0833333 | T69: 2025/72
A70: Seidel Gmbh&co Kg | B70: MA41 | C70: =IFERROR(_xlfn.XLOOKUP(B70,Terméklista!$B$2:$B$103,Terméklista!$C$2:$C$103,)," ") -> Zamak Gewicht | D70: POS010 | F70: =_xlfn.XLOOKUP(B70,Terméklista!B81:B182,Terméklista!G81:G182," ") | G70: 4500103317 | H70: 50000 | I70: 2025-09-29 | J70: 2026-01-26 | K70: 2026-01-23 | L70: x | M70: CMR | N70: =IFERROR(_xlfn.XLOOKUP(B70,Terméklista!B81:B182,Terméklista!H81:H182)," ") | O70: =IFERROR(ROUNDUP(Rendelés[[#This Row],[Amount/pc]]/_xlfn.XLOOKUP(B70,Terméklista!$B$2:$B$103,Terméklista!$M$2:$M$103,),0)," ") -> 143 | P70: =IFERROR(ROUNDUP(Rendelés[[#This Row],[Dobozok száma]]/_xlfn.XLOOKUP(B70,Terméklista!$B$2:$B$103,Terméklista!$N$2:$N$103,),0)," ") -> 2 | Q70: =IFERROR(Rendelés[[#This Row],[Szükséges anyagmennyiség]]+(Rendelés[[#This Row],[Össz raklapok száma]]*25),"") -> 900 | R70: {=(H70*_xlfn.XLOOKUP(B70,Terméklista!$B$2:$B$103,Terméklista!F$2:$F$103,))/1000} -> 850 | S70: =IFERROR(((H70/_xlfn.XLOOKUP(B70,Terméklista!$B$2:$B$103,Terméklista!$E$2:$E$103)*_xlfn.XLOOKUP(B70,Terméklista!$B$2:$B$103,Terméklista!$I$2:$I$103)))/3600," ") -> 34.722222 | T70: 2026/83 | U70: kiszállítva
A71: Fasten Italia S.R.L | B71: P6 body | C71: =IFERROR(_xlfn.XLOOKUP(B71,Terméklista!$B$2:$B$103,Terméklista!$C$2:$C$103,)," ") -> 0 | F71: =_xlfn.XLOOKUP(B71,Terméklista!B83:B184,Terméklista!G83:G184," ") | G71: 25/00646 | H71: 11000 | I71: 2025-10-06 | M71: CMR | N71: =IFERROR(_xlfn.XLOOKUP(B71,Terméklista!B83:B184,Terméklista!H83:H184)," ") | O71: =IFERROR(ROUNDUP(Rendelés[[#This Row],[Amount/pc]]/_xlfn.XLOOKUP(B71,Terméklista!$B$2:$B$103,Terméklista!$M$2:$M$103,),0)," ") | P71: =IFERROR(ROUNDUP(Rendelés[[#This Row],[Dobozok száma]]/_xlfn.XLOOKUP(B71,Terméklista!$B$2:$B$103,Terméklista!$N$2:$N$103,),0)," ") | Q71: =IFERROR(Rendelés[[#This Row],[Szükséges anyagmennyiség]]+(Rendelés[[#This Row],[Össz raklapok száma]]*25),"") | R71: {=(H71*_xlfn.XLOOKUP(B71,Terméklista!$B$2:$B$103,Terméklista!F$2:$F$103,))/1000} -> 0 | S71: =IFERROR(((H71/_xlfn.XLOOKUP(B71,Terméklista!$B$2:$B$103,Terméklista!$E$2:$E$103)*_xlfn.XLOOKUP(B71,Terméklista!$B$2:$B$103,Terméklista!$I$2:$I$103)))/3600," ") | T71: 2025/78 | U71: kiszállítva
A72: Fasten Italia S.R.L | B72: YKK fogó | C72: =IFERROR(_xlfn.XLOOKUP(B72,Terméklista!$B$2:$B$103,Terméklista!$C$2:$C$103,)," ") -> 0 | F72: =_xlfn.XLOOKUP(B72,Terméklista!B84:B185,Terméklista!G84:G185," ") | G72: 25/00646 | H72: 30000 | I72: 2025-10-06 | M72: CMR | N72: =IFERROR(_xlfn.XLOOKUP(B72,Terméklista!B84:B185,Terméklista!H84:H185)," ") | O72: =IFERROR(ROUNDUP(Rendelés[[#This Row],[Amount/pc]]/_xlfn.XLOOKUP(B72,Terméklista!$B$2:$B$103,Terméklista!$M$2:$M$103,),0)," ") | P72: =IFERROR(ROUNDUP(Rendelés[[#This Row],[Dobozok száma]]/_xlfn.XLOOKUP(B72,Terméklista!$B$2:$B$103,Terméklista!$N$2:$N$103,),0)," ") | Q72: =IFERROR(Rendelés[[#This Row],[Szükséges anyagmennyiség]]+(Rendelés[[#This Row],[Össz raklapok száma]]*25),"") | R72: {=(H72*_xlfn.XLOOKUP(B72,Terméklista!$B$2:$B$103,Terméklista!F$2:$F$103,))/1000} -> 0 | S72: =IFERROR(((H72/_xlfn.XLOOKUP(B72,Terméklista!$B$2:$B$103,Terméklista!$E$2:$E$103)*_xlfn.XLOOKUP(B72,Terméklista!$B$2:$B$103,Terméklista!$I$2:$I$103)))/3600," ") | T72: 2025/78 | U72: kiszállítva
A73: Seidel Gmbh&co Kg | B73: MA66 | C73: =IFERROR(_xlfn.XLOOKUP(B73,Terméklista!$B$2:$B$103,Terméklista!$C$2:$C$103,)," ") -> Zamak Gewicht | D73: POS010 | F73: =_xlfn.XLOOKUP(B73,Terméklista!B87:B188,Terméklista!G87:G188," ") | G73: 4500103496 | H73: 200000 | I73: 2025-10-09 | J73: 2025-10-31 | L73: x | M73: CMR | N73: =IFERROR(_xlfn.XLOOKUP(B73,Terméklista!B87:B188,Terméklista!H87:H188)," ") | O73: =IFERROR(ROUNDUP(Rendelés[[#This Row],[Amount/pc]]/_xlfn.XLOOKUP(B73,Terméklista!$B$2:$B$103,Terméklista!$M$2:$M$103,),0)," ") -> 400 | P73: =IFERROR(ROUNDUP(Rendelés[[#This Row],[Dobozok száma]]/_xlfn.XLOOKUP(B73,Terméklista!$B$2:$B$103,Terméklista!$N$2:$N$103,),0)," ") -> 5 | Q73: =IFERROR(Rendelés[[#This Row],[Szükséges anyagmennyiség]]+(Rendelés[[#This Row],[Össz raklapok száma]]*25),"") -> 2225 | R73: {=(H73*_xlfn.XLOOKUP(B73,Terméklista!$B$2:$B$103,Terméklista!F$2:$F$103,))/1000} -> 2100 | S73: =IFERROR(((H73/_xlfn.XLOOKUP(B73,Terméklista!$B$2:$B$103,Terméklista!$E$2:$E$103)*_xlfn.XLOOKUP(B73,Terméklista!$B$2:$B$103,Terméklista!$I$2:$I$103)))/3600," ") -> 138.88889 | T73: 2025/74
A74: Seidel Gmbh&co Kg | B74: MA66 | C74: =IFERROR(_xlfn.XLOOKUP(B74,Terméklista!$B$2:$B$103,Terméklista!$C$2:$C$103,)," ") -> Zamak Gewicht | D74: POS020 | F74: =_xlfn.XLOOKUP(B74,Terméklista!B88:B189,Terméklista!G88:G189," ") | G74: 4500103496 | H74: 200000 | I74: 2025-10-09 | J74: 2025-11-10 | L74: x | M74: CMR | N74: =IFERROR(_xlfn.XLOOKUP(B74,Terméklista!B88:B189,Terméklista!H88:H189)," ") | O74: =IFERROR(ROUNDUP(Rendelés[[#This Row],[Amount/pc]]/_xlfn.XLOOKUP(B74,Terméklista!$B$2:$B$103,Terméklista!$M$2:$M$103,),0)," ") -> 400 | P74: =IFERROR(ROUNDUP(Rendelés[[#This Row],[Dobozok száma]]/_xlfn.XLOOKUP(B74,Terméklista!$B$2:$B$103,Terméklista!$N$2:$N$103,),0)," ") -> 5 | Q74: =IFERROR(Rendelés[[#This Row],[Szükséges anyagmennyiség]]+(Rendelés[[#This Row],[Össz raklapok száma]]*25),"") -> 2225 | R74: {=(H74*_xlfn.XLOOKUP(B74,Terméklista!$B$2:$B$103,Terméklista!F$2:$F$103,))/1000} -> 2100 | S74: =IFERROR(((H74/_xlfn.XLOOKUP(B74,Terméklista!$B$2:$B$103,Terméklista!$E$2:$E$103)*_xlfn.XLOOKUP(B74,Terméklista!$B$2:$B$103,Terméklista!$I$2:$I$103)))/3600," ") -> 138.88889
A75: Seidel Gmbh&co Kg | B75: MA66 | C75: =IFERROR(_xlfn.XLOOKUP(B75,Terméklista!$B$2:$B$103,Terméklista!$C$2:$C$103,)," ") -> Zamak Gewicht | D75: POS030 | F75: =_xlfn.XLOOKUP(B75,Terméklista!B89:B190,Terméklista!G89:G190," ") | G75: 4500103496 | H75: 200000 | I75: 2025-10-09 | J75: 2026-01-09 | L75: x | M75: CMR | N75: =IFERROR(_xlfn.XLOOKUP(B75,Terméklista!B89:B190,Terméklista!H89:H190)," ") | O75: =IFERROR(ROUNDUP(Rendelés[[#This Row],[Amount/pc]]/_xlfn.XLOOKUP(B75,Terméklista!$B$2:$B$103,Terméklista!$M$2:$M$103,),0)," ") -> 400 | P75: =IFERROR(ROUNDUP(Rendelés[[#This Row],[Dobozok száma]]/_xlfn.XLOOKUP(B75,Terméklista!$B$2:$B$103,Terméklista!$N$2:$N$103,),0)," ") -> 5 | Q75: =IFERROR(Rendelés[[#This Row],[Szükséges anyagmennyiség]]+(Rendelés[[#This Row],[Össz raklapok száma]]*25),"") -> 2225 | R75: {=(H75*_xlfn.XLOOKUP(B75,Terméklista!$B$2:$B$103,Terméklista!F$2:$F$103,))/1000} -> 2100 | S75: =IFERROR(((H75/_xlfn.XLOOKUP(B75,Terméklista!$B$2:$B$103,Terméklista!$E$2:$E$103)*_xlfn.XLOOKUP(B75,Terméklista!$B$2:$B$103,Terméklista!$I$2:$I$103)))/3600," ") -> 138.88889 | T75: 2026/81
A76: Seidel Gmbh&co Kg | B76: MB22 | C76: =IFERROR(_xlfn.XLOOKUP(B76,Terméklista!$B$2:$B$103,Terméklista!$C$2:$C$103,)," ") -> Zamak Gewicht | D76: POS010 | F76: =_xlfn.XLOOKUP(B76,Terméklista!B90:B191,Terméklista!G90:G191," ") | G76: 4500103476 | H76: 54000 | I76: 2025-10-10 | J76: 2026-01-06 | L76: x | M76: CMR | N76: =IFERROR(_xlfn.XLOOKUP(B76,Terméklista!B90:B191,Terméklista!H90:H191)," ") | O76: =IFERROR(ROUNDUP(Rendelés[[#This Row],[Amount/pc]]/_xlfn.XLOOKUP(B76,Terméklista!$B$2:$B$103,Terméklista!$M$2:$M$103,),0)," ") -> 54 | P76: =IFERROR(ROUNDUP(Rendelés[[#This Row],[Dobozok száma]]/_xlfn.XLOOKUP(B76,Terméklista!$B$2:$B$103,Terméklista!$N$2:$N$103,),0)," ") -> 1 | Q76: =IFERROR(Rendelés[[#This Row],[Szükséges anyagmennyiség]]+(Rendelés[[#This Row],[Össz raklapok száma]]*25),"") -> 457 | R76: {=(H76*_xlfn.XLOOKUP(B76,Terméklista!$B$2:$B$103,Terméklista!F$2:$F$103,))/1000} -> 432 | S76: =IFERROR(((H76/_xlfn.XLOOKUP(B76,Terméklista!$B$2:$B$103,Terméklista!$E$2:$E$103)*_xlfn.XLOOKUP(B76,Terméklista!$B$2:$B$103,Terméklista!$I$2:$I$103)))/3600," ") -> 18.75 | T76: 2026/81
A77: Seidel Gmbh&co Kg | B77: MA41 | C77: =IFERROR(_xlfn.XLOOKUP(B77,Terméklista!$B$2:$B$103,Terméklista!$C$2:$C$103,)," ") -> Zamak Gewicht | E77: M251034 | F77: =_xlfn.XLOOKUP(B77,Terméklista!$B$2:$B$103,Terméklista!$G$2:$G$103," ") -> Z410 | G77: 4500100901 | H77: 50000 | I77: 20025.03.25 | J77: 2025-06-06 | K77: 2025-06-05 | L77: x | M77: CMR | N77: =_xlfn.XLOOKUP(J77,Terméklista!$B$2:$B$103,Terméklista!$H$2:$H$103," ") | O77: =IFERROR(ROUNDUP(Rendelés[[#This Row],[Amount/pc]]/_xlfn.XLOOKUP(B77,Terméklista!$B$2:$B$103,Terméklista!$M$2:$M$103,),0)," ") -> 143 | P77: =IFERROR(ROUNDUP(Rendelés[[#This Row],[Dobozok száma]]/_xlfn.XLOOKUP(B77,Terméklista!$B$2:$B$103,Terméklista!$N$2:$N$103,),0)," ") -> 2 | Q77: =IFERROR(Rendelés[[#This Row],[Szükséges anyagmennyiség]]+(Rendelés[[#This Row],[Össz raklapok száma]]*25),"") -> 900 | R77: {=(H77*_xlfn.XLOOKUP(B77,Terméklista!$B$2:$B$103,Terméklista!F$2:$F$103,))/1000} -> 850 | S77: =IFERROR(((H77/_xlfn.XLOOKUP(B77,Terméklista!$B$2:$B$103,Terméklista!$E$2:$E$103)*_xlfn.XLOOKUP(B77,Terméklista!$B$2:$B$103,Terméklista!$I$2:$I$103)))/3600," ") -> 34.722222
A78: Inter-Metal Recycling Kft. | B78: Forgács Vas | E78: M251061 Pos-10 | F78: Forgács | H78: 4db | L78: x | N78: =IFERROR(_xlfn.XLOOKUP(B78,Terméklista!B59:B160,Terméklista!H59:H160)," ") -> 0 | O78: =IFERROR(ROUNDUP(Rendelés[[#This Row],[Amount/pc]]/_xlfn.XLOOKUP(B78,Terméklista!$B$2:$B$103,Terméklista!$M$2:$M$103,),0)," ") | P78: =IFERROR(ROUNDUP(Rendelés[[#This Row],[Dobozok száma]]/_xlfn.XLOOKUP(B78,Terméklista!$B$2:$B$103,Terméklista!$N$2:$N$103,),0)," ") | Q78: =IFERROR(Rendelés[[#This Row],[Szükséges anyagmennyiség]]+(Rendelés[[#This Row],[Össz raklapok száma]]*25),"") | S78: =IFERROR(((H78/_xlfn.XLOOKUP(B78,Terméklista!$B$2:$B$103,Terméklista!$E$2:$E$103)*_xlfn.XLOOKUP(B78,Terméklista!$B$2:$B$103,Terméklista!$I$2:$I$103)))/3600," ") | T78: 2025/50
A79: Inter-Metal Recycling Kft. | B79: Forgács Aluminium | E79: M251062 Pos-10 | F79: Forgács | H79: 1db | L79: x | N79: =IFERROR(_xlfn.XLOOKUP(B79,Terméklista!B60:B161,Terméklista!H60:H161)," ") | O79: =IFERROR(ROUNDUP(Rendelés[[#This Row],[Amount/pc]]/_xlfn.XLOOKUP(B79,Terméklista!$B$2:$B$103,Terméklista!$M$2:$M$103,),0)," ") | P79: =IFERROR(ROUNDUP(Rendelés[[#This Row],[Dobozok száma]]/_xlfn.XLOOKUP(B79,Terméklista!$B$2:$B$103,Terméklista!$N$2:$N$103,),0)," ") | Q79: =IFERROR(Rendelés[[#This Row],[Szükséges anyagmennyiség]]+(Rendelés[[#This Row],[Össz raklapok száma]]*25),"") | S79: =IFERROR(((H79/_xlfn.XLOOKUP(B79,Terméklista!$B$2:$B$103,Terméklista!$E$2:$E$103)*_xlfn.XLOOKUP(B79,Terméklista!$B$2:$B$103,Terméklista!$I$2:$I$103)))/3600," ") | T79: 2025/50
A80: Inter-Metal Recycling Kft. | B80: Vas lemez hulladék | E80: M251063 Pos-20 | L80: x | N80: =IFERROR(_xlfn.XLOOKUP(B80,Terméklista!B63:B164,Terméklista!H63:H164)," ") | O80: =IFERROR(ROUNDUP(Rendelés[[#This Row],[Amount/pc]]/_xlfn.XLOOKUP(B80,Terméklista!$B$2:$B$103,Terméklista!$M$2:$M$103,),0)," ") | P80: =IFERROR(ROUNDUP(Rendelés[[#This Row],[Dobozok száma]]/_xlfn.XLOOKUP(B80,Terméklista!$B$2:$B$103,Terméklista!$N$2:$N$103,),0)," ") | Q80: =IFERROR(Rendelés[[#This Row],[Szükséges anyagmennyiség]]+(Rendelés[[#This Row],[Össz raklapok száma]]*25),"") | R80: {=(H80*_xlfn.XLOOKUP(B80,Terméklista!$B$2:$B$103,Terméklista!F$2:$F$103,))/1000} -> 0 | S80: =IFERROR(((H80/_xlfn.XLOOKUP(B80,Terméklista!$B$2:$B$103,Terméklista!$E$2:$E$103)*_xlfn.XLOOKUP(B80,Terméklista!$B$2:$B$103,Terméklista!$I$2:$I$103)))/3600," ") | T80: 2025/55
A81: Ligeti Péter | B81: nyersanyag | E81: M251066 Pos-10 | F81: zamak | H81: 604 Kg | K81: 2025-09-24 | L81: x | M81: CMR | N81: =IFERROR(_xlfn.XLOOKUP(B81,Terméklista!B80:B181,Terméklista!H80:H181)," ") -> 0 | O81: =IFERROR(ROUNDUP(Rendelés[[#This Row],[Amount/pc]]/_xlfn.XLOOKUP(B81,Terméklista!$B$2:$B$103,Terméklista!$M$2:$M$103,),0)," ") | P81: =IFERROR(ROUNDUP(Rendelés[[#This Row],[Dobozok száma]]/_xlfn.XLOOKUP(B81,Terméklista!$B$2:$B$103,Terméklista!$N$2:$N$103,),0)," ") | Q81: =IFERROR(Rendelés[[#This Row],[Szükséges anyagmennyiség]]+(Rendelés[[#This Row],[Össz raklapok száma]]*25),"") | R81: {=(H81*_xlfn.XLOOKUP(B81,Terméklista!$B$2:$B$103,Terméklista!F$2:$F$103,))/1000} -> #VALUE! | S81: =IFERROR(((H81/_xlfn.XLOOKUP(B81,Terméklista!$B$2:$B$103,Terméklista!$E$2:$E$103)*_xlfn.XLOOKUP(B81,Terméklista!$B$2:$B$103,Terméklista!$I$2:$I$103)))/3600," ") | T81: 2025/66
A82: Inter-Metal Recycling Kft. | B82: Forgács Vas | C82: VTSZ:7204 | E82: M251067 Pos-10 | F82: Forgács | H82: 3 | K82: 2025-10-09 | L82: x | N82: =IFERROR(_xlfn.XLOOKUP(B82,Terméklista!B85:B186,Terméklista!H85:H186)," ") | O82: =IFERROR(ROUNDUP(Rendelés[[#This Row],[Amount/pc]]/_xlfn.XLOOKUP(B82,Terméklista!$B$2:$B$103,Terméklista!$M$2:$M$103,),0)," ") | P82: =IFERROR(ROUNDUP(Rendelés[[#This Row],[Dobozok száma]]/_xlfn.XLOOKUP(B82,Terméklista!$B$2:$B$103,Terméklista!$N$2:$N$103,),0)," ") | Q82: =IFERROR(Rendelés[[#This Row],[Szükséges anyagmennyiség]]+(Rendelés[[#This Row],[Össz raklapok száma]]*25),"") | R82: {=(H82*_xlfn.XLOOKUP(B82,Terméklista!$B$2:$B$103,Terméklista!F$2:$F$103,))/1000} -> 0 | S82: =IFERROR(((H82/_xlfn.XLOOKUP(B82,Terméklista!$B$2:$B$103,Terméklista!$E$2:$E$103)*_xlfn.XLOOKUP(B82,Terméklista!$B$2:$B$103,Terméklista!$I$2:$I$103)))/3600," ") | T82: 2025/70
A83: Inter-Metal Recycling Kft. | B83: Forgács Aluminium | C83: VTSZ:7602 | E83: M251067 Pos-20 | F83: Forgács | H83: 3 | K83: 2025-10-09 | L83: x | N83: =IFERROR(_xlfn.XLOOKUP(B83,Terméklista!B86:B187,Terméklista!H86:H187)," ") | O83: =IFERROR(ROUNDUP(Rendelés[[#This Row],[Amount/pc]]/_xlfn.XLOOKUP(B83,Terméklista!$B$2:$B$103,Terméklista!$M$2:$M$103,),0)," ") | P83: =IFERROR(ROUNDUP(Rendelés[[#This Row],[Dobozok száma]]/_xlfn.XLOOKUP(B83,Terméklista!$B$2:$B$103,Terméklista!$N$2:$N$103,),0)," ") | Q83: =IFERROR(Rendelés[[#This Row],[Szükséges anyagmennyiség]]+(Rendelés[[#This Row],[Össz raklapok száma]]*25),"") | R83: {=(H83*_xlfn.XLOOKUP(B83,Terméklista!$B$2:$B$103,Terméklista!F$2:$F$103,))/1000} -> 0 | S83: =IFERROR(((H83/_xlfn.XLOOKUP(B83,Terméklista!$B$2:$B$103,Terméklista!$E$2:$E$103)*_xlfn.XLOOKUP(B83,Terméklista!$B$2:$B$103,Terméklista!$I$2:$I$103)))/3600," ") | T83: 2025/70
A84: Inter-Metal Recycling Kft. | B84: Csöpedék - Horgany | C84: VTSZ: 7204 | E84: M251060 Pos-10 | F84: Forgács | H84: 1 | L84: x | N84: =IFERROR(_xlfn.XLOOKUP(B84,Terméklista!B56:B157,Terméklista!H56:H157)," ") -> 0 | O84: =IFERROR(ROUNDUP(Rendelés[[#This Row],[Amount/pc]]/_xlfn.XLOOKUP(B84,Terméklista!$B$2:$B$103,Terméklista!$M$2:$M$103,),0)," ") | P84: =IFERROR(ROUNDUP(Rendelés[[#This Row],[Dobozok száma]]/_xlfn.XLOOKUP(B84,Terméklista!$B$2:$B$103,Terméklista!$N$2:$N$103,),0)," ") | Q84: =IFERROR(Rendelés[[#This Row],[Szükséges anyagmennyiség]]+(Rendelés[[#This Row],[Össz raklapok száma]]*25),"") | R84: {=(H84*_xlfn.XLOOKUP(B84,Terméklista!$B$2:$B$103,Terméklista!F$2:$F$103,))/1000} -> 0 | S84: =IFERROR(((H84/_xlfn.XLOOKUP(B84,Terméklista!$B$2:$B$103,Terméklista!$E$2:$E$103)*_xlfn.XLOOKUP(B84,Terméklista!$B$2:$B$103,Terméklista!$I$2:$I$103)))/3600," ") | T84: 2025/45
A85: Inter-Metal Recycling Kft. | B85: Forgács Aluminium | C85: =IFERROR(_xlfn.XLOOKUP(B85,Terméklista!$B$2:$B$103,Terméklista!$C$2:$C$103,)," ") -> VTSZ: 7602 | E85: M251036 | F85: =_xlfn.XLOOKUP(B85,Terméklista!$B$2:$B$103,Terméklista!$G$2:$G$103," ") -> Forgács | H85: 2 | L85: x | N85: =_xlfn.XLOOKUP(J85,Terméklista!$B$2:$B$103,Terméklista!$H$2:$H$103," ") -> 0 | O85: =IFERROR(ROUNDUP(Rendelés[[#This Row],[Amount/pc]]/_xlfn.XLOOKUP(B85,Terméklista!$B$2:$B$103,Terméklista!$M$2:$M$103,),0)," ") | P85: =IFERROR(ROUNDUP(Rendelés[[#This Row],[Dobozok száma]]/_xlfn.XLOOKUP(B85,Terméklista!$B$2:$B$103,Terméklista!$N$2:$N$103,),0)," ") | Q85: =IFERROR(Rendelés[[#This Row],[Szükséges anyagmennyiség]]+(Rendelés[[#This Row],[Össz raklapok száma]]*25),"") | R85: {=(H85*_xlfn.XLOOKUP(B85,Terméklista!$B$2:$B$103,Terméklista!F$2:$F$103,))/1000} -> 0 | S85: =IFERROR(((H85/_xlfn.XLOOKUP(B85,Terméklista!$B$2:$B$103,Terméklista!$E$2:$E$103)*_xlfn.XLOOKUP(B85,Terméklista!$B$2:$B$103,Terméklista!$I$2:$I$103)))/3600," ") | T85: 2025/32
A86: Inter-Metal Recycling Kft. | B86: Forgács Aluminium | C86: =IFERROR(_xlfn.XLOOKUP(B86,Terméklista!$B$2:$B$103,Terméklista!$C$2:$C$103,)," ") -> VTSZ: 7602 | E86: M251046 | F86: =_xlfn.XLOOKUP(B86,Terméklista!$B$2:$B$103,Terméklista!$G$2:$G$103," ") -> Forgács | H86: 1 | L86: x | N86: =_xlfn.XLOOKUP(J86,Terméklista!$B$2:$B$103,Terméklista!$H$2:$H$103," ") -> 0 | O86: =IFERROR(ROUNDUP(Rendelés[[#This Row],[Amount/pc]]/_xlfn.XLOOKUP(B86,Terméklista!$B$2:$B$103,Terméklista!$M$2:$M$103,),0)," ") | P86: =IFERROR(ROUNDUP(Rendelés[[#This Row],[Dobozok száma]]/_xlfn.XLOOKUP(B86,Terméklista!$B$2:$B$103,Terméklista!$N$2:$N$103,),0)," ") | Q86: =IFERROR(Rendelés[[#This Row],[Szükséges anyagmennyiség]]+(Rendelés[[#This Row],[Össz raklapok száma]]*25),"") | R86: {=(H86*_xlfn.XLOOKUP(B86,Terméklista!$B$2:$B$103,Terméklista!F$2:$F$103,))/1000} -> 0 | S86: =IFERROR(((H86/_xlfn.XLOOKUP(B86,Terméklista!$B$2:$B$103,Terméklista!$E$2:$E$103)*_xlfn.XLOOKUP(B86,Terméklista!$B$2:$B$103,Terméklista!$I$2:$I$103)))/3600," ") | T86: 2025/38
A87: Inter-Metal Recycling Kft. | B87: Forgács Aluminium | C87: VTSZ: 7602 | E87: M251060 Pos-20 | F87: Forgács | H87: 2 | L87: x | N87: =IFERROR(_xlfn.XLOOKUP(B87,Terméklista!B57:B158,Terméklista!H57:H158)," ") -> 0 | O87: =IFERROR(ROUNDUP(Rendelés[[#This Row],[Amount/pc]]/_xlfn.XLOOKUP(B87,Terméklista!$B$2:$B$103,Terméklista!$M$2:$M$103,),0)," ") | P87: =IFERROR(ROUNDUP(Rendelés[[#This Row],[Dobozok száma]]/_xlfn.XLOOKUP(B87,Terméklista!$B$2:$B$103,Terméklista!$N$2:$N$103,),0)," ") | Q87: =IFERROR(Rendelés[[#This Row],[Szükséges anyagmennyiség]]+(Rendelés[[#This Row],[Össz raklapok száma]]*25),"") | R87: {=(H87*_xlfn.XLOOKUP(B87,Terméklista!$B$2:$B$103,Terméklista!F$2:$F$103,))/1000} -> 0 | S87: =IFERROR(((H87/_xlfn.XLOOKUP(B87,Terméklista!$B$2:$B$103,Terméklista!$E$2:$E$103)*_xlfn.XLOOKUP(B87,Terméklista!$B$2:$B$103,Terméklista!$I$2:$I$103)))/3600," ") | T87: 2025/45
A88: Inter-Metal Recycling Kft. | B88: Forgács Vas | C88: =IFERROR(_xlfn.XLOOKUP(B88,Terméklista!$B$2:$B$103,Terméklista!$C$2:$C$103,)," ") -> VTSZ: 7204 | E88: M251045 | F88: =_xlfn.XLOOKUP(B88,Terméklista!$B$2:$B$103,Terméklista!$G$2:$G$103," ") -> Forgács | H88: 5 | L88: x | N88: =_xlfn.XLOOKUP(J88,Terméklista!$B$2:$B$103,Terméklista!$H$2:$H$103," ") -> 0 | O88: =IFERROR(ROUNDUP(Rendelés[[#This Row],[Amount/pc]]/_xlfn.XLOOKUP(B88,Terméklista!$B$2:$B$103,Terméklista!$M$2:$M$103,),0)," ") | P88: =IFERROR(ROUNDUP(Rendelés[[#This Row],[Dobozok száma]]/_xlfn.XLOOKUP(B88,Terméklista!$B$2:$B$103,Terméklista!$N$2:$N$103,),0)," ") | Q88: =IFERROR(Rendelés[[#This Row],[Szükséges anyagmennyiség]]+(Rendelés[[#This Row],[Össz raklapok száma]]*25),"") | R88: {=(H88*_xlfn.XLOOKUP(B88,Terméklista!$B$2:$B$103,Terméklista!F$2:$F$103,))/1000} -> 0 | S88: =IFERROR(((H88/_xlfn.XLOOKUP(B88,Terméklista!$B$2:$B$103,Terméklista!$E$2:$E$103)*_xlfn.XLOOKUP(B88,Terméklista!$B$2:$B$103,Terméklista!$I$2:$I$103)))/3600," ") | T88: 2025/38
A89: Inter-Metal Recycling Kft. | B89: Forgács Vas | C89: VTSZ: 7204 | E89: M251060 Pos-30 | F89: Forgács | H89: 3 | L89: x | N89: =IFERROR(_xlfn.XLOOKUP(B89,Terméklista!B58:B159,Terméklista!H58:H159)," ") -> 0 | O89: =IFERROR(ROUNDUP(Rendelés[[#This Row],[Amount/pc]]/_xlfn.XLOOKUP(B89,Terméklista!$B$2:$B$103,Terméklista!$M$2:$M$103,),0)," ") | P89: =IFERROR(ROUNDUP(Rendelés[[#This Row],[Dobozok száma]]/_xlfn.XLOOKUP(B89,Terméklista!$B$2:$B$103,Terméklista!$N$2:$N$103,),0)," ") | Q89: =IFERROR(Rendelés[[#This Row],[Szükséges anyagmennyiség]]+(Rendelés[[#This Row],[Össz raklapok száma]]*25),"") | R89: {=(H89*_xlfn.XLOOKUP(B89,Terméklista!$B$2:$B$103,Terméklista!F$2:$F$103,))/1000} -> 0 | S89: =IFERROR(((H89/_xlfn.XLOOKUP(B89,Terméklista!$B$2:$B$103,Terméklista!$E$2:$E$103)*_xlfn.XLOOKUP(B89,Terméklista!$B$2:$B$103,Terméklista!$I$2:$I$103)))/3600," ") | T89: 2025/45
A90: Inter-Metal Recycling Kft. | B90: Forgács Vegyes | C90: =IFERROR(_xlfn.XLOOKUP(B90,Terméklista!$B$2:$B$103,Terméklista!$C$2:$C$103,)," ") -> VTSZ: 7204 | E90: M251037 | F90: =_xlfn.XLOOKUP(B90,Terméklista!$B$2:$B$103,Terméklista!$G$2:$G$103," ") -> Forgács | H90: 4 | L90: x | N90: =_xlfn.XLOOKUP(J90,Terméklista!$B$2:$B$103,Terméklista!$H$2:$H$103," ") -> 0 | O90: =IFERROR(ROUNDUP(Rendelés[[#This Row],[Amount/pc]]/_xlfn.XLOOKUP(B90,Terméklista!$B$2:$B$103,Terméklista!$M$2:$M$103,),0)," ") | P90: =IFERROR(ROUNDUP(Rendelés[[#This Row],[Dobozok száma]]/_xlfn.XLOOKUP(B90,Terméklista!$B$2:$B$103,Terméklista!$N$2:$N$103,),0)," ") | Q90: =IFERROR(Rendelés[[#This Row],[Szükséges anyagmennyiség]]+(Rendelés[[#This Row],[Össz raklapok száma]]*25),"") | R90: {=(H90*_xlfn.XLOOKUP(B90,Terméklista!$B$2:$B$103,Terméklista!F$2:$F$103,))/1000} -> 0 | S90: =IFERROR(((H90/_xlfn.XLOOKUP(B90,Terméklista!$B$2:$B$103,Terméklista!$E$2:$E$103)*_xlfn.XLOOKUP(B90,Terméklista!$B$2:$B$103,Terméklista!$I$2:$I$103)))/3600," ") | T90: 2025/32
A91: Inter-Metal Recycling Kft. | B91: Vas lemez hulladék | C91: =IFERROR(_xlfn.XLOOKUP(B91,Terméklista!$B$2:$B$103,Terméklista!$C$2:$C$103,)," ") -> VTSZ:7204 | E91: M251047 | F91: =_xlfn.XLOOKUP(B91,Terméklista!$B$2:$B$103,Terméklista!$G$2:$G$103," ") -> Forgács | H91: 1 | L91: x | N91: =IFERROR(_xlfn.XLOOKUP(B91,Terméklista!B46:B147,Terméklista!H46:H147)," ") -> 0 | O91: =IFERROR(ROUNDUP(Rendelés[[#This Row],[Amount/pc]]/_xlfn.XLOOKUP(B91,Terméklista!$B$2:$B$103,Terméklista!$M$2:$M$103,),0)," ") | P91: =IFERROR(ROUNDUP(Rendelés[[#This Row],[Dobozok száma]]/_xlfn.XLOOKUP(B91,Terméklista!$B$2:$B$103,Terméklista!$N$2:$N$103,),0)," ") | Q91: =IFERROR(Rendelés[[#This Row],[Szükséges anyagmennyiség]]+(Rendelés[[#This Row],[Össz raklapok száma]]*25),"") | R91: {=(H91*_xlfn.XLOOKUP(B91,Terméklista!$B$2:$B$103,Terméklista!F$2:$F$103,))/1000} -> 0 | S91: =IFERROR(((H91/_xlfn.XLOOKUP(B91,Terméklista!$B$2:$B$103,Terméklista!$E$2:$E$103)*_xlfn.XLOOKUP(B91,Terméklista!$B$2:$B$103,Terméklista!$I$2:$I$103)))/3600," ")
A92: Ela Solutions Kft. | B92: 90ZA-ZK001-06 | C92: =IFERROR(_xlfn.XLOOKUP(B92,Terméklista!$B$2:$B$103,Terméklista!$C$2:$C$103,)," ") -> 0 | F92: =_xlfn.XLOOKUP(B92,Terméklista!B91:B192,Terméklista!G91:G192," ") | G92: 5947 | H92: 500 | I92: 2025-10-21 | J92: 2025-10-27 | L92: x | N92: =IFERROR(_xlfn.XLOOKUP(B92,Terméklista!B91:B192,Terméklista!H91:H192)," ") | O92: =IFERROR(ROUNDUP(Rendelés[[#This Row],[Amount/pc]]/_xlfn.XLOOKUP(B92,Terméklista!$B$2:$B$103,Terméklista!$M$2:$M$103,),0)," ") | P92: =IFERROR(ROUNDUP(Rendelés[[#This Row],[Dobozok száma]]/_xlfn.XLOOKUP(B92,Terméklista!$B$2:$B$103,Terméklista!$N$2:$N$103,),0)," ") | Q92: =IFERROR(Rendelés[[#This Row],[Szükséges anyagmennyiség]]+(Rendelés[[#This Row],[Össz raklapok száma]]*25),"") | R92: {=(H92*_xlfn.XLOOKUP(B92,Terméklista!$B$2:$B$103,Terméklista!F$2:$F$103,))/1000} -> 11.17 | S92: =IFERROR(((H92/_xlfn.XLOOKUP(B92,Terméklista!$B$2:$B$103,Terméklista!$E$2:$E$103)*_xlfn.XLOOKUP(B92,Terméklista!$B$2:$B$103,Terméklista!$I$2:$I$103)))/3600," ") -> 1.0416667
A93: Seidel Gmbh&co Kg | B93: MA51 | C93: =IFERROR(_xlfn.XLOOKUP(B93,Terméklista!$B$2:$B$103,Terméklista!$C$2:$C$103,)," ") -> Zamak Gewicht | D93: POS010 | F93: =_xlfn.XLOOKUP(B93,Terméklista!B92:B193,Terméklista!G92:G193," ") | G93: 4500103801 | H93: 50000 | I93: 2025-11-03 | J93: 2026-01-15 | L93: x | M93: CMR | N93: =IFERROR(_xlfn.XLOOKUP(B93,Terméklista!B92:B193,Terméklista!H92:H193)," ") | O93: =IFERROR(ROUNDUP(Rendelés[[#This Row],[Amount/pc]]/_xlfn.XLOOKUP(B93,Terméklista!$B$2:$B$103,Terméklista!$M$2:$M$103,),0)," ") -> 143 | P93: =IFERROR(ROUNDUP(Rendelés[[#This Row],[Dobozok száma]]/_xlfn.XLOOKUP(B93,Terméklista!$B$2:$B$103,Terméklista!$N$2:$N$103,),0)," ") -> 5 | Q93: =IFERROR(Rendelés[[#This Row],[Szükséges anyagmennyiség]]+(Rendelés[[#This Row],[Össz raklapok száma]]*25),"") -> 1551 | R93: {=(H93*_xlfn.XLOOKUP(B93,Terméklista!$B$2:$B$103,Terméklista!F$2:$F$103,))/1000} -> 1426 | S93: =IFERROR(((H93/_xlfn.XLOOKUP(B93,Terméklista!$B$2:$B$103,Terméklista!$E$2:$E$103)*_xlfn.XLOOKUP(B93,Terméklista!$B$2:$B$103,Terméklista!$I$2:$I$103)))/3600," ") -> 69.444444 | T93: 2026/82
A94: Ela Solutions Kft. | B94: 90ZA-ZK010-06 | C94: =IFERROR(_xlfn.XLOOKUP(B94,Terméklista!$B$2:$B$103,Terméklista!$C$2:$C$103,)," ") -> kereszt kulcs | D94: EMKE logó | F94: =_xlfn.XLOOKUP(B94,Terméklista!B93:B194,Terméklista!G93:G194," ") | G94: 5966 | H94: 470 | I94: 2025-11-05 | J94: 2025-11-11 | L94: x | N94: =IFERROR(_xlfn.XLOOKUP(B94,Terméklista!B93:B194,Terméklista!H93:H194)," ") | O94: =IFERROR(ROUNDUP(Rendelés[[#This Row],[Amount/pc]]/_xlfn.XLOOKUP(B94,Terméklista!$B$2:$B$103,Terméklista!$M$2:$M$103,),0)," ") | P94: =IFERROR(ROUNDUP(Rendelés[[#This Row],[Dobozok száma]]/_xlfn.XLOOKUP(B94,Terméklista!$B$2:$B$103,Terméklista!$N$2:$N$103,),0)," ") | Q94: =IFERROR(Rendelés[[#This Row],[Szükséges anyagmennyiség]]+(Rendelés[[#This Row],[Össz raklapok száma]]*25),"") | R94: {=(H94*_xlfn.XLOOKUP(B94,Terméklista!$B$2:$B$103,Terméklista!F$2:$F$103,))/1000} -> 28.623 | S94: =IFERROR(((H94/_xlfn.XLOOKUP(B94,Terméklista!$B$2:$B$103,Terméklista!$E$2:$E$103)*_xlfn.XLOOKUP(B94,Terméklista!$B$2:$B$103,Terméklista!$I$2:$I$103)))/3600," ") -> 1.9583333 | T94: 2025/75
A95: Inter-Metal Recycling Kft. | B95: Forgács Rozsdamentés | E95: M251068 Pos-10 | F95: Forgács | H95: 1 | L95: x | N95: =IFERROR(_xlfn.XLOOKUP(B95,Terméklista!B94:B195,Terméklista!H94:H195)," ") | O95: =IFERROR(ROUNDUP(Rendelés[[#This Row],[Amount/pc]]/_xlfn.XLOOKUP(B95,Terméklista!$B$2:$B$103,Terméklista!$M$2:$M$103,),0)," ") | P95: =IFERROR(ROUNDUP(Rendelés[[#This Row],[Dobozok száma]]/_xlfn.XLOOKUP(B95,Terméklista!$B$2:$B$103,Terméklista!$N$2:$N$103,),0)," ") | Q95: =IFERROR(Rendelés[[#This Row],[Szükséges anyagmennyiség]]+(Rendelés[[#This Row],[Össz raklapok száma]]*25),"") | R95: {=(H95*_xlfn.XLOOKUP(B95,Terméklista!$B$2:$B$103,Terméklista!F$2:$F$103,))/1000} -> 0 | S95: =IFERROR(((H95/_xlfn.XLOOKUP(B95,Terméklista!$B$2:$B$103,Terméklista!$E$2:$E$103)*_xlfn.XLOOKUP(B95,Terméklista!$B$2:$B$103,Terméklista!$I$2:$I$103)))/3600," ") | T95: 2025/76
A96: Inter-Metal Recycling Kft. | B96: Forgács Aluminium | E96: M251068 Pos-20 | F96: Forgács | H96: 2 | L96: x | N96: =IFERROR(_xlfn.XLOOKUP(B96,Terméklista!B95:B196,Terméklista!H95:H196)," ") | O96: =IFERROR(ROUNDUP(Rendelés[[#This Row],[Amount/pc]]/_xlfn.XLOOKUP(B96,Terméklista!$B$2:$B$103,Terméklista!$M$2:$M$103,),0)," ") | P96: =IFERROR(ROUNDUP(Rendelés[[#This Row],[Dobozok száma]]/_xlfn.XLOOKUP(B96,Terméklista!$B$2:$B$103,Terméklista!$N$2:$N$103,),0)," ") | Q96: =IFERROR(Rendelés[[#This Row],[Szükséges anyagmennyiség]]+(Rendelés[[#This Row],[Össz raklapok száma]]*25),"") | R96: {=(H96*_xlfn.XLOOKUP(B96,Terméklista!$B$2:$B$103,Terméklista!F$2:$F$103,))/1000} -> 0 | S96: =IFERROR(((H96/_xlfn.XLOOKUP(B96,Terméklista!$B$2:$B$103,Terméklista!$E$2:$E$103)*_xlfn.XLOOKUP(B96,Terméklista!$B$2:$B$103,Terméklista!$I$2:$I$103)))/3600," ") | T96: 2026/01
A97: Inter-Metal Recycling Kft. | B97: Forgács Vas | E97: M251068 Pos-30 | F97: Forgács | H97: 4 | L97: x | N97: =IFERROR(_xlfn.XLOOKUP(B97,Terméklista!B96:B197,Terméklista!H96:H197)," ") | O97: =IFERROR(ROUNDUP(Rendelés[[#This Row],[Amount/pc]]/_xlfn.XLOOKUP(B97,Terméklista!$B$2:$B$103,Terméklista!$M$2:$M$103,),0)," ") | P97: =IFERROR(ROUNDUP(Rendelés[[#This Row],[Dobozok száma]]/_xlfn.XLOOKUP(B97,Terméklista!$B$2:$B$103,Terméklista!$N$2:$N$103,),0)," ") | Q97: =IFERROR(Rendelés[[#This Row],[Szükséges anyagmennyiség]]+(Rendelés[[#This Row],[Össz raklapok száma]]*25),"") | R97: {=(H97*_xlfn.XLOOKUP(B97,Terméklista!$B$2:$B$103,Terméklista!F$2:$F$103,))/1000} -> 0 | S97: =IFERROR(((H97/_xlfn.XLOOKUP(B97,Terméklista!$B$2:$B$103,Terméklista!$E$2:$E$103)*_xlfn.XLOOKUP(B97,Terméklista!$B$2:$B$103,Terméklista!$I$2:$I$103)))/3600," ") | T97: 2026/01
A98: Seidel Gmbh&co Kg | B98: MA41 | C98: =IFERROR(_xlfn.XLOOKUP(B98,Terméklista!$B$2:$B$103,Terméklista!$C$2:$C$103,)," ") -> Zamak Gewicht | D98: POS010 | F98: =_xlfn.XLOOKUP(B98,Terméklista!B97:B198,Terméklista!G97:G198," ") | G98: 4500104015 | H98: 100000 | I98: 2025-11-17 | J98: 2026-02-09 | K98: 2026-02-10 | L98: x | M98: CMR | N98: =IFERROR(_xlfn.XLOOKUP(B98,Terméklista!B97:B198,Terméklista!H97:H198)," ") | O98: =IFERROR(ROUNDUP(Rendelés[[#This Row],[Amount/pc]]/_xlfn.XLOOKUP(B98,Terméklista!$B$2:$B$103,Terméklista!$M$2:$M$103,),0)," ") -> 286 | P98: =IFERROR(ROUNDUP(Rendelés[[#This Row],[Dobozok száma]]/_xlfn.XLOOKUP(B98,Terméklista!$B$2:$B$103,Terméklista!$N$2:$N$103,),0)," ") -> 4 | Q98: =IFERROR(Rendelés[[#This Row],[Szükséges anyagmennyiség]]+(Rendelés[[#This Row],[Össz raklapok száma]]*25),"") -> 1800 | R98: {=(H98*_xlfn.XLOOKUP(B98,Terméklista!$B$2:$B$103,Terméklista!F$2:$F$103,))/1000} -> 1700 | S98: =IFERROR(((H98/_xlfn.XLOOKUP(B98,Terméklista!$B$2:$B$103,Terméklista!$E$2:$E$103)*_xlfn.XLOOKUP(B98,Terméklista!$B$2:$B$103,Terméklista!$I$2:$I$103)))/3600," ") -> 69.444444 | T98: 2026/5 | U98: kiszállítva
A99: Seidel Gmbh&co Kg | B99: MA66 | C99: =IFERROR(_xlfn.XLOOKUP(B99,Terméklista!$B$2:$B$103,Terméklista!$C$2:$C$103,)," ") -> Zamak Gewicht | D99: POS010 | F99: =_xlfn.XLOOKUP(B99,Terméklista!B98:B199,Terméklista!G98:G199," ") | G99: 4500104126 | H99: 200000 | I99: 2025-11-25 | J99: 2026-03-09 | N99: =IFERROR(_xlfn.XLOOKUP(B99,Terméklista!B98:B199,Terméklista!H98:H199)," ") | O99: =IFERROR(ROUNDUP(Rendelés[[#This Row],[Amount/pc]]/_xlfn.XLOOKUP(B99,Terméklista!$B$2:$B$103,Terméklista!$M$2:$M$103,),0)," ") -> 400 | P99: =IFERROR(ROUNDUP(Rendelés[[#This Row],[Dobozok száma]]/_xlfn.XLOOKUP(B99,Terméklista!$B$2:$B$103,Terméklista!$N$2:$N$103,),0)," ") -> 5 | Q99: =IFERROR(Rendelés[[#This Row],[Szükséges anyagmennyiség]]+(Rendelés[[#This Row],[Össz raklapok száma]]*25),"") -> 2225 | R99: {=(H99*_xlfn.XLOOKUP(B99,Terméklista!$B$2:$B$103,Terméklista!F$2:$F$103,))/1000} -> 2100 | S99: =IFERROR(((H99/_xlfn.XLOOKUP(B99,Terméklista!$B$2:$B$103,Terméklista!$E$2:$E$103)*_xlfn.XLOOKUP(B99,Terméklista!$B$2:$B$103,Terméklista!$I$2:$I$103)))/3600," ") -> 138.88889 | U99: folyamatban
A100: Seidel Gmbh&co Kg | B100: MA66 | C100: =IFERROR(_xlfn.XLOOKUP(B100,Terméklista!$B$2:$B$103,Terméklista!$C$2:$C$103,)," ") -> Zamak Gewicht | D100: POS010 | F100: =_xlfn.XLOOKUP(B100,Terméklista!B99:B200,Terméklista!G99:G200," ") | G100: 4500104215 | H100: 250000 | I100: 2025-12-02 | J100: 2026-03-16 | N100: =IFERROR(_xlfn.XLOOKUP(B100,Terméklista!B99:B200,Terméklista!H99:H200)," ") | O100: =IFERROR(ROUNDUP(Rendelés[[#This Row],[Amount/pc]]/_xlfn.XLOOKUP(B100,Terméklista!$B$2:$B$103,Terméklista!$M$2:$M$103,),0)," ") -> 500 | P100: =IFERROR(ROUNDUP(Rendelés[[#This Row],[Dobozok száma]]/_xlfn.XLOOKUP(B100,Terméklista!$B$2:$B$103,Terméklista!$N$2:$N$103,),0)," ") -> 6 | Q100: =IFERROR(Rendelés[[#This Row],[Szükséges anyagmennyiség]]+(Rendelés[[#This Row],[Össz raklapok száma]]*25),"") -> 2775 | R100: {=(H100*_xlfn.XLOOKUP(B100,Terméklista!$B$2:$B$103,Terméklista!F$2:$F$103,))/1000} -> 2625 | S100: =IFERROR(((H100/_xlfn.XLOOKUP(B100,Terméklista!$B$2:$B$103,Terméklista!$E$2:$E$103)*_xlfn.XLOOKUP(B100,Terméklista!$B$2:$B$103,Terméklista!$I$2:$I$103)))/3600," ") -> 173.61111 | U100: ~02.23. indul
...

Sheet Gyártás-Csomagolás
A1: Megrendelési információ | J1: Lila | K1: 11 | M1: =SUM(M3:M762) -> 0 | Y1: 25
A2: Customer | B2: Termék neve | C2: Megnevezése | D2: Megjegyzés | E2: Saját rendelési szám | F2: Anyag | G2: Mennyiség | H2: Required delivery date (year/month/day) | I2: Felületkezelés | J2: Szállításra kész | K2: Össz dobozok száma db | L2: Össz raklapok száma | M2: Össz nettó súly | N2: Össz bruttó súly | O2: címke adatok/doboz doboz: termék darab, dátum | P2: milyen utómunka kell pl mosás (M), sorjázás (S), koptatás (K) válogatás (V) kézi tördelés (KT) (felsorolás) | Q2: Utómunka fele kész (x) | R2: Utómunka kész (x) | S2: MEO megtörtént (x) | T2: Selejt % | U2: Mérés & Dobozolás kész (x) | V2: Szállítható (dátum) | W2: Várható késés (x) | X2: Új időpont késés esetén | Y2: rendelési szám
A3: Arsisco AMO Pack LLC | C3: 0 | E3: szerszám - sin5 | H3: 2025-07-16 | I3: =IFERROR(_xlfn.XLOOKUP(B3,Terméklista!$B$6:$B$105,Terméklista!$H$6:$H$105)," ") -> 0 | N3: =IFERROR(M3+(L3*30),"")
A4: Arsisco AMO Pack LLC | C4: 0 | D4: szerszám - sin5 | E4: M251044 | H4: 2025-07-16 | I4: =IFERROR(_xlfn.XLOOKUP(B4,Terméklista!$B$6:$B$105,Terméklista!$H$6:$H$105)," ") -> 0 | N4: =IFERROR(M4+(L4*30),"")
A5: Fasten Italia S.R.L | B5: P6 body | C5: 0 | G5: 11000 | I5: =IFERROR(_xlfn.XLOOKUP(B5,Terméklista!$B$6:$B$105,Terméklista!$H$6:$H$105)," ") -> 0 | N5: =IFERROR(M5+(L5*30),"") -> 0 | Y5: 25/00646
A6: Fasten Italia S.R.L | B6: YKK fogó | C6: 0 | G6: 30000 | I6: =IFERROR(_xlfn.XLOOKUP(B6,Terméklista!$B$6:$B$105,Terméklista!$H$6:$H$105)," ") -> 0 | N6: =IFERROR(M6+(L6*30),"") -> 0 | Y6: 25/00646
A7: Seidel Gmbh&co Kg | B7: MA66 | C7: Zamak Gewicht | D7: POS010 | G7: 200000 | H7: 2026-03-09 | I7: =IFERROR(_xlfn.XLOOKUP(B7,Terméklista!$B$6:$B$105,Terméklista!$H$6:$H$105)," ") -> 0 | N7: =IFERROR(M7+(L7*30),"") -> 0 | Y7: 4500104126
A8: Seidel Gmbh&co Kg | B8: MA66 | C8: Zamak Gewicht | D8: POS010 | G8: 250000 | H8: 2026-03-16 | I8: =IFERROR(_xlfn.XLOOKUP(B8,Terméklista!$B$6:$B$105,Terméklista!$H$6:$H$105)," ") -> 0 | N8: =IFERROR(M8+(L8*30),"") -> 0 | Y8: 4500104215
A9: Seidel Gmbh&co Kg | B9: M83 | C9: Zamak Gewicht | D9: POS010 | G9: 33750 | H9: 2026-02-25 | I9: =IFERROR(_xlfn.XLOOKUP(B9,Terméklista!$B$6:$B$105,Terméklista!$H$6:$H$105)," ") -> 0 | N9: =IFERROR(M9+(L9*30),"") -> 0 | Y9: 4500104347
A10: Seidel Gmbh&co Kg | B10: MA41 | C10: Zamak Gewicht | D10: POS020 | G10: 50000 | H10: 2026-02-25 | I10: =IFERROR(_xlfn.XLOOKUP(B10,Terméklista!$B$6:$B$105,Terméklista!$H$6:$H$105)," ") -> 0 | N10: =IFERROR(M10+(L10*30),"") -> 0 | Y10: 4500104347
A11: Seidel Gmbh&co Kg | B11: MB22 | C11: Zamak Gewicht | D11: POS030 | G11: 80000 | H11: 2026-02-25 | I11: =IFERROR(_xlfn.XLOOKUP(B11,Terméklista!$B$6:$B$105,Terméklista!$H$6:$H$105)," ") -> 0 | N11: =IFERROR(M11+(L11*30),"") -> 0 | Y11: 4500104347
A12: Seidel Gmbh&co Kg | C12: 0 | D12: MB44 szerszám | G12: 1 | H12: 2026-03-24 | I12: =IFERROR(_xlfn.XLOOKUP(B12,Terméklista!$B$6:$B$105,Terméklista!$H$6:$H$105)," ") -> 0 | N12: =IFERROR(M12+(L12*30),"") -> 0 | Y12: 4500104683
A13: Seidel Gmbh&co Kg | B13: MB44 | C13: 80 0230 018 001 01 02 | D13: POS020 | G13: 500 | H13: 2026-03-31 | I13: =IFERROR(_xlfn.XLOOKUP(B13,Terméklista!$B$6:$B$105,Terméklista!$H$6:$H$105)," ") -> 0 | N13: =IFERROR(M13+(L13*30),"") -> 0 | Y13: 4500104683
A14: Seidel Gmbh&co Kg | B14: MA51 | C14: Zamak Gewicht | D14: POS010, rendelés módosítás 2026.02.04én | G14: 50000 | H14: 2026-02-25 | I14: =IFERROR(_xlfn.XLOOKUP(B14,Terméklista!$B$6:$B$105,Terméklista!$H$6:$H$105)," ") -> 0 | J14: x | N14: =IFERROR(M14+(L14*30),"") -> 0 | Y14: 4500104784
A15: Systec Pos-Technology Gmbh | B15: Sperritzteil-2 | E15: M251070 Pos-10 | G15: 10000 | H15: 2026-03-23 | I15: =IFERROR(_xlfn.XLOOKUP(B15,Terméklista!$B$6:$B$105,Terméklista!$H$6:$H$105)," ") -> 0 | N15: =IFERROR(M15+(L15*30),"") -> 0 | Y15: 27366
A16: Inter-Metal Recycling Kft. | B16: Forgács Aluminium | E16: M251071 Pos-10 | G16: 5 | I16: =IFERROR(_xlfn.XLOOKUP(B16,Terméklista!$B$6:$B$105,Terméklista!$H$6:$H$105)," ") -> 0 | N16: =IFERROR(M16+(L16*30),"") -> 0
A17: Inter-Metal Recycling Kft. | B17: Forgács Rozsdamentés | E17: M251071 Pos-20 | G17: 1 | I17: =IFERROR(_xlfn.XLOOKUP(B17,Terméklista!$B$6:$B$105,Terméklista!$H$6:$H$105)," ") -> 0 | N17: =IFERROR(M17+(L17*30),"") -> 0
A18: Inter-Metal Recycling Kft. | B18: Forgács Vegyes | E18: M251071 Pos-30 | G18: 1 | I18: =IFERROR(_xlfn.XLOOKUP(B18,Terméklista!$B$6:$B$105,Terméklista!$H$6:$H$105)," ") -> 0 | N18: =IFERROR(M18+(L18*30),"") -> 0
A19: Ela Solutions Kft. | B19: 90ZA-ZK001-06 | G19: 1500 | H19: 2026-02-20 | I19: =IFERROR(_xlfn.XLOOKUP(B19,Terméklista!$B$6:$B$105,Terméklista!$H$6:$H$105)," ") -> 0 | N19: =IFERROR(M19+(L19*30),"") -> 0 | Y19: 6076
A20: Seidel Gmbh&co Kg | B20: MA51 | D20: POS020 | G20: 50000 | H20: 2026-03-16 | I20: =IFERROR(_xlfn.XLOOKUP(B20,Terméklista!$B$6:$B$105,Terméklista!$H$6:$H$105)," ") -> 0 | N20: =IFERROR(M20+(L20*30),"") -> 0 | Y20: 4500104784
A21: Seidel Gmbh&co Kg | B21: MA41 | D21: POS010 | G21: 50000 | H21: 2026-04-13 | I21: =IFERROR(_xlfn.XLOOKUP(B21,Terméklista!$B$6:$B$105,Terméklista!$H$6:$H$105)," ") -> 0 | N21: =IFERROR(M21+(L21*30),"") -> 0 | Y21: 4500105052
A22: Seidel Gmbh&co Kg | B22: MA66 | D22: POS010 | G22: 250000 | H22: 2026-06-01 | I22: =IFERROR(_xlfn.XLOOKUP(B22,Terméklista!$B$6:$B$105,Terméklista!$H$6:$H$105)," ") -> 0 | N22: =IFERROR(M22+(L22*30),"") -> 0 | Y22: 4500105053

Sheet Terméklista
A1: Ügyfél | B1: Termék rajzszáma | C1: Termék megnevezés | D1: Megjegyzés | E1: Fészekszáma | F1: Súly/db g | G1: Anyag | H1: Felületkezelés | I1: Ciklus idő | J1: Utómunka idő | K1: Utómunkák | L1: Doboz méret | M1: Doboz/db | N1: Doboz/Raklap | O1: Arktikál nr. | P1: Raktár | Q1: Engusz súly
A2: Arsisco AMO Pack LLC | B2: Fehér hüvely | E2: 4 | F2: 0.225 | G2: Műanyag | I2: 13 | Q2: 0.675
A3: Arsisco AMO Pack LLC | B3: Töltő sin | G3: Z414 | I3: 15
A4: Arsisco AMO Pack LLC | B4: Lánctalp | G4: Z414 | I4: 15
A5: Ela Solutions Kft. | B5: 90ZA-AD001-00 | C5: rúdadapter | D5: Logó | E5: 2 | F5: 21.6 | G5: Z410 | I5: 15
A6: Ela Solutions Kft. | B6: 90ZA-B001-06 | C6: zárbetét - 3mm | E6: 2 | F6: 14.85 | G6: Z410 | I6: 15
A7: Ela Solutions Kft. | B7: 90ZA-B003-06 | E7: 2 | F7: 15.6 | G7: Z410 | I7: 15
A8: Ela Solutions Kft. | B8: 90ZA-B004-06 | C8: zárbetét | E8: 2 | F8: 8.1 | G8: Z410 | I8: 15 | V8: {=TRANSPOSE(_xlfn._xlws.SORT(_xlfn.UNIQUE(Alkatrészek[Ügyfél])))} -> Arsisco AMO Pack LLC | W8: Ela Solutions Kft. | X8: Fasten Italia S.R.L | Y8: Inter-Metal Recycling Kft. | Z8: Ligeti Péter | AA8: R-Plast Manufacturing Kft | AB8: R-Szerkterv Kft. | AC8: Seidel Gmbh&co Kg | AD8: Systec Pos-Technology Gmbh
A9: Ela Solutions Kft. | B9: 90ZA-B007-04 | C9: zárbetét - 9,5mm 3szög | E9: 2 | F9: 12 | G9: Z410 | I9: 15 | V9: {=_xlfn._xlws.FILTER(Alkatrészek[Termék rajzszáma],Alkatrészek[Ügyfél]=V8,"")} -> Fehér hüvely | W9: {=_xlfn._xlws.FILTER(Alkatrészek[Termék rajzszáma],Alkatrészek[Ügyfél]=W8,"")} -> 90ZA-AD001-00 | X9: {=_xlfn._xlws.FILTER(Alkatrészek[Termék rajzszáma],Alkatrészek[Ügyfél]=X8,"")} -> corpoP6 nyitó | Y9: {=_xlfn._xlws.FILTER(Alkatrészek[Termék rajzszáma],Alkatrészek[Ügyfél]=Y8,"")} -> Forgács Aluminium | Z9: {=_xlfn._xlws.FILTER(Alkatrészek[Termék rajzszáma],Alkatrészek[Ügyfél]=Z8,"")} -> nyersanyag | AA9: {=_xlfn._xlws.FILTER(Alkatrészek[Termék rajzszáma],Alkatrészek[Ügyfél]=AA8,"")} -> Magasságállító | AB9: {=_xlfn._xlws.FILTER(Alkatrészek[Termék rajzszáma],Alkatrészek[Ügyfél]=AB8,"")} -> M 400-2 | AC9: {=_xlfn._xlws.FILTER(Alkatrészek[Termék rajzszáma],Alkatrészek[Ügyfél]=AC8,"")} -> B83 | AD9: {=_xlfn._xlws.FILTER(Alkatrészek[Termék megnevezés],Alkatrészek[Termék rajzszáma]=AD8,"")} | AE9: {=_xlfn._xlws.FILTER(Alkatrészek[Termék rajzszáma],Alkatrészek[Ügyfél]=AE8,"")} | AF9: {=_xlfn._xlws.FILTER(Alkatrészek[Termék rajzszáma],Alkatrészek[Ügyfél]=AF8,"")} | AG9: {=_xlfn._xlws.FILTER(Alkatrészek[Termék rajzszáma],Alkatrészek[Ügyfél]=AG8,"")}
A10: Ela Solutions Kft. | B10: 90ZA-B008-04 | E10: 2 | F10: 12.5 | G10: Z410 | I10: 15 | V10: Töltő sin | W10: 90ZA-B001-06 | X10: P6 body | Y10: Forgács Rozsdamentés | AA10: Szíj rövid | AB10: M 400-4 | AC10: B93 | AD10: {=_xlfn._xlws.FILTER(Alkatrészek[Termék megnevezés],Alkatrészek[Termék rajzszáma]=AD9,"")}
A11: Ela Solutions Kft. | B11: 90ZA-B009-04 | C11: Zárbetét 2x4-es sliccel | E11: 2 | F11: 17.4 | G11: Z410 | I11: 15 | V11: Lánctalp | W11: 90ZA-B003-06 | X11: YKK fogó | Y11: Forgács Vas | AA11: Szíj hosszú | AC11: M66 | AD11: {=_xlfn._xlws.FILTER(Alkatrészek[Termék megnevezés],Alkatrészek[Termék rajzszáma]=AD10,"")}
A12: Ela Solutions Kft. | B12: 90ZA-B010-04 | C12: zárbetét sliccel | E12: 2 | F12: 7 | G12: Z410 | I12: 15 | V12: Sín 5 | W12: 90ZA-B004-06 | X12: P6 body szerszám | Y12: Forgács Vegyes | AA12: Pánt | AC12: M70 | AD12: {=_xlfn._xlws.FILTER(Alkatrészek[Termék megnevezés],Alkatrészek[Termék rajzszáma]=AD11,"")}
A13: Ela Solutions Kft. | B13: 90ZA-B012-06 | C13: zárbetét - 8mm | E13: 2 | F13: 12.2 | G13: Z410 | I13: 15 | W13: 90ZA-B007-04 | Y13: Vas lemez hulladék | AA13: Szíj doboz | AC13: M83 | AD13: {=_xlfn._xlws.FILTER(Alkatrészek[Termék megnevezés],Alkatrészek[Termék rajzszáma]=AD12,"")}
A14: Ela Solutions Kft. | B14: 90ZA-H001-06 | C14: zárház | E14: 2 | F14: 24.5 | G14: Z410 | I14: 15 | W14: 90ZA-B008-04 | Y14: Csöpedék - Horgany | AC14: MA41 | AD14: {=_xlfn._xlws.FILTER(Alkatrészek[Termék megnevezés],Alkatrészek[Termék rajzszáma]=AD13,"")}
A15: Ela Solutions Kft. | B15: 90ZA-H002-06 | C15: zárház | E15: 2 | F15: 18.5 | G15: Z410 | I15: 15 | W15: 90ZA-B009-04 | Y15: Réz | AC15: MA51 | AD15: {=_xlfn._xlws.FILTER(Alkatrészek[Termék megnevezés],Alkatrészek[Termék rajzszáma]=AD14,"")}
A16: Ela Solutions Kft. | B16: 90ZA-H005-04 | C16: zárház | E16: 2 | F16: 8.3 | G16: Z410 | I16: 15 | W16: 90ZA-B010-04 | AC16: MA62 | AD16: {=_xlfn._xlws.FILTER(Alkatrészek[Termék megnevezés],Alkatrészek[Termék rajzszáma]=AD15,"")}
A17: Ela Solutions Kft. | B17: 90ZA-H020-06 | C17: lakattal zárható zárház | E17: 2 | F17: 92.53 | G17: Z410 | I17: 15 | W17: 90ZA-B012-06 | AC17: MA66 | AD17: {=_xlfn._xlws.FILTER(Alkatrészek[Termék megnevezés],Alkatrészek[Termék rajzszáma]=AD16,"")}
A18: Ela Solutions Kft. | B18: 90ZA-H021-06 | C18: lakattal zárható zárház | E18: 2 | F18: 92.56 | G18: Z410 | I18: 15 | W18: 90ZA-H001-06 | AC18: MB01 | AD18: {=_xlfn._xlws.FILTER(Alkatrészek[Termék megnevezés],Alkatrészek[Termék rajzszáma]=AD17,"")}
A19: Ela Solutions Kft. | B19: 90ZA-HT001-00 | C19: anya M22x1,5 | E19: 6 | F19: 8.3 | G19: Z410 | I19: 15 | W19: 90ZA-H002-06 | AC19: MB22 | AD19: {=_xlfn._xlws.FILTER(Alkatrészek[Termék megnevezés],Alkatrészek[Termék rajzszáma]=AD18,"")}
A20: Ela Solutions Kft. | B20: 90ZA-HT001-00 | C20: anya M22x1,5 (30.000 db) | E20: 6 | F20: 8.3 | G20: Z410 | I20: 15 | W20: 90ZA-H005-04 | AC20: MB44 | AD20: {=_xlfn._xlws.FILTER(Alkatrészek[Termék megnevezés],Alkatrészek[Termék rajzszáma]=AD19,"")}
A21: Ela Solutions Kft. | B21: 90ZA-HT002-00 | C21: anya M16x1 | E21: 6 | F21: 2.5 | G21: Z410 | I21: 15 | W21: 90ZA-H020-06 | AD21: {=_xlfn._xlws.FILTER(Alkatrészek[Termék megnevezés],Alkatrészek[Termék rajzszáma]=AD20,"")}
A22: Ela Solutions Kft. | B22: 90ZA-HT004-00 | E22: 4 | F22: 5.2 | G22: Z410 | I22: 15 | W22: 90ZA-H021-06 | AD22: {=_xlfn._xlws.FILTER(Alkatrészek[Termék megnevezés],Alkatrészek[Termék rajzszáma]=AD21,"")}
A23: Ela Solutions Kft. | B23: 90ZA-NY001-00 | C23: fogasnyelv | E23: 2 | F23: 14.9 | G23: Z410 | I23: 15 | W23: 90ZA-HT001-00 | AD23: {=_xlfn._xlws.FILTER(Alkatrészek[Termék megnevezés],Alkatrészek[Termék rajzszáma]=AD22,"")}
A24: Ela Solutions Kft. | B24: 90ZA-ZK001-06 | E24: 2 | F24: 22.34 | G24: Z410 | I24: 15 | W24: 90ZA-HT001-00 | AD24: {=_xlfn._xlws.FILTER(Alkatrészek[Termék megnevezés],Alkatrészek[Termék rajzszáma]=AD23,"")}
A25: Ela Solutions Kft. | B25: 90ZA-ZK006-06 | C25: kulcs - 8mm | E25: 2 | F25: 23.6 | G25: Z410 | I25: 15 | W25: 90ZA-HT002-00 | AD25: {=_xlfn._xlws.FILTER(Alkatrészek[Termék megnevezés],Alkatrészek[Termék rajzszáma]=AD24,"")}
A26: Ela Solutions Kft. | B26: 90ZA-ZK007-06 | C26: kulcs 10mm 3szög | E26: 2 | F26: 25.3 | G26: Z410 | I26: 15 | W26: 90ZA-HT004-00 | AD26: {=_xlfn._xlws.FILTER(Alkatrészek[Termék megnevezés],Alkatrészek[Termék rajzszáma]=AD25,"")}
A27: Ela Solutions Kft. | B27: 90ZA-ZK008-06 | C27: kiskulcs - 3mm | E27: 2 | F27: 22.8 | G27: Z410 | I27: 15 | W27: 90ZA-NY001-00 | AD27: {=_xlfn._xlws.FILTER(Alkatrészek[Termék megnevezés],Alkatrészek[Termék rajzszáma]=AD26,"")}
A28: Ela Solutions Kft. | B28: 90ZA-ZK009-06 | E28: 2 | F28: 21.7 | G28: Z410 | I28: 15 | W28: 90ZA-ZK001-06 | AD28: {=_xlfn._xlws.FILTER(Alkatrészek[Termék megnevezés],Alkatrészek[Termék rajzszáma]=AD27,"")}
A29: Ela Solutions Kft. | B29: 90ZA-ZK010-06 | C29: kereszt kulcs | E29: 1 | F29: 60.9 | G29: Z410 | I29: 15 | W29: 90ZA-ZK006-06 | AD29: {=_xlfn._xlws.FILTER(Alkatrészek[Termék megnevezés],Alkatrészek[Termék rajzszáma]=AD28,"")}
A30: Ela Solutions Kft. | B30: 90ZA-ZK011-06 | C30: nagykulcs - 3mm | E30: 2 | F30: 47.55 | G30: Z410 | I30: 15 | W30: 90ZA-ZK007-06 | AD30: {=_xlfn._xlws.FILTER(Alkatrészek[Termék megnevezés],Alkatrészek[Termék rajzszáma]=AD29,"")}
A31: Ela Solutions Kft. | B31: 90ZA-ZK012-06 | C31: nagykulcs - 5mm | E31: 2 | F31: 47.3 | G31: Z410 | I31: 15 | W31: 90ZA-ZK008-06 | AD31: {=_xlfn._xlws.FILTER(Alkatrészek[Termék megnevezés],Alkatrészek[Termék rajzszáma]=AD30,"")}
A32: Ela Solutions Kft. | B32: 90ZA-ZS001-06 | C32: Zsanérbelső | E32: 2 | F32: 15 | G32: Z410 | I32: 15 | W32: 90ZA-ZK009-06 | AD32: {=_xlfn._xlws.FILTER(Alkatrészek[Termék megnevezés],Alkatrészek[Termék rajzszáma]=AD31,"")}
A33: Ela Solutions Kft. | B33: 90ZA-ZS002-06 | C33: Zsanérkülső | E33: 2 | F33: 20.8 | G33: Z410 | I33: 15 | W33: 90ZA-ZK010-06 | AD33: {=_xlfn._xlws.FILTER(Alkatrészek[Termék megnevezés],Alkatrészek[Termék rajzszáma]=AD32,"")}
A34: Ela Solutions Kft. | B34: 90ZA-ZS004-00 | C34: zsanértest | E34: 2 | F34: 70 | G34: Z410 | I34: 15 | W34: 90ZA-ZK011-06 | AD34: {=_xlfn._xlws.FILTER(Alkatrészek[Termék megnevezés],Alkatrészek[Termék rajzszáma]=AD33,"")}
A35: Ela Solutions Kft. | B35: 90ZA-ZS005-06 | C35: zsanértest | E35: 2 | F35: 81.72 | G35: Z410 | I35: 15 | W35: 90ZA-ZK012-06 | AD35: {=_xlfn._xlws.FILTER(Alkatrészek[Termék megnevezés],Alkatrészek[Termék rajzszáma]=AD34,"")}
A36: Ela Solutions Kft. | B36: 90ZA-ZS013-06 | C36: zsanértest | E36: 2 | F36: 52.6 | G36: Z410 | I36: 15 | W36: 90ZA-ZS001-06 | AD36: {=_xlfn._xlws.FILTER(Alkatrészek[Termék megnevezés],Alkatrészek[Termék rajzszáma]=AD35,"")}
A37: Ela Solutions Kft. | B37: 90ZA-ZS016-06 | C37: engusz letörés csiszolása | E37: 1 | F37: 0 | G37: Z410 | I37: 15 | W37: 90ZA-ZS002-06 | AD37: {=_xlfn._xlws.FILTER(Alkatrészek[Termék megnevezés],Alkatrészek[Termék rajzszáma]=AD36,"")}
A38: Ela Solutions Kft. | B38: 90ZA-ZS016-06 | C38: menet készítés | E38: 2 | F38: 0 | G38: Z410 | I38: 15 | W38: 90ZA-ZS004-00 | AD38: {=_xlfn._xlws.FILTER(Alkatrészek[Termék megnevezés],Alkatrészek[Termék rajzszáma]=AD37,"")}
A39: Ela Solutions Kft. | B39: 90ZA-ZS016-06 | C39: öntés, koptatás, mosás | E39: 1 | F39: 0 | G39: Z410 | I39: 15 | W39: 90ZA-ZS005-06 | AD39: {=_xlfn._xlws.FILTER(Alkatrészek[Termék megnevezés],Alkatrészek[Termék rajzszáma]=AD38,"")}
A40: Ela Solutions Kft. | B40: 90ZA-ZS016-06 | C40: zsanérbelső | E40: 1 | F40: 206 | G40: Z410 | I40: 15 | W40: 90ZA-ZS013-06 | AD40: {=_xlfn._xlws.FILTER(Alkatrészek[Termék megnevezés],Alkatrészek[Termék rajzszáma]=AD39,"")}
... A44: Ela Solutions Kft. | B44: 90ZA-ZS019-16 | C44: zsanértest | E44: 2 | F44: 22.6 | G44: Z410 | I44: 15 | W44: 90ZA-ZS016-06 | AD44: {=_xlfn._xlws.FILTER(Alkatrészek[Termék megnevezés],Alkatrészek[Termék rajzszáma]=AD43,"")}
A45: Ela Solutions Kft. | B45: 90ZA-ZS023-06 | C45: Zanér fél | F45: 69.1 | G45: Z410 | I45: 15 | W45: 90ZA-ZS017-06 | AD45: {=_xlfn._xlws.FILTER(Alkatrészek[Termék megnevezés],Alkatrészek[Termék rajzszáma]=AD44,"")}
A46: Ela Solutions Kft. | B46: 91ZA-HT001-00 | C46: betét | E46: 2 | F46: 16.8 | G46: Z410 | I46: 15 | W46: 90ZA-ZS017-06 | AD46: {=_xlfn._xlws.FILTER(Alkatrészek[Termék megnevezés],Alkatrészek[Termék rajzszáma]=AD45,"")}
A47: Ela Solutions Kft. | B47: 91ZA-H0006-06 | C47: zártest | E47: 1 | F47: 300 | G47: Z410 | I47: 15 | W47: 90ZA-ZS017-06 | AD47: {=_xlfn._xlws.FILTER(Alkatrészek[Termék megnevezés],Alkatrészek[Termék rajzszáma]=AD46,"")}
A48: Ela Solutions Kft. | B48: 91ZA-F002-06 | C48: vésznyitó | E48: 1 | F48: 56.1 | G48: Z410 | I48: 15 | W48: 90ZA-ZS019-16 | AD48: {=_xlfn._xlws.FILTER(Alkatrészek[Termék megnevezés],Alkatrészek[Termék rajzszáma]=AD47,"")}
A49: Ela Solutions Kft. | B49: 91ZA-NY003-00 | C49: zárnyelv | E49: 1 | F49: 25.1 | G49: Z410 | I49: 15 | W49: 90ZA-ZS023-06 | AD49: {=_xlfn._xlws.FILTER(Alkatrészek[Termék megnevezés],Alkatrészek[Termék rajzszáma]=AD48,"")}
A50: Ela Solutions Kft. | B50: 99ZA-B001-06 | C50: zárbetét - 6mm 4szög | E50: 2 | F50: 4.5 | G50: Z410 | I50: 15 | W50: 91ZA-HT001-00 | AD50: {=_xlfn._xlws.FILTER(Alkatrészek[Termék megnevezés],Alkatrészek[Termék rajzszáma]=AD49,"")}
A51: Ela Solutions Kft. | B51: 99ZA-H001-06 | C51: Minkels zárház | E51: 2 | F51: 20.7 | G51: Z410 | I51: 15 | W51: 91ZA-H0006-06 | AD51: {=_xlfn._xlws.FILTER(Alkatrészek[Termék megnevezés],Alkatrészek[Termék rajzszáma]=AD50,"")}
A52: Ela Solutions Kft. | B52: 99ZA-NY001-00 | C52: fogasnyelv | E52: 2 | F52: 14.9 | G52: Z410 | I52: 15 | W52: 91ZA-F002-06 | AD52: {=_xlfn._xlws.FILTER(Alkatrészek[Termék megnevezés],Alkatrészek[Termék rajzszáma]=AD51,"")}
A53: Ela Solutions Kft. | B53: 99ZA-ZS001-06 | C53: zsanér | E53: 1 | F53: 100.7 | G53: Z410 | I53: 15 | W53: 91ZA-NY003-00 | AD53: {=_xlfn._xlws.FILTER(Alkatrészek[Termék megnevezés],Alkatrészek[Termék rajzszáma]=AD52,"")}
A54: Ela Solutions Kft. | B54: 90ZA-B0011-06 | F54: 2.89 | G54: Z410 | I54: 15 | W54: 99ZA-B001-06 | AD54: {=_xlfn._xlws.FILTER(Alkatrészek[Termék megnevezés],Alkatrészek[Termék rajzszáma]=AD53,"")}
A55: Fasten Italia S.R.L | B55: corpoP6 nyitó | G55: Z410 | I55: 15 | W55: 99ZA-H001-06 | AD55: {=_xlfn._xlws.FILTER(Alkatrészek[Termék megnevezés],Alkatrészek[Termék rajzszáma]=AD54,"")}
A56: Fasten Italia S.R.L | B56: P6 body | G56: Z410 | I56: 15 | W56: 99ZA-NY001-00 | AD56: {=_xlfn._xlws.FILTER(Alkatrészek[Termék megnevezés],Alkatrészek[Termék rajzszáma]=AD55,"")}
A57: Fasten Italia S.R.L | B57: YKK fogó | G57: Z410 | I57: 15 | W57: 99ZA-ZS001-06 | AD57: {=_xlfn._xlws.FILTER(Alkatrészek[Termék megnevezés],Alkatrészek[Termék rajzszáma]=AD56,"")}
A58: Inter-Metal Recycling Kft. | B58: Forgács Aluminium | C58: VTSZ: 7602 | G58: Forgács | W58: 90ZA-B0011-06 | AD58: {=_xlfn._xlws.FILTER(Alkatrészek[Termék megnevezés],Alkatrészek[Termék rajzszáma]=AD57,"")}
A59: Inter-Metal Recycling Kft. | B59: Forgács Rozsdamentés | C59: VTSZ: 7204 | G59: Forgács
A60: Inter-Metal Recycling Kft. | B60: Forgács Vas | C60: VTSZ: 7204 | G60: Forgács
A61: Inter-Metal Recycling Kft. | B61: Forgács Vegyes | C61: VTSZ: 7204 | G61: Forgács
A62: Inter-Metal Recycling Kft. | B62: Vas lemez hulladék | C62: VTSZ:7204 | G62: Forgács
A63: Inter-Metal Recycling Kft. | B63: Csöpedék - Horgany | C63: VTSZ: 7204 | G63: Forgács
A64: Inter-Metal Recycling Kft. | B64: Réz | C64: VTSZ: 7404 | G64: Forgács
A65: R-Plast Manufacturing Kft | B65: Magasságállító | G65: Műanyag | I65: 15
A66: R-Plast Manufacturing Kft | B66: Szíj rövid | G66: Műanyag | I66: 15
A67: R-Plast Manufacturing Kft | B67: Szíj hosszú | G67: Műanyag | I67: 15
A68: R-Plast Manufacturing Kft | B68: Pánt | G68: Műanyag | I68: 15
A69: R-Plast Manufacturing Kft | B69: Szíj doboz | G69: Műanyag | I69: 15
A70: R-Szerkterv Kft. | B70: M 400-2 | G70: Z410 | I70: 15
A71: R-Szerkterv Kft. | B71: M 400-4 | G71: Z410 | I71: 15
A72: Seidel Gmbh&co Kg | B72: B83 | C72: Zamak Gewicht | D72: 1001948 | E72: 8 | F72: 11.6 | G72: Z410 | I72: 20 | L72: 205x210x215 | M72: 800 | N72: 126
A73: Seidel Gmbh&co Kg | B73: B93 | C73: Zamak Gewicht | D73: 1011968 | E73: 16 | F73: 14 | G73: Z410 | I73: 20 | L73: 205x210x215 | M73: 500 | N73: 120
A74: Seidel Gmbh&co Kg | B74: M66 | C74: Zamak Gewicht | E74: 8 | F74: 34 | G74: Z410 | I74: 20 | L74: 205x210x215 | M74: 300 | N74: 120
A75: Seidel Gmbh&co Kg | B75: M70 | C75: Zamak Gewicht | D75: 1001955 | E75: 8 | F75: 13.8 | G75: Z410 | I75: 20 | L75: 205x210x215 | M75: 750 | N75: 120
A76: Seidel Gmbh&co Kg | B76: M83 | C76: Zamak Gewicht | D76: 1001971 | E76: 4 | F76: 65.3 | G76: Z410 | I76: 20 | L76: 205x210x215 | M76: 150 | N76: 30
A77: Seidel Gmbh&co Kg | B77: MA41 | C77: Zamak Gewicht | D77: 1013800 | E77: 8 | F77: 17 | G77: Z410 | I77: 20 | L77: 205x210x90 | M77: 350 | N77: 72
A78: Seidel Gmbh&co Kg | B78: MA51 | C78: Zamak Gewicht | D78: 1015504 | E78: 4 | F78: 28.52 | G78: Z410 | I78: 20 | L78: 205x210x215 | M78: 350 | N78: 30
A79: Seidel Gmbh&co Kg | B79: MA62 | C79: Zamak Gewicht | D79: 8023754 | E79: 4 | F79: 29.93 | G79: Z410 | I79: 20 | L79: 205x210x215 | M79: 400 | N79: 50
A80: Seidel Gmbh&co Kg | B80: MA66 | C80: Zamak Gewicht | D80: 8024290 | E80: 8 | F80: 10.5 | G80: Z410 | I80: 20 | L80: 205x210x215 | M80: 500 | N80: 90
A81: Seidel Gmbh&co Kg | B81: MB01 | C81: Zamak Gewicht | D81: 8028899 | E81: 4 | F81: 21.43 | G81: Z410 | I81: 20 | L81: 205x210x205 | M81: 500 | N81: 120
A82: Seidel Gmbh&co Kg | B82: MB22 | C82: Zamak Gewicht | E82: 16 | F82: 8 | G82: Z410 | I82: 20 | L82: 205x210x90 | M82: 1000 | N82: 120
A83: Systec Pos-Technology Gmbh | B83: Sperrhacken zn | C83: Euroloc 1 | D83: 37409029 | E83: 6 | F83: 19 | G83: Z410 | I83: 15 | M83: 500 | N83: 120
A84: Systec Pos-Technology Gmbh | B84: Sperrhacken Zn S | C84: Euroloc 1 | D84: 37409028 | E84: 2 | F84: 18.7 | G84: Z410 | I84: 15 | M84: 500 | N84: 120
A85: Systec Pos-Technology Gmbh | B85: Sperrhacken Zn S | C85: Euroloc 2 | E85: 4 | F85: 17.4 | G85: Z410 | I85: 15 | M85: 500 | N85: 120
A86: Systec Pos-Technology Gmbh | B86: Sperrhacken Zn M(E208) | C86: Euroloc 3 | E86: 4 | F86: 18.5 | G86: Z410 | I86: 15 | M86: 500 | N86: 120
A87: Systec Pos-Technology Gmbh | B87: Kamm-125-2 | C87: Smartstop-2 | E87: 6 | F87: 35 | G87: Z410 | I87: 15 | M87: 1200 | N87: 120
A88: Systec Pos-Technology Gmbh | B88: Rasthebel-2 | C88: Smartstop-2 | D88: 31410203 | E88: 6 | F88: 15.03 | G88: Z410 | I88: 15 | M88: 625 | N88: 120
A89: Systec Pos-Technology Gmbh | B89: Sperritzteil-2 | C89: Smartstop-2 | D89: 31410115 | E89: 6 | F89: 67 | G89: Z410 | I89: 15 | M89: 150 | N89: 120
A90: Systec Pos-Technology Gmbh | B90: VARIL/3DURAL2 | E90: 2 | F90: 29.25 | G90: Z410 | I90: 15 | N90: 120
A91: Systec Pos-Technology Gmbh | B91: C3R Flanch | C91: Verdrehsicherung | E91: 2 | F91: 116.27 | G91: Z410 | I91: 15 | K91: 1 menet | M91: 580 | N91: 120
A92: Systec Pos-Technology Gmbh | B92: CVLROH | C92: Verdrehsicherung | D92: 31102077 | E92: 2 | F92: 54.7 | G92: Z410 | I92: 15 | M92: 200 | N92: 120
A93: Systec Pos-Technology Gmbh | B93: W1L-S6 | C93: Verdrehsicherung | D93: 31102015 | E93: 2 | F93: 66 | G93: Z410 | H93: Galvanizálás | I93: 15 | M93: 200 | N93: 120
A94: Systec Pos-Technology Gmbh | B94: W1L-S6 | C94: Verdrehsicherung | D94: 31102006 | E94: 2 | F94: 54.1 | G94: Z410 | H94: Galvanizálás | I94: 15 | M94: 200 | N94: 120
A95: Systec Pos-Technology Gmbh | B95: W1R-S6 | C95: Verdrehsicherung | E95: 2 | F95: 54.1 | G95: Z410 | H95: Galvanizálás | I95: 15 | M95: 200 | N95: 120
A96: Systec Pos-Technology Gmbh | B96: W4L-S6 | C96: Verdrehsicherung | E96: 2 | F96: 54.7 | G96: Z410 | H96: Galvanizálás | I96: 15 | M96: 200 | N96: 120
A97: Arsisco AMO Pack LLC | B97: Sín 5 | C97: 22.07.08-05.01-10 | E97: 4 | F97: 0.2 | G97: Műanyag | I97: 15
A98: Fasten Italia S.R.L | B98: P6 body szerszám | G98: Szerszám
A99: Ligeti Péter | B99: nyersanyag | G99: zamak
A100: Seidel Gmbh&co Kg | B100: MB44 | C100: 80 0230 018 001 01 02 | E100: 10 | F100: 12.07 | G100: zamak

Sheet Céglista
A1: Vevő név | B1: Szállító Nyelve | C1: Város | D1: Irányítószám | E1: Utca, házszám | F1: Ország | G1: Cím | H1: Adószám | I1: Vevő név2
A2: Arsisco AMO Pack LLC | B2: EN | C2: Bishkek | D2: 720040 | E2: Yusup Abdrahmanov street 146 | F2: Kirgizisztán | G2: =CONCATENATE(D2," ",C2,", ",E2) -> 720040 Bishkek, Yusup Abdrahmanov street 146 | H2: 1003202210384 | I2: Arsisco AMO Pack LLC
A3: Ela Solutions Kft. | B3: HU | C3: Törökbálint | D3: 2045 | E3: FSD Park 4 | F3: Magyarország | G3: =CONCATENATE(D3," ",C3,", ",E3) -> 2045 Törökbálint, FSD Park 4 | H3: 12072260-2-13 | I3: Ela Solutions Kft.
A4: Fasten Italia S.R.L | B4: EN | C4: Albaredo Di Vedelago(Tv) | D4: 31030 | E4: Via Dei Piazotti 24 | F4: Olaszország | G4: =CONCATENATE(D4," ",C4,", ",E4) -> 31030 Albaredo Di Vedelago(Tv), Via Dei Piazotti 24 | H4: IT03425940263 | I4: Fasten Italia S.R.L
A5: Ironicon Kft. | B5: HU | C5: Budapest | D5: 1211 | E5: Déli utca 13. | F5: Magyarország | G5: =CONCATENATE(D5," ",C5,", ",E5) -> 1211 Budapest, Déli utca 13. | H5: 14778182-2-43 | I5: Ironicon Kft.
A6: Ligeti Péter | B6: HU | C6: Budapest | D6: 1205 | E6: Határ út 57 | F6: Magyarország | G6: =CONCATENATE(D6," ",C6,", ",E6) -> 1205 Budapest, Határ út 57 | H6: 40307411-2-43 | I6: Ligeti Péter
A7: R-Plast Manufacturing Kft | B7: HU | C7: Mezőkeresztes | D7: 3441 | E7: Mihály utca 142 | F7: Magyarország | G7: =CONCATENATE(D7," ",C7,", ",E7) -> 3441 Mezőkeresztes, Mihály utca 142 | H7: 26670809-2-05 | I7: R-Plast Manufacturing Kft
A8: R-Szerkterv Kft. | B8: HU | C8: Alsónémedi | D8: 2351 | E8: RaktárAD utca D3. | F8: Magyarország | G8: =CONCATENATE(D8," ",C8,", ",E8) -> 2351 Alsónémedi, RaktárAD utca D3. | H8: 14309041-2-41 | I8: R-Szerkterv
A9: Seidel Gmbh&co Kg | B9: EN | C9: Fronhausen | D9: 35112 | E9: Marburger strasse 60. | F9: Germany | G9: =CONCATENATE(D9," ",C9,", ",E9) -> 35112 Fronhausen, Marburger strasse 60. | H9: DE113353335 | I9: Seidel Gmbh&co Kg
A10: Systec Pos-Technology Gmbh | B10: EN | C10: Puchheim | D10: 82178 | E10: Lindberghstrasse 8 | F10: Germany | G10: =CONCATENATE(D10," ",C10,", ",E10) -> 82178 Puchheim, Lindberghstrasse 8 | H10: DE128246029 | I10: Systec Pos-Technology Gmbh
A11: Gramm Technik GmbH | B11: EN | C11: Ditzingen-Heimerdingen | D11: 71254 | E11: Otto-Hahn-StraBe Tor 2 | F11: Germany | G11: =CONCATENATE(D11," ",C11,", ",E11) -> 71254 Ditzingen-Heimerdingen, Otto-Hahn-StraBe Tor 2
A12: Inter-Metal Recycling Kft. | B12: HU | C12: Budapest | D12: 1211 | E12: Budafoki út 5-7. | F12: Magyarország | G12: =CONCATENATE(D12," ",C12,", ",E12) -> 1211 Budapest, Budafoki út 5-7. | H12: 12266355-2-44 | I12: Inter-Metal Kft.
A13: Systec Pos-Technology Gmbh | B13: EN | C13: Puchheim | D13: 82178 | E13: Lindberghstrasse 8 | F13: Germany | G13: 82178 Puchheim, Lindberghstrasse 8 | H13: DE128246029 | I13: Systec Pos-Technology Gmbh

Sheet Szállítólevél
A1: Szállítólevél
A2: Cég | B2: Száma
A3: Ela | B3: 0012
A4: Seidel Gmbh&co Kg | B4: 13
A5: Seidel Gmbh&co Kg | B5: 14
A6: Ela Solutions Kft. | B6: 15
A7: Ela Solutions Kft. | B7: 16
A8: Seidel Gmbh&co Kg | B8: 17
A9: Seidel Gmbh&co Kg | B9: 18
A10: Seidel Gmbh&co Kg | B10: 19
A11: Ela Solutions Kft. | B11: 20
A12: Seidel Gmbh&co Kg | B12: 21
A13: Systec Pos-Technology Gmbh | B13: 22
A14: Seidel Gmbh&co Kg | B14: 23
A15: Seidel Gmbh&co Kg | B15: 24
... A81: Ela Solutions Kft. | B81: 10

Sheet Rendelésszám
A1: Árajánlatszám | B1: Megrednelő Neve | C1: Elkészült | D1: Kiküldve | E1: Megjegyzés | F1: Ideje | G1: Határidő | H1: Megrendelve
A2: M251001 | B2: Systec Pos-Technology Gmbh
A3: M251002 | B3: Seidel Gmbh&co Kg
A4: M251003 | B4: Seidel Gmbh&co Kg
A5: M251004 | B5: Ela Solutions Kft.
A6: M251005 | B6: Ela Solutions Kft.
A7: M251006 | B7: Seidel Gmbh&co Kg
A8: M251007 | B8: Arsisco AMO Pack LLC
A9: M251008 | B9: Ela Solutions Kft.
A10: M251009 | B10: Ela Solutions Kft.
A11: M251010 | B11: Ela Solutions Kft.
A12: M251011 | B12: Ela Solutions Kft.
A13: M251012 | B13: Seidel Gmbh&co Kg
... A72: M251071 | B72: Inter-Metal Recycling Kft.

Sheet CMR
K1: Saját rendelési szám
A2: 1. Feladó (Név, cím, ország), Sender (Name, Address, Country) Magma Kft H-1211 Budapest, Déli utca 13. HU10368152-2-43 | F2: NEMZETKÖZI FUVARLEVÉL
F3: INTERNATIONAL CONSIGNMENT NOTE
F4: This carriage is subject, nothwith- standing any clause to the contrary to the Convention on the Contract for the international Carriage of goods by road (CMR). | I4: A fuvarozásra elétrő megállapodás esetén is a nemzetközi árufuvarozási egyezmény CMR rendelkezései az irányagók
A5: 2. Átvevő (Név, cím, ország) Consignee (Name, Address, Country) | F5: 16. Carrier (Name, Address, Country) Fuvarozó (Név, cím, ország)
A8: 3. Az áru átvételének helye és iőpontja. Place of delivery of the goods | F8: 17 Successive carriers (Name, Address, Country) További fuvarozó (Név, cím, ország)
A9: Place/Ort/helység | B9: Budapest
A10: Country/Land/ország | B10: Hungary
A11: 4. Az áru átvételének helye és időponja Place and date of taking over of the goods
A12: Place/Ort/helység | F12: 18. Carrier's reservations and observations A fuvarozó fenntartásai és bejegyzése
A13: Country/Land/ország
A14: 5. Mellékelt okmány, Documents attached
A15: 6. Marks and Nos Jel és szám | B15: 7. Number of packages Darabszám | C15: 8. Method of packing Csomagolás | F15: 9. Nature of the goods Áru megnevezése | G15: 10. Statistical num. Statisztikai szám | I15: 11. Gross weight kg Bruttósúly i kg | K15: 12. Volume in m3 Térfogat m3
A19: 13. Sender's instructions (Customs and other formalities) Feladó rendelkezései (Vám és egyéb hivatalos kezelés) | F19: 19. To be paied by: Fiezetendő: | G19: Sender Feladő | I19: Currency Pénznem | K19: Consignee Átvevő
F20: Carriage charges /Fuvardíj
F21: Supplem charges Pluszköltség
F22: Other charges Extra / más egyéb költség
F23: Total to be paied Teljes költség
A24: 14. Cash on delivery Visszatérítés
A25: 15. Directions as to payment for carriage Fuvardíjfizetési meghagyások | F25: 20. Special agreements Egyedi megállapodások
A26: 21. Ausgefertigt in Kiállitás helye, | B26: Budapest | D26: am on | H26: 24.Goods received Date Áru átvétele dátum
A27: 22. A feladó aláírása és bélyegzője Signature and stamp of the sender | D27: 23. Fuvaroó aláírása és bélyegzője Signature and stamp of the carrier
H28: Signature and stamp of the consignee Az átvevő aláírása és bélyezője
A29: 25. Vehicle Jármű | B29: Registration number- Kennzeichen- Rendszám

Sheet Raklap
A1: Kaufer : | J1: Absender :
J2: MAGMA KFT
J3: Budapest
J4: Déli u.13.
J5: H - 1211
A6: Order No:
F8: karton | I8: stück/karton
A10: =H8*E8 -> 0 | H10: stück
A12: Nettó gewicht: | K12: Bruttó: | M12: =E12+30 -> 30

Sheet Doboz

Sheet szállító HU
A10: Szállítólevél
A12: Bizonylat sorszáma: | G12: 2026/
A14: Feladó: | E14: Címzett:
A16: Magma Kft
A17: Budapest, Déli u. 13, HU 1211
A19: Adószám: 10368152-2-43
A22: Megrendelés száma | D22: Megrendelés kelte | G22: Fizetés módja | H22: Szállítás dátuma
G23: átutalás
A25: Tétel | B25: Megnevezés | D25: Darab | E25: Nettó súly (kg) | F25: Doboz szám | G25: Raklap szám | H25: Bruttó súly (kg)
B33: Összesítő | E33: =SUM(E26:E32) -> 0 | F33: =SUM(F26:F32) -> 0 | G33: =SUM(G26:G32) -> 0 | H33: =SUM(H26:H32) -> 0
B41: Kiállító | F41: Átvevő

Sheet szállító EN
A10: Delivery Note
A12: Delivery note No: | G12: 2026/
A14: From | E14: To
A16: Magma Kft
A17: Budapest, Déli u. 13, Hungary, H-1211
A19: VAT no.: HU10368152
A22: Order No. | D22: Order Date (DMY) | G22: Payment term | H22: Delivery date (DMY)
G23: bank transfer
A25: Item | B25: Product description | D25: Qty | E25: Net weight (kg) | F25: No. of box | G25: No. Of palets | H25: Gross weight (kg)
B33: Total | E33: =SUM(E26:E32) -> 0 | F33: =SUM(F26:F32) -> 0 | G33: =SUM(G26:G32) -> 0 | H33: =SUM(H26:H32) -> 0
B41: Sender | F41: Reciever

Sheet szállító EN-or
A13: Delivery Note
A15: Delivery note No: | H15: 0021/2023
A17: From | E17: To
A19: Magma Kft | E19: Seidel GMBh
A20: Budapest, Déli u. 13, Hungary, H-1211 | E20: 35112 Fronhausen, Marburger str. 60
A22: VAT no.: HU10368152 | E22: VAT no.: DE113353335
A25: Order No. | C25: Order Date (DMY) | G25: Payment term | H25: Delivery date (DMY)
A26: 4500089126 (POS020) | C26: 2023-01-16 | G26: bank transfer | H26: 2023-08-23
A28: Item | B28: Product description | D28: Qty | E28: Net weight (kg) | F28: No. of box | G28: No. Of palets | H28: Gross weight (kg)
A29: 1 | B29: MA66 Ringgewicht zamak | D29: 250.000 | E29: 2700 | F29: 500 | G29: 4 | H29: 2820
B30: 8024290
B35: Total | E35: =SUM(E29:E34) -> 2700 | F35: =SUM(F29:F34) -> 500 | G35: =SUM(G29:G34) -> 4 | H35: =SUM(H29:H34) -> 2820
B43: Sender | F43: Reciever
F47: Budapest, | H47: =TODAY() -> 2026-03-03

Sheet Etiket - 40db

Sheet 2024 prices
A1: Aktuelle Teilepreise 2024. Q4
A3: Product | B3: Artikel Bezeichnung | C3: Gewicht / g | D3: Abbrand 5 % | E3: MPB kg € | F3: aktueller MP kg € | G3: Grund preis 100 Stück € | H3: Diff. durch MP per kg € | I3: Diff+Ab-brand /kg € | J3: Preis-Diff./ 100 Stück € | K3: Preis-einheit | L3: Aktueller Preis / 100 Stück € | M3: Aktueller Preis / 1 Stück €
A4: B83 | B4: WEIGHT GUCCI 10 B83 | C4: 11.6 | D4: =H4*0.06 -> 0.0282 | E4: 3 | F4: 3.47 | G4: 7.127512 | H4: =F4-E4 -> 0.47 | I4: =H4+D4 -> 0.4982 | J4: =C4*I4/1000*100 -> 0.577912 | K4: 100 | L4: =G4+J4 -> 7.705424 | M4: =L4/100 -> 0.07705424
A5: B93 3 mm | B5: GEWICHT BOSS 13 3MM. | C5: 14 | D5: =H5*0.06 -> 0.0282 | E5: 3 | F5: 3.47 | G5: 6.66884 | H5: =F5-E5 -> 0.47 | I5: =H5+D5 -> 0.4982 | J5: =C5*I5/1000*100 -> 0.69748 | K5: 100 | L5: =G5+J5 -> 7.36632 | M5: =L5/100 -> 0.0736632
A6: M66 | B6: RING ZAMAK 50 ML | C6: 34 | D6: =H6*0.06 -> 0.0282 | E6: 3 | F6: 3.47 | G6: 15.99788 | H6: =F6-E6 -> 0.47 | I6: =H6+D6 -> 0.4982 | J6: =C6*I6/1000*100 -> 1.69388 | K6: 100 | L6: =G6+J6 -> 17.69176 | M6: =L6/100 -> 0.1769176
A7: M70 | B7: RING ZAMAK 15 ML | C7: 13.8 | D7: =H7*0.06 -> 0.0282 | E7: 3 | F7: 3.47 | G7: 8.650316 | H7: =F7-E7 -> 0.47 | I7: =H7+D7 -> 0.4982 | J7: =C7*I7/1000*100 -> 0.687516 | K7: 100 | L7: =G7+J7 -> 9.337832 | M7: =L7/100 -> 0.09337832
A8: M83 | B8: WEIGHT 50 ML | C8: 65.3 | D8: =H8*0.06 -> 0.0282 | E8: 3 | F8: 3.47 | G8: 29.375046 | H8: =F8-E8 -> 0.47 | I8: =H8+D8 -> 0.4982 | J8: =C8*I8/1000*100 -> 3.253246 | K8: 100 | L8: =G8+J8 -> 32.628292 | M8: =L8/100 -> 0.32628292
A9: MA41 | B9: GEWICHT M41 | C9: 17 | D9: =H9*0.06 -> 0.0282 | E9: 3 | F9: 3.47 | G9: 8.87002 | H9: =F9-E9 -> 0.47 | I9: =H9+D9 -> 0.4982 | J9: =C9*I9/1000*100 -> 0.84694 | K9: 101 | L9: =G9+J9 -> 9.71696 | M9: =L9/100 -> 0.0971696
A10: MA51 | B10: RING ZAMAK 15 ML | C10: 28.52 | D10: =H10*0.06 -> 0.0282 | E10: 3 | F10: 3.47 | G10: 15.79 | H10: =F10-E10 -> 0.47 | I10: =H10+D10 -> 0.4982 | J10: =C10*I10/1000*100 -> 1.4208664 | K10: 101 | L10: =G10+J10 -> 17.210866 | M10: =L10/100 -> 0.17210866
A11: MA62 | B11: RING ZAMAK | C11: 29.93 | D11: =H11*0.06 -> 0.0282 | E11: 3 | F11: 3.47 | G11: 15.85 | H11: =F11-E11 -> 0.47 | I11: =H11+D11 -> 0.4982 | J11: =C11*I11/1000*100 -> 1.4911126 | K11: 101 | L11: =G11+J11 -> 17.341113 | M11: =L11/100 -> 0.17341113
A12: MA66 | B12: GEWICHT MA66 | C12: 10.5 | D12: =H12*0.06 -> 0.0282 | E12: 3 | F12: 3.47 | G12: 6.15757 | H12: =F12-E12 -> 0.47 | I12: =H12+D12 -> 0.4982 | J12: =C12*I12/1000*100 -> 0.52311 | K12: 101 | L12: =G12+J12 -> 6.68068 | M12: =L12/100 -> 0.0668068
A13: MB01 | B13: GEWICHT MB01 | C13: 21.43 | D13: =H13*0.06 -> 0.0282 | E13: 3 | F13: 3.47 | G13: 11.729223 | H13: =F13-E13 -> 0.47 | I13: =H13+D13 -> 0.4982 | J13: =C13*I13/1000*100 -> 1.0676426 | K13: 101 | L13: =G13+J13 -> 12.796865 | M13: =L13/100 -> 0.12796865
A14: MB22 | B14: GEWICHT MB22 | C14: 8.3 | D14: =H14*0.06 -> 0.0282 | E14: 3 | F14: 3.47 | G14: 5.15 | H14: =F14-E14 -> 0.47 | I14: =H14+D14 -> 0.4982 | J14: =C14*I14/1000*100 -> 0.413506 | K14: 101 | L14: =G14+J14 -> 5.563506 | M14: =L14/100 -> 0.05563506
A15: Euroloc 1 sperrhacken zn | C15: 19 | D15: 0.097 | E15: 1.53 | F15: 3.47 | G15: 8.54 | H15: 1.94 | I15: 2.037 | J15: 3.8703 | K15: 100 | L15: 12.4103 | M15: 0.124103
A16: Euroloc 1 sperrhacken Zn S | C16: 18.7 | D16: 0.097 | E16: 1.53 | F16: 3.47 | G16: 16.35 | H16: 1.94 | I16: 2.037 | J16: 3.80919 | K16: 100 | L16: 20.15919 | M16: 0.2015919
A17: Euroloc 2 sperrhacken Zn S | C17: 17.4 | D17: 0.097 | E17: 1.53 | F17: 3.47 | G17: 11.15 | H17: 1.94 | I17: 2.037 | J17: 3.54438 | K17: 100 | L17: 14.69438 | M17: 0.1469438
A18: Euroloc 3 sperrhacken Zn M(E208) | C18: 18.5 | D18: 0.097 | E18: 1.53 | F18: 3.47 | G18: 12 | H18: 1.94 | I18: 2.037 | J18: 3.76845 | K18: 101 | L18: 15.76845 | M18: 0.1576845
A19: Smartstop-2 Kamm-125-2 | C19: 35 | D19: 0.097 | E19: 1.53 | F19: 3.47 | G19: 16.3 | H19: 1.94 | I19: 2.037 | J19: 7.1295 | K19: 100 | L19: 23.4295 | M19: 0.234295
A20: Smartstop-2 Rasthebel-2 | C20: 15.03 | D20: 0.097 | E20: 1.53 | F20: 3.47 | G20: 8.72 | H20: 1.94 | I20: 2.037 | J20: 3.061611 | K20: 100 | L20: 11.781611 | M20: 0.11781611
A21: Smartstop-2 Sperritzteil-2 | C21: 67 | D21: 0.097 | E21: 1.53 | F21: 3.47 | G21: 18.8 | H21: 1.94 | I21: 2.037 | J21: 13.6479 | K21: 100 | L21: 32.4479 | M21: 0.324479
A22: VARIL/3DURAL2 | C22: 29.25 | D22: 0.097 | E22: 1.53 | F22: 3.47 | G22: 19.8 | H22: 1.94 | I22: 2.037 | J22: 5.958225 | K22: 100 | L22: 25.758225 | M22: 0.25758225
A23: Verdrehsicherung C3R Flanch | C23: 116.27 | D23: 0.097 | E23: 1.53 | F23: 3.47 | G23: 39.39 | H23: 1.94 | I23: 2.037 | J23: 23.684199 | K23: 100 | L23: 63.074199 | M23: 0.63074199
A24: Verdrehsicherung CVLROH | C24: 54.7 | D24: 0.097 | E24: 1.53 | F24: 3.47 | G24: 25.99 | H24: 1.94 | I24: 2.037 | J24: 11.14239 | K24: 101 | L24: 37.13239 | M24: 0.3713239
A25: Verdrehsicherung W1L-S6 | C25: 54.1 | D25: 0.097 | E25: 1.53 | F25: 3.47 | G25: 36 | H25: 1.94 | I25: 2.037 | J25: 11.02017 | K25: 100 | L25: 47.02017 | M25: 0.4702017
A26: Verdrehsicherung W1R-S6 | C26: 54.1 | D26: 0.097 | E26: 1.53 | F26: 3.47 | G26: 36 | H26: 1.94 | I26: 2.037 | J26: 11.02017 | K26: 100 | L26: 47.02017 | M26: 0.4702017
A27: Verdrehsicherung W4L-S6 | C27: 54.7 | D27: 0.097 | E27: 1.53 | F27: 3.47 | G27: 36 | H27: 1.94 | I27: 2.037 | J27: 11.14239 | K27: 100 | L27: 47.14239 | M27: 0.4714239
A28: 90ZA-AD001-00 | B28: rúdadapter | C28: 21.6 | H28: =F28-C28 -> -21.6 | I28: =H28+D28 -> -21.6 | L28: =G28+J28 -> 0 | M28: 0.226
A29: 90ZA-B001-06 | B29: zárbetét - 3mm | C29: 14.85 | H29: =F29-C29 -> -14.85 | I29: =H29+D29 -> -14.85 | L29: =G29+J29 -> 0 | M29: 0.2089
A30: 90ZA-B003-06 | B30: zárbetét - 5mm | C30: 15.6 | H30: =F30-C30 -> -15.6 | I30: =H30+D30 -> -15.6 | L30: =G30+J30 -> 0 | M30: 0.2109
A31: 90ZA-B004-06 | B31: zárbetét | C31: 8.1 | H31: =F31-C31 -> -8.1 | I31: =H31+D31 -> -8.1 | L31: =G31+J31 -> 0 | M31: 0.1738
A32: 90ZA-B007-04 | B32: zárbetét - 9,5mm 3szög | C32: 12 | H32: =F32-C32 -> -12 | I32: =H32+D32 -> -12 | L32: =G32+J32 -> 0 | M32: 0.1828
A33: 90ZA-B008-04 | C33: 12.5 | H33: =F33-C33 -> -12.5 | I33: =H33+D33 -> -12.5 | L33: =G33+J33 -> 0 | M33: 0.204
A34: 90ZA-B009-04 | B34: Zárbetét 2x4-es sliccel | C34: 17.4 | H34: =F34-C34 -> -17.4 | I34: =H34+D34 -> -17.4 | L34: =G34+J34 -> 0 | M34: 0.216
A35: 90ZA-B010-04 | B35: zárbetét sliccel | C35: 7 | H35: =F35-C35 -> -7 | I35: =H35+D35 -> -7 | L35: =G35+J35 -> 0 | M35: 0.171
A36: 90ZA-B011-06 | B36: zárbetét - 7mm | C36: 11.5 | H36: =F36-C36 -> -11.5 | I36: =H36+D36 -> -11.5 | L36: =G36+J36 -> 0 | M36: 0.169
A37: 90ZA-B012-06 | B37: zárbetét - 8mm | C37: 12.2 | H37: =F37-C37 -> -12.2 | I37: =H37+D37 -> -12.2 | L37: =G37+J37 -> 0 | M37: 0.2028
A38: 90ZA-H001-06 | B38: zárház | C38: 24.5 | H38: =F38-C38 -> -24.5 | I38: =H38+D38 -> -24.5 | L38: =G38+J38 -> 0 | M38: 0.228
A39: 90ZA-H002-06 | B39: zárház | C39: 18.5 | H39: =F39-C39 -> -18.5 | I39: =H39+D39 -> -18.5 | L39: =G39+J39 -> 0 | M39: 0.216
A40: 90ZA-H005-04 | B40: zárház | C40: 8.3 | H40: =F40-C40 -> -8.3 | I40: =H40+D40 -> -8.3 | L40: =G40+J40 -> 0 | M40: 0.18
A41: 90ZA-H020-06 | B41: lakattal zárható zárház | C41: 92.53 | H41: =F41-C41 -> -92.53 | I41: =H41+D41 -> -92.53 | L41: =G41+J41 -> 0 | M41: 0.4128
A42: 90ZA-H021-06 | B42: lakattal zárható zárház | C42: 92.56 | H42: =F42-C42 -> -92.56 | I42: =H42+D42 -> -92.56 | L42: =G42+J42 -> 0 | M42: 0.4128
A43: 90ZA-HT001-00 | B43: anya M22x1,5 | C43: 8.3 | H43: =F43-C43 -> -8.3 | I43: =H43+D43 -> -8.3 | L43: =G43+J43 -> 0 | M43: 0.0784
A44: 90ZA-HT002-00 | B44: anya M16x1 | C44: 2.5 | H44: =F44-C44 -> -2.5 | I44: =H44+D44 -> -2.5 | L44: =G44+J44 -> 0 | M44: 0.064
A45: 90ZA-HT004-00 | C45: 5.2 | H45: =F45-C45 -> -5.2 | I45: =H45+D45 -> -5.2 | L45: =G45+J45 -> 0 | M45: 0.0993
A46: 90ZA-NY001-00 | B46: fogasnyelv | C46: 14.9 | H46: =F46-C46 -> -14.9 | I46: =H46+D46 -> -14.9 | L46: =G46+J46 -> 0 | M46: 0.206
A47: 90ZA-ZK001-06 | B47: kiskulcs 6mm 4szög | C47: 22.34 | H47: =F47-C47 -> -22.34 | I47: =H47+D47 -> -22.34 | L47: =G47+J47 -> 0 | M47: 0.2274
A48: 90ZA-ZK006-06 | B48: kulcs - 8mm | C48: 23.6 | H48: =F48-C48 -> -23.6 | I48: =H48+D48 -> -23.6 | L48: =G48+J48 -> 0 | M48: 0.2298
A49: 90ZA-ZK007-06 | B49: kulcs 10mm 3szög | C49: 25.3 | H49: =F49-C49 -> -25.3 | I49: =H49+D49 -> -25.3 | L49: =G49+J49 -> 0 | M49: 0.2348
A50: 90ZA-ZK008-06 | B50: kiskulcs - 3mm | C50: 22.8 | H50: =F50-C50 -> -22.8 | I50: =H50+D50 -> -22.8 | L50: =G50+J50 -> 0 | M50: 0.2295
A51: 90ZA-ZK009-06 | C51: 21.7 | H51: =F51-C51 -> -21.7 | I51: =H51+D51 -> -21.7 | L51: =G51+J51 -> 0 | M51: 0.2145
A52: 90ZA-ZK010-06 | B52: kereszt kulcs | C52: 60.9 | H52: =F52-C52 -> -60.9 | I52: =H52+D52 -> -60.9 | L52: =G52+J52 -> 0 | M52: 0.4987
A53: 90ZA-ZK011-06 | B53: nagykulcs - 3mm | C53: 47.55 | H53: =F53-C53 -> -47.55 | I53: =H53+D53 -> -47.55 | L53: =G53+J53 -> 0 | M53: 0.2998
A54: 90ZA-ZK012-06 | B54: nagykulcs - 5mm | C54: 47.3 | H54: =F54-C54 -> -47.3 | I54: =H54+D54 -> -47.3 | L54: =G54+J54 -> 0 | M54: 0.3006
A55: 90ZA-ZS001-06 | B55: Zsanérbelső | C55: 15 | H55: =F55-C55 -> -15 | I55: =H55+D55 -> -15 | L55: =G55+J55 -> 0 | M55: 0.2099
A56: 90ZA-ZS002-06 | B56: Zsanérkülső | C56: 20.8 | H56: =F56-C56 -> -20.8 | I56: =H56+D56 -> -20.8 | L56: =G56+J56 -> 0 | M56: 0.2234
A57: 90ZA-ZS004-00 | B57: zsanértest | C57: 70 | H57: =F57-C57 -> -70 | I57: =H57+D57 -> -70 | L57: =G57+J57 -> 0 | M57: 0.3512
A58: 90ZA-ZS005-06 | B58: zsanértest | C58: 81.72 | H58: =F58-C58 -> -81.72 | I58: =H58+D58 -> -81.72 | L58: =G58+J58 -> 0 | M58: 0.4167
A59: 90ZA-ZS013-06 | B59: zsanértest | C59: 52.6 | H59: =F59-C59 -> -52.6 | I59: =H59+D59 -> -52.6 | L59: =G59+J59 -> 0 | M59: 0.317
A60: 90ZA-ZS016-06 | B60: zsanérbelső | C60: 206 | H60: =F60-C60 -> -206 | I60: =H60+D60 -> -206 | L60: =G60+J60 -> 0 | M60: 1.2186918
A61: 90ZA-ZS017-06 | B61: zsanérkülső | C61: 63.4 | H61: =F61-C61 -> -63.4 | I61: =H61+D61 -> -63.4 | L61: =G61+J61 -> 0 | M61: 0.4152
A62: 90ZA-ZS019-16 | B62: zsanértest | C62: 22.6 | H62: =F62-C62 -> -22.6 | I62: =H62+D62 -> -22.6 | L62: =G62+J62 -> 0 | M62: 0.229
A63: 90ZA-ZS023-06 | B63: Zanér fél | C63: 69.1 | H63: =F63-C63 -> -69.1 | I63: =H63+D63 -> -69.1 | L63: =G63+J63 -> 0 | M63: 0.389
A64: 91Za-F002-06 | C64: 56 | H64: =F64-C64 -> -56 | I64: =H64+D64 -> -56 | L64: =G64+J64 -> 0 | M64: 0.41
A65: 91ZA-H006 | C65: 300 | H65: =F65-C65 -> -300 | I65: =H65+D65 -> -300 | L65: =G65+J65 -> 0 | M65: 1.134
A66: 91ZA-HT001-00 | B66: betét | C66: 16.8 | H66: =F66-C66 -> -16.8 | I66: =H66+D66 -> -16.8 | L66: =G66+J66 -> 0 | M66: 0.2148
A67: 91ZA-NY003 | C67: 25 | H67: =F67-C67 -> -25 | I67: =H67+D67 -> -25 | L67: =G67+J67 -> 0 | M67: 0.36
A68: 99ZA-B001-06 | B68: zárbetét - 6mm 4szög | C68: 4.5 | H68: =F68-C68 -> -4.5 | I68: =H68+D68 -> -4.5 | L68: =G68+J68 -> 0 | M68: 0.168
A69: 99ZA-H001-06 | B69: Minkels zárház | C69: 20.7 | H69: =F69-C69 -> -20.7 | I69: =H69+D69 -> -20.7 | L69: =G69+J69 -> 0 | M69: 0.2276
A70: 99ZA-NY001-00 | B70: fogasnyelv | C70: 14.9 | H70: =F70-C70 -> -14.9 | I70: =H70+D70 -> -14.9 | L70: =G70+J70 -> 0 | M70: 0.1995
A71: 99ZA-ZS001-06 | B71: zsanér | C71: 100 | H71: =F71-C71 -> -100 | I71: =H71+D71 -> -100 | L71: =G71+J71 -> 0 | M71: 0.6068

Sheet Raktár 2025
A1: Cég | B1: Öntvény neve | C1: súly (g) | D1: súly (kg) | E1: db | F1: össz súly (kg) | G1: zamak beszerzési ár/kg | H1: total EUR | I1: total HUF (390) | J1: Induló darabszám
A2: Seidel | B2: B83 | C2: 11.6 | D2: =C2/1000 -> 0.0116 | E2: =SUM(J2:Q2) -> 18400 | F2: =E2*D2 -> 213.44 | G2: 3.21 | H2: =G2*F2 -> 685.1424 | I2: =H2*$K$1 -> 0 | J2: 18400
A3: Seidel | B3: B93 3 mm | C3: 14 | D3: =C3/1000 -> 0.014 | E3: =SUM(J3:Q3) -> 162000 | F3: =E3*D3 -> 2268 | G3: 3.21 | H3: =G3*F3 -> 7280.28 | I3: =H3*$K$1 -> 0 | J3: 162000
A4: Seidel | B4: M66 | C4: 34 | D4: =C4/1000 -> 0.034 | E4: =SUM(J4:Q4) -> 399 | F4: =E4*D4 -> 13.566 | G4: 3.21 | H4: =G4*F4 -> 43.54686 | I4: =H4*$K$1 -> 0 | J4: 399
A5: Seidel | B5: M70 | C5: 13.8 | D5: =C5/1000 -> 0.0138 | E5: =SUM(J5:Q5) -> 24750 | F5: =E5*D5 -> 341.55 | G5: 3.21 | H5: =G5*F5 -> 1096.3755 | I5: =H5*$K$1 -> 0 | J5: 24750
A6: Seidel | B6: M83 | C6: 65.3 | D6: =C6/1000 -> 0.0653 | E6: =SUM(J6:Q6) -> 8550 | F6: =E6*D6 -> 558.315 | G6: 3.21 | H6: =G6*F6 -> 1792.1911 | I6: =H6*$K$1 -> 0 | J6: 8550
A7: Seidel | B7: MA41 | C7: 17 | D7: =C7/1000 -> 0.017 | E7: =SUM(J7:Q7) -> 1221 | F7: =E7*D7 -> 20.757 | G7: 3.21 | H7: =G7*F7 -> 66.62997 | I7: =H7*$K$1 -> 0 | J7: 1221
A8: Seidel | B8: MA51 | C8: 28.52 | D8: =C8/1000 -> 0.02852 | E8: =SUM(J8:Q8) -> 26600 | F8: =E8*D8 -> 758.632 | G8: 3.21 | H8: =G8*F8 -> 2435.2087 | I8: =H8*$K$1 -> 0 | J8: 26600
A9: Seidel | B9: MA62 | C9: 29.93 | D9: =C9/1000 -> 0.02993 | E9: =SUM(J9:Q9) -> 6400 | F9: =E9*D9 -> 191.552 | G9: 3.21 | H9: =G9*F9 -> 614.88192 | I9: =H9*$K$1 -> 0 | J9: 6400
A10: Seidel | B10: MA66 | C10: 10.5 | D10: =C10/1000 -> 0.0105 | E10: =SUM(J10:Q10) -> 11000 | F10: =E10*D10 -> 115.5 | G10: 3.21 | H10: =G10*F10 -> 370.755 | I10: =H10*$K$1 -> 0 | J10: 11000
A11: Seidel | B11: MB01 | C11: 21.43 | D11: =C11/1000 -> 0.02143 | E11: =SUM(J11:Q11) -> 4500 | F11: =E11*D11 -> 96.435 | G11: 3.21 | H11: =G11*F11 -> 309.55635 | I11: =H11*$K$1 -> 0 | J11: 4500
A12: Seidel | B12: MB22 | D12: =C12/1000 -> 0 | E12: =SUM(J12:Q12) -> 28469 | F12: =E12*D12 -> 0 | G12: 3.21 | H12: =G12*F12 -> 0 | I12: =H12*$K$1 -> 0 | J12: 28469
A13: Ela | B13: 90ZA-AD001-00 / rúdadapter | C13: 21.6 | D13: =C13/1000 -> 0.0216 | E13: =SUM(J13:Q13) -> 4720 | F13: =E13*D13 -> 101.952 | G13: 3.21 | H13: =G13*F13 -> 327.26592 | I13: =H13*$K$1 -> 0 | J13: 4720
A14: Ela | B14: 90ZA-B001-06 / zárbetét - 3mm | C14: 14.85 | D14: =C14/1000 -> 0.01485 | E14: =SUM(J14:Q14) -> 3616 | F14: =E14*D14 -> 53.6976 | G14: 3.21 | H14: =G14*F14 -> 172.3693 | I14: =H14*$K$1 -> 0 | J14: 3616
A15: Ela | B15: 90ZA-B003-06 / zárbetét - 5mm | C15: 15.6 | D15: =C15/1000 -> 0.0156 | E15: =SUM(J15:Q15) -> 3000 | F15: =E15*D15 -> 46.8 | G15: 3.21 | H15: =G15*F15 -> 150.228 | I15: =H15*$K$1 -> 0 | J15: 3000
A16: Ela | B16: 90ZA-B004-06 / zárbetét | C16: 8.1 | D16: =C16/1000 -> 0.0081 | E16: =SUM(J16:Q16) -> 495 | F16: =E16*D16 -> 4.0095 | G16: 3.21 | H16: =G16*F16 -> 12.870495 | I16: =H16*$K$1 -> 0 | J16: 495
A17: Ela | B17: 90ZA-B007-04 / zárbetét - 9,5mm 3szög | C17: 12 | D17: =C17/1000 -> 0.012 | E17: =SUM(J17:Q17) -> 2698 | F17: =E17*D17 -> 32.376 | G17: 3.21 | H17: =G17*F17 -> 103.92696 | I17: =H17*$K$1 -> 0 | J17: 2698
A18: Ela | B18: 90ZA-B008-04 | C18: 12.5 | D18: =C18/1000 -> 0.0125 | E18: =SUM(J18:Q18) -> 3622 | F18: =E18*D18 -> 45.275 | G18: 3.21 | H18: =G18*F18 -> 145.33275 | I18: =H18*$K$1 -> 0 | J18: 3622
A19: Ela | B19: 90ZA-B009-04 / Zárbetét 2x4-es sliccel | C19: 17.4 | D19: =C19/1000 -> 0.0174 | E19: =SUM(J19:Q19) -> 430 | F19: =E19*D19 -> 7.482 | G19: 3.21 | H19: =G19*F19 -> 24.01722 | I19: =H19*$K$1 -> 0 | J19: 430
A20: Ela | B20: 90ZA-B010-04 / zárbetét sliccel | C20: 7 | D20: =C20/1000 -> 0.007 | E20: =SUM(J20:Q20) -> 539 | F20: =E20*D20 -> 3.773 | G20: 3.21 | H20: =G20*F20 -> 12.11133 | I20: =H20*$K$1 -> 0 | J20: 539
A21: Ela | B21: 90ZA-B012-06 / zárbetét - 8mm | C21: 12.2 | D21: =C21/1000 -> 0.0122 | E21: =SUM(J21:Q21) -> 2210 | F21: =E21*D21 -> 26.962 | G21: 3.21 | H21: =G21*F21 -> 86.54802 | I21: =H21*$K$1 -> 0 | J21: 2210
A22: Ela | B22: 90ZA-H001-06 / zárház | C22: 24.5 | D22: =C22/1000 -> 0.0245 | E22: =SUM(J22:Q22) -> 2622 | F22: =E22*D22 -> 64.239 | G22: 3.21 | H22: =G22*F22 -> 206.20719 | I22: =H22*$K$1 -> 0 | J22: 0 | K22: 3622 | L22: -1000
A23: Ela | B23: 90ZA-H002-06 / zárház | C23: 18.5 | D23: =C23/1000 -> 0.0185 | E23: =SUM(J23:Q23) -> 0 | F23: =E23*D23 -> 0 | G23: 3.21 | H23: =G23*F23 -> 0 | I23: =H23*$K$1 -> 0 | J23: 0
A24: Ela | B24: 90ZA-H005-04 / zárház | C24: 8.3 | D24: =C24/1000 -> 0.0083 | E24: =SUM(J24:Q24) -> 2288 | F24: =E24*D24 -> 18.9904 | G24: 3.21 | H24: =G24*F24 -> 60.959184 | I24: =H24*$K$1 -> 0 | J24: 2288
A25: Ela | B25: 90ZA-H020-06 / lakattal zárható zárház | C25: 92.53 | D25: =C25/1000 -> 0.09253 | E25: =SUM(J25:Q25) -> 3846 | F25: =E25*D25 -> 355.87038 | G25: 3.21 | H25: =G25*F25 -> 1142.3439 | I25: =H25*$K$1 -> 0 | J25: 3846
A26: Ela | B26: 90ZA-H021-06 / lakattal zárható zárház | C26: 92.56 | D26: =C26/1000 -> 0.09256 | E26: =SUM(J26:Q26) -> 1164 | F26: =E26*D26 -> 107.73984 | G26: 3.21 | H26: =G26*F26 -> 345.84489 | I26: =H26*$K$1 -> 0 | J26: 1364 | K26: -200
A27: Ela | B27: 90ZA-HT001-00 / anya M22x1,5 | C27: 8.3 | D27: =C27/1000 -> 0.0083 | E27: =SUM(J27:Q27) -> 0 | F27: =E27*D27 -> 0 | G27: 3.21 | H27: =G27*F27 -> 0 | I27: =H27*$K$1 -> 0 | J27: 0
A28: Ela | B28: 90ZA-HT001-00 / anya M22x1,5 (30.000 db) | C28: 8.3 | D28: =C28/1000 -> 0.0083 | E28: =SUM(J28:Q28) -> 0 | F28: =E28*D28 -> 0 | G28: 3.21 | H28: =G28*F28 -> 0 | I28: =H28*$K$1 -> 0 | J28: 0
A29: Ela | B29: 90ZA-HT002-00 / anya M16x1 | C29: 2.5 | D29: =C29/1000 -> 0.0025 | E29: =SUM(J29:Q29) -> 0 | F29: =E29*D29 -> 0 | G29: 3.21 | H29: =G29*F29 -> 0 | I29: =H29*$K$1 -> 0 | J29: 0
A30: Ela | B30: 90ZA-HT004-00 | C30: 5.2 | D30: =C30/1000 -> 0.0052 | E30: =SUM(J30:Q30) -> 2600 | F30: =E30*D30 -> 13.52 | G30: 3.21 | H30: =G30*F30 -> 43.3992 | I30: =H30*$K$1 -> 0 | J30: 2600
A31: Ela | B31: 90ZA-NY001-00 / fogasnyelv | C31: 14.9 | D31: =C31/1000 -> 0.0149 | E31: =SUM(J31:Q31) -> 255 | F31: =E31*D31 -> 3.7995 | G31: 3.21 | H31: =G31*F31 -> 12.196395 | I31: =H31*$K$1 -> 0 | J31: 255
A32: Ela | B32: 90ZA-ZK001-06 / kiskulcs 6mm 4szög | C32: 22.34 | D32: =C32/1000 -> 0.02234 | E32: =SUM(J32:Q32) -> 25316 | F32: =E32*D32 -> 565.55944 | G32: 3.21 | H32: =G32*F32 -> 1815.4458 | I32: =H32*$K$1 -> 0 | J32: 30316 | K32: -500 | L32: -2000 | M32: -2000 | N32: -500
A33: Ela | B33: 90ZA-ZK006-06 / kulcs - 8mm | C33: 23.6 | D33: =C33/1000 -> 0.0236 | E33: =SUM(J33:Q33) -> 4905 | F33: =E33*D33 -> 115.758 | G33: 3.21 | H33: =G33*F33 -> 371.58318 | I33: =H33*$K$1 -> 0 | J33: 4905
A34: Ela | B34: 90ZA-ZK007-06 kulcs 10mm 3szög | C34: 25.3 | D34: =C34/1000 -> 0.0253 | E34: =SUM(J34:Q34) -> 1345 | F34: =E34*D34 -> 34.0285 | G34: 3.21 | H34: =G34*F34 -> 109.23149 | I34: =H34*$K$1 -> 0 | J34: 1645 | K34: -300
A35: Ela | B35: 90ZA-ZK008-06 / kiskulcs - 3mm | C35: 22.8 | D35: =C35/1000 -> 0.0228 | E35: =SUM(J35:Q35) -> 0 | F35: =E35*D35 -> 0 | G35: 3.21 | H35: =G35*F35 -> 0 | I35: =H35*$K$1 -> 0 | J35: 0
A36: Ela | B36: 90ZA-ZK009-06 | C36: 21.7 | D36: =C36/1000 -> 0.0217 | E36: =SUM(J36:Q36) -> 1587 | F36: =E36*D36 -> 34.4379 | G36: 3.21 | H36: =G36*F36 -> 110.54566 | I36: =H36*$K$1 -> 0 | J36: 1587
A37: Ela | B37: 90ZA-ZK010-06 / kereszt kulcs | C37: 60.9 | D37: =C37/1000 -> 0.0609 | E37: =SUM(J37:Q37) -> 0 | F37: =E37*D37 -> 0 | G37: 3.21 | H37: =G37*F37 -> 0 | I37: =H37*$K$1 -> 0 | J37: 0
A38: Ela | B38: 90ZA-ZK011-06 / nagykulcs - 3mm | C38: 47.55 | D38: =C38/1000 -> 0.04755 | E38: =SUM(J38:Q38) -> 220 | F38: =E38*D38 -> 10.461 | G38: 3.21 | H38: =G38*F38 -> 33.57981 | I38: =H38*$K$1 -> 0 | J38: 7720 | K38: -1000 | L38: -1500 | M38: -1000 | N38: -1000 | O38: -1000 | P38: -1000 | Q38: -1000
A39: Ela | B39: 90ZA-ZK012-06 / nagykulcs - 5mm | C39: 47.3 | D39: =C39/1000 -> 0.0473 | E39: =SUM(J39:Q39) -> 0 | F39: =E39*D39 -> 0 | G39: 3.21 | H39: =G39*F39 -> 0 | I39: =H39*$K$1 -> 0 | J39: 0
A40: Ela | B40: 90ZA-ZS001-06 / Zsanérbelső | C40: 15 | D40: =C40/1000 -> 0.015 | E40: =SUM(J40:Q40) -> 7914 | F40: =E40*D40 -> 118.71 | G40: 3.21 | H40: =G40*F40 -> 381.0591 | I40: =H40*$K$1 -> 0 | J40: 8914 | K40: -1000
A41: Ela | B41: 90ZA-ZS002-06 / Zsanérkülső | C41: 20.8 | D41: =C41/1000 -> 0.0208 | E41: =SUM(J41:Q41) -> 6251 | F41: =E41*D41 -> 130.0208 | G41: 3.21 | H41: =G41*F41 -> 417.36677 | I41: =H41*$K$1 -> 0 | J41: 7251 | K41: -1000
A42: Ela | B42: 90ZA-ZS004-00 zsanértest | C42: 70 | D42: =C42/1000 -> 0.07 | E42: =SUM(J42:Q42) -> 0 | F42: =E42*D42 -> 0 | G42: 3.21 | H42: =G42*F42 -> 0 | I42: =H42*$K$1 -> 0 | J42: 750 | K42: -200 | L42: -550
A43: Ela | B43: 90ZA-ZS005-06 / zsanértest | C43: 81.72 | D43: =C43/1000 -> 0.08172 | E43: =SUM(J43:Q43) -> 1170 | F43: =E43*D43 -> 95.6124 | G43: 3.21 | H43: =G43*F43 -> 306.9158 | I43: =H43*$K$1 -> 0 | J43: 1170
A44: Ela | B44: 90ZA-ZS013-06 / zsanértest | C44: 52.6 | D44: =C44/1000 -> 0.0526 | E44: =SUM(J44:Q44) -> 2170 | F44: =E44*D44 -> 114.142 | G44: 3.21 | H44: =G44*F44 -> 366.39582 | I44: =H44*$K$1 -> 0 | J44: 2170
A45: Ela | B45: 90ZA-ZS016-06 / zsanérbelső | C45: 206 | D45: =C45/1000 -> 0.206 | E45: =SUM(J45:Q45) -> 230 | F45: =E45*D45 -> 47.38 | G45: 3.21 | H45: =G45*F45 -> 152.0898 | I45: =H45*$K$1 -> 0 | J45: 230
A46: Ela | B46: 90ZA-ZS017-06 / zsanérkülső | C46: 63.4 | D46: =C46/1000 -> 0.0634 | E46: =SUM(J46:Q46) -> 700 | F46: =E46*D46 -> 44.38 | G46: 3.21 | H46: =G46*F46 -> 142.4598 | I46: =H46*$K$1 -> 0 | J46: 700
A47: Ela | B47: 90ZA-ZS019-16 / zsanértest | C47: 22.6 | D47: =C47/1000 -> 0.0226 | E47: =SUM(J47:Q47) -> 6710 | F47: =E47*D47 -> 151.646 | G47: 3.21 | H47: =G47*F47 -> 486.78366 | I47: =H47*$K$1 -> 0 | J47: 6710
A48: Ela | B48: 90ZA-ZS023-06 Zanér fél | C48: 69.1 | D48: =C48/1000 -> 0.0691 | E48: =SUM(J48:Q48) -> 4139 | F48: =E48*D48 -> 286.0049 | G48: 3.21 | H48: =G48*F48 -> 918.07573 | I48: =H48*$K$1 -> 0 | J48: 4139
A49: Ela | B49: 91ZA-HT001-00 / betét | C49: 16.8 | D49: =C49/1000 -> 0.0168 | E49: =SUM(J49:Q49) -> 0 | F49: =E49*D49 -> 0 | G49: 3.21 | H49: =G49*F49 -> 0 | I49: =H49*$K$1 -> 0 | J49: 0
A50: Ela | B50: 99ZA-B001-06 / zárbetét - 6mm 4szög | C50: 4.5 | D50: =C50/1000 -> 0.0045 | E50: =SUM(J50:Q50) -> 0 | F50: =E50*D50 -> 0 | G50: 3.21 | H50: =G50*F50 -> 0 | I50: =H50*$K$1 -> 0 | J50: 0
A51: Ela | B51: 99ZA-H001-06 / Minkels zárház | C51: 20.7 | D51: =C51/1000 -> 0.0207 | E51: =SUM(J51:Q51) -> 2989 | F51: =E51*D51 -> 61.8723 | G51: 3.21 | H51: =G51*F51 -> 198.61008 | I51: =H51*$K$1 -> 0 | J51: 2989
A52: Ela | B52: 99ZA-NY001-00 / fogasnyelv | C52: 14.9 | D52: =C52/1000 -> 0.0149 | E52: =SUM(J52:Q52) -> 255 | F52: =E52*D52 -> 3.7995 | G52: 3.21 | H52: =G52*F52 -> 12.196395 | I52: =H52*$K$1 -> 0 | J52: 255
A53: Ela | B53: 99ZA-ZS001-06 / zsanér | C53: 100.7 | D53: =C53/1000 -> 0.1007 | E53: =SUM(J53:Q53) -> 0 | F53: =E53*D53 -> 0 | G53: 3.21 | H53: =G53*F53 -> 0 | I53: =H53*$K$1 -> 0 | J53: 0
A54: Ela | B54: 90ZA-ZK008-06 / kiskulcs - COALSA | E54: =SUM(J54:Q54) -> 2700 | F54: =E54*D54 -> 0 | G54: 3.21 | H54: =G54*F54 -> 0 | I54: =H54*$K$1 -> 0 | J54: 4700 | K54: -2000
A55: Ela | B55: 90ZA-ZK011-06 / nagykulcs - COALSA | E55: =SUM(J55:Q55) -> 2600 | F55: =E55*D55 -> 0 | G55: 3.21 | H55: =G55*F55 -> 0 | I55: =H55*$K$1 -> 0 | J55: 2600
A56: Ela | B56: 90ZA-ZK011-06 / nagykulcs - Rosenberg | E56: =SUM(J56:Q56) -> 800 | F56: =E56*D56 -> 0 | G56: 3.21 | H56: =G56*F56 -> 0 | I56: =H56*$K$1 -> 0 | J56: 800
A57: Ela | B57: 90ZA-ZK010-06 / kereszt kulcs - EMKA | E57: =SUM(J57:Q57) -> 470 | F57: =E57*D57 -> 0 | G57: 3.21 | H57: =G57*F57 -> 0 | I57: =H57*$K$1 -> 0 | J57: 470
A58: Ela | B58: 90ZA-ZK005-06 | E58: =SUM(J58:Q58) -> 1530 | F58: =E58*D58 -> 0 | G58: 3.21 | H58: =G58*F58 -> 0 | I58: =H58*$K$1 -> 0 | J58: 1530
A59: Ela | B59: 90ZA-ZS06-06 | E59: =SUM(J59:Q59) -> 2500 | F59: =E59*D59 -> 0 | G59: 3.21 | H59: =G59*F59 -> 0 | I59: =H59*$K$1 -> 0 | J59: 2500
A60: Ela | B60: 90ZA-H019-06 | E60: =SUM(J60:Q60) -> 1046 | F60: =E60*D60 -> 0 | G60: 3.21 | H60: =G60*F60 -> 0 | I60: =H60*$K$1 -> 0 | J60: 1046
A61: Ela | B61: 90ZA-B011 | E61: =SUM(J61:Q61) -> 0 | F61: =E61*D61 -> 0 | G61: 3.21 | H61: =G61*F61 -> 0 | I61: =H61*$K$1 -> 0 | J61: 992 | K61: -150 | L61: -842
A62: Ela | B62: 90ZA-F002 | E62: =SUM(J62:Q62) -> 0 | F62: =E62*D62 -> 0 | G62: 3.21 | H62: =G62*F62 -> 0 | I62: =H62*$K$1 -> 0 | J62: 248 | K62: -248
A63: Ela | B63: 90ZA-ZK012- ROSENBERG | E63: =SUM(J63:Q63) -> 47 | F63: =E63*D63 -> 0 | G63: 3.21 | H63: =G63*F63 -> 0 | I63: =H63*$K$1 -> 0 | J63: 47
A64: Ela | B64: 90ZA-B026 | E64: =SUM(J64:Q64) -> 617 | F64: =E64*D64 -> 0 | G64: 3.21 | H64: =G64*F64 -> 0 | I64: =H64*$K$1 -> 0 | J64: 617
A65: Ela | B65: 90ZA-ZS001-06 / Zsanérbelső | E65: =SUM(J65:Q65) -> 41 | F65: =E65*D65 -> 0 | G65: 3.21 | H65: =G65*F65 -> 0 | I65: =H65*$K$1 -> 0 | J65: 41
A66: Ela | B66: 90ZA-ZK06-06 ELA | E66: =SUM(J66:Q66) -> 920 | F66: =E66*D66 -> 0 | G66: 3.21 | H66: =G66*F66 -> 0 | I66: =H66*$K$1 -> 0 | J66: 920
A67: Ela | B67: 90ZA-H006-06 | E67: =SUM(J67:Q67) -> 13 | F67: =E67*D67 -> 0 | G67: 3.21 | H67: =G67*F67 -> 0 | I67: =H67*$K$1 -> 0 | J67: 213 | K67: -200
A68: Systec | B68: Euroloc 1 sperrhacken zn + sorjázás | C68: 19 | D68: =C68/1000 -> 0.019 | E68: =SUM(J68:Q68) -> 3948 | F68: =E68*D68 -> 75.012 | G68: 3.21 | H68: =G68*F68 -> 240.78852 | I68: =H68*$K$1 -> 0 | J68: 3948
A69: Systec | B69: Euroloc 1 sperrhacken Zn S + sorjázás | C69: 18.7 | D69: =C69/1000 -> 0.0187 | E69: =SUM(J69:Q69) -> 26678 | F69: =E69*D69 -> 498.8786 | G69: 3.21 | H69: =G69*F69 -> 1601.4003 | I69: =H69*$K$1 -> 0 | J69: 26678
A70: Systec | B70: Euroloc 2 sperrhacken Zn S + sorjázás | C70: 17.4 | D70: =C70/1000 -> 0.0174 | E70: =SUM(J70:Q70) -> 6500 | F70: =E70*D70 -> 113.1 | G70: 3.21 | H70: =G70*F70 -> 363.051 | I70: =H70*$K$1 -> 0 | J70: 6500
A71: Systec | B71: Euroloc 3 sperrhacken Zn M(E208) + sorjázás | C71: 18.5 | D71: =C71/1000 -> 0.0185 | E71: =SUM(J71:Q71) -> 3267 | F71: =E71*D71 -> 60.4395 | G71: 3.21 | H71: =G71*F71 -> 194.01079 | I71: =H71*$K$1 -> 0 | J71: 3267
A72: Systec | B72: Smartstop-2 Kamm-125-2 | C72: 35 | D72: =C72/1000 -> 0.035 | E72: =SUM(J72:Q72) -> 0 | F72: =E72*D72 -> 0 | G72: 3.21 | H72: =G72*F72 -> 0 | I72: =H72*$K$1 -> 0 | J72: 0
A73: Systec | B73: Smartstop-2 Rasthebel-2 | C73: 15.03 | D73: =C73/1000 -> 0.01503 | E73: =SUM(J73:Q73) -> 0 | F73: =E73*D73 -> 0 | G73: 3.21 | H73: =G73*F73 -> 0 | I73: =H73*$K$1 -> 0 | J73: 0
A74: Systec | B74: Smartstop-2 Sperritzteil-2 | C74: 67 | D74: =C74/1000 -> 0.067 | E74: =SUM(J74:Q74) -> 2550 | F74: =E74*D74 -> 170.85 | G74: 3.21 | H74: =G74*F74 -> 548.4285 | I74: =H74*$K$1 -> 0 | J74: 2550
A75: Systec | B75: VARIL/3DURAL2 | C75: 29.25 | D75: =C75/1000 -> 0.02925 | E75: =SUM(J75:Q75) -> 4800 | F75: =E75*D75 -> 140.4 | G75: 3.21 | H75: =G75*F75 -> 450.684 | I75: =H75*$K$1 -> 0 | J75: 4800
A76: Systec | B76: Verdrehsicherung C3R Flanch + 1 menet | C76: 116.27 | D76: =C76/1000 -> 0.11627 | E76: =SUM(J76:Q76) -> 500 | F76: =E76*D76 -> 58.135 | G76: 3.21 | H76: =G76*F76 -> 186.61335 | I76: =H76*$K$1 -> 0 | J76: 500
A77: Systec | B77: Verdrehsicherung CVLROH | C77: 54.7 | D77: =C77/1000 -> 0.0547 | E77: =SUM(J77:Q77) -> 1700 | F77: =E77*D77 -> 92.99 | G77: 3.21 | H77: =G77*F77 -> 298.4979 | I77: =H77*$K$1 -> 0 | J77: 1700
A78: Systec | B78: Verdrehsicherung W1L-S6 | C78: 66 | D78: =C78/1000 -> 0.066 | E78: =SUM(J78:Q78) -> 1349 | F78: =E78*D78 -> 89.034 | G78: 3.21 | H78: =G78*F78 -> 285.79914 | I78: =H78*$K$1 -> 0 | J78: 1349
A79: Systec | B79: Verdrehsicherung W1L-S6 | C79: 54.1 | D79: =C79/1000 -> 0.0541 | E79: =SUM(J79:Q79) -> 0 | F79: =E79*D79 -> 0 | G79: 3.21 | H79: =G79*F79 -> 0 | I79: =H79*$K$1 -> 0 | J79: 0
... A81: Systec | B81: Verdrehsicherung W4L-S6 | C81: 54.7 | D81: =C81/1000 -> 0.0547 | E81: =SUM(J81:Q81) -> 400 | F81: =E81*D81 -> 21.88 | G81: 3.21 | H81: =G81*F81 -> 70.2348 | I81: =H81*$K$1 -> 0 | J81: 400
A82: Systec | B82: Verdrehsicherung W6L | D82: =C82/1000 -> 0 | E82: =SUM(J82:Q82) -> 1200 | F82: =E82*D82 -> 0 | G82: 3.21 | H82: =G82*F82 -> 0 | I82: =H82*$K$1 -> 0 | J82: 1200
A83: Fasten | B83: P6 | D83: =C83/1000 -> 0 | E83: =SUM(J83:Q83) -> 5324 | F83: =E83*D83 -> 0 | G83: 3.21 | H83: =G83*F83 -> 0 | I83: =H83*$K$1 -> 0 | J83: 5324
A84: Fasten | B84: Ykk fogó | D84: =C84/1000 -> 0 | E84: =SUM(J84:Q84) -> 4000 | F84: =E84*D84 -> 0 | G84: 3.21 | H84: =G84*F84 -> 0 | I84: =H84*$K$1 -> 0 | J84: 4000
A85: MAGMA | B85: MAG1 | E85: =SUM(J85:Q85) -> 2950 | J85: 2950
A86: MAGMA | B86: MAG2 | E86: =SUM(J86:Q86) -> 3720 | J86: 3720
A87: MAGMA | B87: MAG3 | E87: =SUM(J87:Q87) -> 2990 | J87: 2990
A88: CÍMER | B88: KATASZTRÓFA CÍMER | E88: =SUM(J88:Q88) -> 2000 | J88: 2000
B89: ZÁRNYELV | E89: =SUM(J89:Q89) -> 817 | J89: 817
B90: ZÁRNYELV | E90: =SUM(J90:Q90) -> 1880 | J90: 2080 | K90: -200
A91: Nyersanyag | E91: =SUM(J91:Q91) -> 18000 | F91: =E91*D91 -> 0 | J91: 15000 | K91: -9000 | L91: 12000
